Workbook
Name \0: #REF!
Name \0: #REF!
Name \0: #REF!
Name \0: #REF!
Name \0: #REF!
Name _FY2018: #REF!
Name _FY2018: #REF!
Name _FY2018: #REF!
Name _FY2018: #REF!
Name _FY2018: #REF!
Name _FY2019: #REF!
Name _FY2019: #REF!
Name _FY2019: #REF!
Name _FY2019: #REF!
Name _FY2019: #REF!
Name _FY2020: #REF!
Name _FY2020: #REF!
Name _FY2020: #REF!
Name _FY2020: #REF!
Name _FY2020: #REF!
Name _FY2021: #REF!
Name Adjustment: '[1]Do not Edit'!$D$4:$D$6
Name Admin: '[2]MC Assumptions'!$B$5
Name alldata: #REF!
Name alldata: #REF!
Name alldata: #REF!
Name alldata: #REF!
Name alldata: #REF!
Name alled: #REF!
Name alled: #REF!
Name alled: #REF!
Name alled: #REF!
Name alled: #REF!
Name allstem: #REF!
Name allstem: #REF!
Name allstem: #REF!
Name allstem: #REF!
Name allstem: #REF!
Name HARDCOPY: #REF!
Name Modifier: '[1]Do not Edit'!$J$4:$J$46
Name Modifier1: '[1]Do not Edit'!$G$4:$G$5
Name Modifier3: '[1]Do not Edit'!$I$4:$I$8
Name OffsetValue: #REF!
Name OffsetValue: #REF!
Name OffsetValue: #REF!
Name OffsetValue: #REF!
Name OffsetValue: #REF!
Name OffsetValue: #REF!
Name Place: '[3]Do not Edit'!$J$2:$J$9
Name PremiumTax: '[2]MC Assumptions'!$B$4
Name RiskMargin: '[2]MC Assumptions'!$B$3
Name sheet1: #REF!
Name sheet1: #REF!
Name sheet1: #REF!
Name sheet1: #REF!
Name sheet1: #REF!
Name UP: #REF!
Name UP: #REF!
Name UP: #REF!
Name UPDATE: #REF!

Sheet Fiscal by Program
A1: Updated on 2/7/2025
A2: Texas Health and Human Services Commission
A3: Provider Finance Department
A4: PERSONAL ATTENDANT BASE WAGE FISCAL ESTIMATE CALCULATOR
A5: 2026-2027 BIENNIUM
A7: Target Hourly Wage | B7: 10.6 | D7: Change the value in the highlighted cell to the left to see how service rates at a particular target wage affect fiscal outcomes.
A8: Target Payroll Taxes and Benefits Percentage for All Community Care Attendants | B8: 0.1075 | D8: Change the value in the highlighted cell to the left to see how service rates at a particular target wage affect fiscal outcomes.
A9: Target Payroll Taxes and Benefits Percentage for All Facility Based Attendants | B9: 0.1075 | D9: Change the value in the highlighted cell to the left to see how service rates at a particular target wage affect fiscal outcomes.
J10: 3-3-3-3
A11: (!) Table below will show Fiscal Impact based on the selected Target Hourly Wage set above. A change in the total estimated fiscal impact depends on which services are impacted.
A13: Notes:
A14: * Intervener services under DBMD are excluded from the fiscal impact because the services are not listed within Title 1 of the Texas Administrative Code §355.7051, Base Wage for a Personal Attendant. The Intervener services are provided by interpreters and not personal attendants.
A15: ** ICF/IID is not considered a community attendant service. It is added to the bottom of this table for informational purposes and is not included in the Total Community Attendant Fiscal Impact. A total fiscal impact that includes the community attendant and ICF/IID fiscal estimate is provided at the bottom of the this document.
A17: Service Category | B17: SFY 2026 | E17: SFY 2027 | H17: Estimated Attendant Hours
B18: AF | C18: FF | D18: GR | E18: AF | F18: FF | G18: GR | H18: SFY 2026 | I18: SFY 2027
A19: COMMUNITY ATTENDANT TOTAL FISCAL IMPACT | B19: =B117 -> 0 | C19: =C117 -> 0 | D19: =D117 -> 0 | E19: =E117 -> 0 | F19: =F117 -> 0 | G19: =G117 -> 0 | H19: =H117 -> 0 | I19: =I117 -> 0
A20: Fiscal Impact breakdown by Program and Service Category is below as follows:
A21: Community Living Assistance & Support Services Waiver (CLASS)
A22: Employment Assistance and Supported Employment | B22: =SUMIFS('Fiscal Calculation'!AO:AO,'Fiscal Calculation'!J:J,'Fiscal by Program'!$J22) -> 0 | C22: =B22-D22 -> 0 | D22: =SUMIFS('Fiscal Calculation'!AP:AP,'Fiscal Calculation'!J:J,'Fiscal by Program'!$J22) -> 0 | E22: =SUMIFS('Fiscal Calculation'!AQ:AQ,'Fiscal Calculation'!J:J,'Fiscal by Program'!$J22) -> 0 | F22: =E22-G22 -> 0 | G22: =SUMIFS('Fiscal Calculation'!AR:AR,'Fiscal Calculation'!J:J,'Fiscal by Program'!$J22) -> 0 | H22: =IF(B22>0,SUMIFS('Fiscal Calculation'!AM:AM,'Fiscal Calculation'!J:J,'Fiscal by Program'!$J22),"") | I22: =IF(E22>0,SUMIFS('Fiscal Calculation'!AN:AN,'Fiscal Calculation'!J:J,'Fiscal by Program'!$J22),"") | J22: {=INDEX('Rate Table Service Desc XWalk'!F:F,MATCH(1,(A22='Rate Table Service Desc XWalk'!B:B)*("CLASS"='Rate Table Service Desc XWalk'!A:A),0))} -> 1-1-23
A23: Habilitation | B23: =SUMIFS('Fiscal Calculation'!AO:AO,'Fiscal Calculation'!J:J,'Fiscal by Program'!$J23) -> 0 | C23: =B23-D23 -> 0 | D23: =SUMIFS('Fiscal Calculation'!AP:AP,'Fiscal Calculation'!J:J,'Fiscal by Program'!$J23) -> 0 | E23: =SUMIFS('Fiscal Calculation'!AQ:AQ,'Fiscal Calculation'!J:J,'Fiscal by Program'!$J23) -> 0 | F23: =E23-G23 -> 0 | G23: =SUMIFS('Fiscal Calculation'!AR:AR,'Fiscal Calculation'!J:J,'Fiscal by Program'!$J23) -> 0 | H23: =IF(B23>0,SUMIFS('Fiscal Calculation'!AM:AM,'Fiscal Calculation'!J:J,'Fiscal by Program'!$J23),"") | I23: =IF(E23>0,SUMIFS('Fiscal Calculation'!AN:AN,'Fiscal Calculation'!J:J,'Fiscal by Program'!$J23),"") | J23: {=INDEX('Rate Table Service Desc XWalk'!F:F,MATCH(1,(A23='Rate Table Service Desc XWalk'!B:B)*("CLASS"='Rate Table Service Desc XWalk'!A:A),0))} -> 1-1-26
A24: In Home Respite | B24: =SUMIFS('Fiscal Calculation'!AO:AO,'Fiscal Calculation'!J:J,'Fiscal by Program'!$J24) -> 0 | C24: =B24-D24 -> 0 | D24: =SUMIFS('Fiscal Calculation'!AP:AP,'Fiscal Calculation'!J:J,'Fiscal by Program'!$J24) -> 0 | E24: =SUMIFS('Fiscal Calculation'!AQ:AQ,'Fiscal Calculation'!J:J,'Fiscal by Program'!$J24) -> 0 | F24: =E24-G24 -> 0 | G24: =SUMIFS('Fiscal Calculation'!AR:AR,'Fiscal Calculation'!J:J,'Fiscal by Program'!$J24) -> 0 | H24: =IF(B24>0,SUMIFS('Fiscal Calculation'!AM:AM,'Fiscal Calculation'!J:J,'Fiscal by Program'!$J24),"") | I24: =IF(E24>0,SUMIFS('Fiscal Calculation'!AN:AN,'Fiscal Calculation'!J:J,'Fiscal by Program'!$J24),"") | J24: {=INDEX('Rate Table Service Desc XWalk'!F:F,MATCH(1,(A24='Rate Table Service Desc XWalk'!B:B)*("CLASS"='Rate Table Service Desc XWalk'!A:A),0))} -> 1-1-55
A25: PAS/HAB (CFC) | B25: =SUMIFS('Fiscal Calculation'!AO:AO,'Fiscal Calculation'!J:J,'Fiscal by Program'!$J25) -> 0 | C25: =B25-D25 -> 0 | D25: =SUMIFS('Fiscal Calculation'!AP:AP,'Fiscal Calculation'!J:J,'Fiscal by Program'!$J25) -> 0 | E25: =SUMIFS('Fiscal Calculation'!AQ:AQ,'Fiscal Calculation'!J:J,'Fiscal by Program'!$J25) -> 0 | F25: =E25-G25 -> 0 | G25: =SUMIFS('Fiscal Calculation'!AR:AR,'Fiscal Calculation'!J:J,'Fiscal by Program'!$J25) -> 0 | H25: =IF(B25>0,SUMIFS('Fiscal Calculation'!AM:AM,'Fiscal Calculation'!J:J,'Fiscal by Program'!$J25),"") | I25: =IF(E25>0,SUMIFS('Fiscal Calculation'!AN:AN,'Fiscal Calculation'!J:J,'Fiscal by Program'!$J25),"") | J25: {=INDEX('Rate Table Service Desc XWalk'!F:F,MATCH(1,(A25='Rate Table Service Desc XWalk'!B:B)*("CLASS"='Rate Table Service Desc XWalk'!A:A),0))} -> 1-1-78
A26: CDS Employment Assistance and Supported Employment | B26: =SUMIFS('Fiscal Calculation'!AO:AO,'Fiscal Calculation'!J:J,'Fiscal by Program'!$J26) -> 0 | C26: =B26-D26 -> 0 | D26: =SUMIFS('Fiscal Calculation'!AP:AP,'Fiscal Calculation'!J:J,'Fiscal by Program'!$J26) -> 0 | E26: =SUMIFS('Fiscal Calculation'!AQ:AQ,'Fiscal Calculation'!J:J,'Fiscal by Program'!$J26) -> 0 | F26: =E26-G26 -> 0 | G26: =SUMIFS('Fiscal Calculation'!AR:AR,'Fiscal Calculation'!J:J,'Fiscal by Program'!$J26) -> 0 | H26: =IF(B26>0,SUMIFS('Fiscal Calculation'!AM:AM,'Fiscal Calculation'!J:J,'Fiscal by Program'!$J26),"") | I26: =IF(E26>0,SUMIFS('Fiscal Calculation'!AN:AN,'Fiscal Calculation'!J:J,'Fiscal by Program'!$J26),"") | J26: {=INDEX('Rate Table Service Desc XWalk'!F:F,MATCH(1,(A26='Rate Table Service Desc XWalk'!B:B)*("CLASS"='Rate Table Service Desc XWalk'!A:A),0))} -> 1-5-121
A27: CDS Habilitation | B27: =SUMIFS('Fiscal Calculation'!AO:AO,'Fiscal Calculation'!J:J,'Fiscal by Program'!$J27) -> 0 | C27: =B27-D27 -> 0 | D27: =SUMIFS('Fiscal Calculation'!AP:AP,'Fiscal Calculation'!J:J,'Fiscal by Program'!$J27) -> 0 | E27: =SUMIFS('Fiscal Calculation'!AQ:AQ,'Fiscal Calculation'!J:J,'Fiscal by Program'!$J27) -> 0 | F27: =E27-G27 -> 0 | G27: =SUMIFS('Fiscal Calculation'!AR:AR,'Fiscal Calculation'!J:J,'Fiscal by Program'!$J27) -> 0 | H27: =IF(B27>0,SUMIFS('Fiscal Calculation'!AM:AM,'Fiscal Calculation'!J:J,'Fiscal by Program'!$J27),"") | I27: =IF(E27>0,SUMIFS('Fiscal Calculation'!AN:AN,'Fiscal Calculation'!J:J,'Fiscal by Program'!$J27),"") | J27: {=INDEX('Rate Table Service Desc XWalk'!F:F,MATCH(1,(A27='Rate Table Service Desc XWalk'!B:B)*("CLASS"='Rate Table Service Desc XWalk'!A:A),0))} -> 1-5-122
A28: CDS In Home Respite | B28: =SUMIFS('Fiscal Calculation'!AO:AO,'Fiscal Calculation'!J:J,'Fiscal by Program'!$J28) -> 0 | C28: =B28-D28 -> 0 | D28: =SUMIFS('Fiscal Calculation'!AP:AP,'Fiscal Calculation'!J:J,'Fiscal by Program'!$J28) -> 0 | E28: =SUMIFS('Fiscal Calculation'!AQ:AQ,'Fiscal Calculation'!J:J,'Fiscal by Program'!$J28) -> 0 | F28: =E28-G28 -> 0 | G28: =SUMIFS('Fiscal Calculation'!AR:AR,'Fiscal Calculation'!J:J,'Fiscal by Program'!$J28) -> 0 | H28: =IF(B28>0,SUMIFS('Fiscal Calculation'!AM:AM,'Fiscal Calculation'!J:J,'Fiscal by Program'!$J28),"") | I28: =IF(E28>0,SUMIFS('Fiscal Calculation'!AN:AN,'Fiscal Calculation'!J:J,'Fiscal by Program'!$J28),"") | J28: {=INDEX('Rate Table Service Desc XWalk'!F:F,MATCH(1,(A28='Rate Table Service Desc XWalk'!B:B)*("CLASS"='Rate Table Service Desc XWalk'!A:A),0))} -> 1-5-136
A29: CDS PAS/HAB (CFC) | B29: =SUMIFS('Fiscal Calculation'!AO:AO,'Fiscal Calculation'!J:J,'Fiscal by Program'!$J29) -> 0 | C29: =B29-D29 -> 0 | D29: =SUMIFS('Fiscal Calculation'!AP:AP,'Fiscal Calculation'!J:J,'Fiscal by Program'!$J29) -> 0 | E29: =SUMIFS('Fiscal Calculation'!AQ:AQ,'Fiscal Calculation'!J:J,'Fiscal by Program'!$J29) -> 0 | F29: =E29-G29 -> 0 | G29: =SUMIFS('Fiscal Calculation'!AR:AR,'Fiscal Calculation'!J:J,'Fiscal by Program'!$J29) -> 0 | H29: =IF(B29>0,SUMIFS('Fiscal Calculation'!AM:AM,'Fiscal Calculation'!J:J,'Fiscal by Program'!$J29),"") | I29: =IF(E29>0,SUMIFS('Fiscal Calculation'!AN:AN,'Fiscal Calculation'!J:J,'Fiscal by Program'!$J29),"") | J29: {=INDEX('Rate Table Service Desc XWalk'!F:F,MATCH(1,(A29='Rate Table Service Desc XWalk'!B:B)*("CLASS"='Rate Table Service Desc XWalk'!A:A),0))} -> 1-5-142
A30: CLASS Subtotal | B30: =SUM(B22:B29) -> 0 | C30: =SUM(C22:C29) -> 0 | D30: =SUM(D22:D29) -> 0 | E30: =SUM(E22:E29) -> 0 | F30: =SUM(F22:F29) -> 0 | G30: =SUM(G22:G29) -> 0 | H30: =SUM(H22:H29) -> 0 | I30: =SUM(I22:I29) -> 0
A31: Deaf-blind Multiple Disabilities Waiver (DBMD) *
A32: Assisted Living | B32: =SUMIFS('Fiscal Calculation'!AO:AO,'Fiscal Calculation'!J:J,'Fiscal by Program'!$J32) -> 0 | C32: =B32-D32 -> 0 | D32: =SUMIFS('Fiscal Calculation'!AP:AP,'Fiscal Calculation'!J:J,'Fiscal by Program'!$J32) -> 0 | E32: =SUMIFS('Fiscal Calculation'!AQ:AQ,'Fiscal Calculation'!J:J,'Fiscal by Program'!$J32) -> 0 | F32: =E32-G32 -> 0 | G32: =SUMIFS('Fiscal Calculation'!AR:AR,'Fiscal Calculation'!J:J,'Fiscal by Program'!$J32) -> 0 | H32: =IF(B32>0,SUMIFS('Fiscal Calculation'!AM:AM,'Fiscal Calculation'!J:J,'Fiscal by Program'!$J32),"") | I32: =IF(E32>0,SUMIFS('Fiscal Calculation'!AN:AN,'Fiscal Calculation'!J:J,'Fiscal by Program'!$J32),"") | J32: {=INDEX('Rate Table Service Desc XWalk'!F:F,MATCH(1,(A32='Rate Table Service Desc XWalk'!B:B)*("DBMD"='Rate Table Service Desc XWalk'!A:A),0))} -> 2-1-3
A33: Chore Services | B33: =SUMIFS('Fiscal Calculation'!AO:AO,'Fiscal Calculation'!J:J,'Fiscal by Program'!$J33) -> 0 | C33: =B33-D33 -> 0 | D33: =SUMIFS('Fiscal Calculation'!AP:AP,'Fiscal Calculation'!J:J,'Fiscal by Program'!$J33) -> 0 | E33: =SUMIFS('Fiscal Calculation'!AQ:AQ,'Fiscal Calculation'!J:J,'Fiscal by Program'!$J33) -> 0 | F33: =E33-G33 -> 0 | G33: =SUMIFS('Fiscal Calculation'!AR:AR,'Fiscal Calculation'!J:J,'Fiscal by Program'!$J33) -> 0 | H33: =IF(B33>0,SUMIFS('Fiscal Calculation'!AM:AM,'Fiscal Calculation'!J:J,'Fiscal by Program'!$J33),"") | I33: =IF(E33>0,SUMIFS('Fiscal Calculation'!AN:AN,'Fiscal Calculation'!J:J,'Fiscal by Program'!$J33),"") | J33: {=INDEX('Rate Table Service Desc XWalk'!F:F,MATCH(1,(A33='Rate Table Service Desc XWalk'!B:B)*("DBMD"='Rate Table Service Desc XWalk'!A:A),0))} -> 2-1-12
A34: Individualized Skills and Socialization - On-Site and Off-Site | B34: =SUMIFS('Fiscal Calculation'!AO:AO,'Fiscal Calculation'!J:J,'Fiscal by Program'!$J34) -> 0 | C34: =B34-D34 -> 0 | D34: =SUMIFS('Fiscal Calculation'!AP:AP,'Fiscal Calculation'!J:J,'Fiscal by Program'!$J34) -> 0 | E34: =SUMIFS('Fiscal Calculation'!AQ:AQ,'Fiscal Calculation'!J:J,'Fiscal by Program'!$J34) -> 0 | F34: =E34-G34 -> 0 | G34: =SUMIFS('Fiscal Calculation'!AR:AR,'Fiscal Calculation'!J:J,'Fiscal by Program'!$J34) -> 0 | H34: =IF(B34>0,SUMIFS('Fiscal Calculation'!AM:AM,'Fiscal Calculation'!J:J,'Fiscal by Program'!$J34),"") | I34: =IF(E34>0,SUMIFS('Fiscal Calculation'!AN:AN,'Fiscal Calculation'!J:J,'Fiscal by Program'!$J34),"") | J34: {=INDEX('Rate Table Service Desc XWalk'!F:F,MATCH(1,(A34='Rate Table Service Desc XWalk'!B:B)*("DBMD"='Rate Table Service Desc XWalk'!A:A),0))} -> 2-1-44
A35: In Home Respite | B35: =SUMIFS('Fiscal Calculation'!AO:AO,'Fiscal Calculation'!J:J,'Fiscal by Program'!$J35) -> 0 | C35: =B35-D35 -> 0 | D35: =SUMIFS('Fiscal Calculation'!AP:AP,'Fiscal Calculation'!J:J,'Fiscal by Program'!$J35) -> 0 | E35: =SUMIFS('Fiscal Calculation'!AQ:AQ,'Fiscal Calculation'!J:J,'Fiscal by Program'!$J35) -> 0 | F35: =E35-G35 -> 0 | G35: =SUMIFS('Fiscal Calculation'!AR:AR,'Fiscal Calculation'!J:J,'Fiscal by Program'!$J35) -> 0 | H35: =IF(B35>0,SUMIFS('Fiscal Calculation'!AM:AM,'Fiscal Calculation'!J:J,'Fiscal by Program'!$J35),"") | I35: =IF(E35>0,SUMIFS('Fiscal Calculation'!AN:AN,'Fiscal Calculation'!J:J,'Fiscal by Program'!$J35),"") | J35: {=INDEX('Rate Table Service Desc XWalk'!F:F,MATCH(1,(A35='Rate Table Service Desc XWalk'!B:B)*("DBMD"='Rate Table Service Desc XWalk'!A:A),0))} -> 2-1-55
A36: PAS/HAB (CFC) and Transportation | B36: =SUMIFS('Fiscal Calculation'!AO:AO,'Fiscal Calculation'!J:J,'Fiscal by Program'!$J36) -> 0 | C36: =B36-D36 -> 0 | D36: =SUMIFS('Fiscal Calculation'!AP:AP,'Fiscal Calculation'!J:J,'Fiscal by Program'!$J36) -> 0 | E36: =SUMIFS('Fiscal Calculation'!AQ:AQ,'Fiscal Calculation'!J:J,'Fiscal by Program'!$J36) -> 0 | F36: =E36-G36 -> 0 | G36: =SUMIFS('Fiscal Calculation'!AR:AR,'Fiscal Calculation'!J:J,'Fiscal by Program'!$J36) -> 0 | H36: =IF(B36>0,SUMIFS('Fiscal Calculation'!AM:AM,'Fiscal Calculation'!J:J,'Fiscal by Program'!$J36),"") | I36: =IF(E36>0,SUMIFS('Fiscal Calculation'!AN:AN,'Fiscal Calculation'!J:J,'Fiscal by Program'!$J36),"") | J36: {=INDEX('Rate Table Service Desc XWalk'!F:F,MATCH(1,(A36='Rate Table Service Desc XWalk'!B:B)*("DBMD"='Rate Table Service Desc XWalk'!A:A),0))} -> 2-1-79
A37: CDS In Home Respite | B37: =SUMIFS('Fiscal Calculation'!AO:AO,'Fiscal Calculation'!J:J,'Fiscal by Program'!$J37) -> 0 | C37: =B37-D37 -> 0 | D37: =SUMIFS('Fiscal Calculation'!AP:AP,'Fiscal Calculation'!J:J,'Fiscal by Program'!$J37) -> 0 | E37: =SUMIFS('Fiscal Calculation'!AQ:AQ,'Fiscal Calculation'!J:J,'Fiscal by Program'!$J37) -> 0 | F37: =E37-G37 -> 0 | G37: =SUMIFS('Fiscal Calculation'!AR:AR,'Fiscal Calculation'!J:J,'Fiscal by Program'!$J37) -> 0 | H37: =IF(B37>0,SUMIFS('Fiscal Calculation'!AM:AM,'Fiscal Calculation'!J:J,'Fiscal by Program'!$J37),"") | I37: =IF(E37>0,SUMIFS('Fiscal Calculation'!AN:AN,'Fiscal Calculation'!J:J,'Fiscal by Program'!$J37),"") | J37: {=INDEX('Rate Table Service Desc XWalk'!F:F,MATCH(1,(A37='Rate Table Service Desc XWalk'!B:B)*("DBMD"='Rate Table Service Desc XWalk'!A:A),0))} -> 2-5-136
A38: CDS PAS/HAB (CFC) and Transportation | B38: =SUMIFS('Fiscal Calculation'!AO:AO,'Fiscal Calculation'!J:J,'Fiscal by Program'!$J38) -> 0 | C38: =B38-D38 -> 0 | D38: =SUMIFS('Fiscal Calculation'!AP:AP,'Fiscal Calculation'!J:J,'Fiscal by Program'!$J38) -> 0 | E38: =SUMIFS('Fiscal Calculation'!AQ:AQ,'Fiscal Calculation'!J:J,'Fiscal by Program'!$J38) -> 0 | F38: =E38-G38 -> 0 | G38: =SUMIFS('Fiscal Calculation'!AR:AR,'Fiscal Calculation'!J:J,'Fiscal by Program'!$J38) -> 0 | H38: =IF(B38>0,SUMIFS('Fiscal Calculation'!AM:AM,'Fiscal Calculation'!J:J,'Fiscal by Program'!$J38),"") | I38: =IF(E38>0,SUMIFS('Fiscal Calculation'!AN:AN,'Fiscal Calculation'!J:J,'Fiscal by Program'!$J38),"") | J38: {=INDEX('Rate Table Service Desc XWalk'!F:F,MATCH(1,(A38='Rate Table Service Desc XWalk'!B:B)*("DBMD"='Rate Table Service Desc XWalk'!A:A),0))} -> 2-5-143
A39: DBMD Subtotal | B39: =SUM(B32:B38) -> 0 | C39: =SUM(C32:C38) -> 0 | D39: =SUM(D32:D38) -> 0 | E39: =SUM(E32:E38) -> 0 | F39: =SUM(F32:F38) -> 0 | G39: =SUM(G32:G38) -> 0 | H39: =SUM(H32:H38) -> 0 | I39: =SUM(I32:I38) -> 0
A40: Home and Community-Based Services Waiver (HCS)
A41: Employment Assistance and Supported Employment | B41: =SUMIFS('Fiscal Calculation'!AO:AO,'Fiscal Calculation'!J:J,'Fiscal by Program'!$J41) -> 0 | C41: =B41-D41 -> 0 | D41: =SUMIFS('Fiscal Calculation'!AP:AP,'Fiscal Calculation'!J:J,'Fiscal by Program'!$J41) -> 0 | E41: =SUMIFS('Fiscal Calculation'!AQ:AQ,'Fiscal Calculation'!J:J,'Fiscal by Program'!$J41) -> 0 | F41: =E41-G41 -> 0 | G41: =SUMIFS('Fiscal Calculation'!AR:AR,'Fiscal Calculation'!J:J,'Fiscal by Program'!$J41) -> 0 | H41: =IF(B41>0,SUMIFS('Fiscal Calculation'!AM:AM,'Fiscal Calculation'!J:J,'Fiscal by Program'!$J41),"") | I41: =IF(E41>0,SUMIFS('Fiscal Calculation'!AN:AN,'Fiscal Calculation'!J:J,'Fiscal by Program'!$J41),"") | J41: {=INDEX('Rate Table Service Desc XWalk'!F:F,MATCH(1,(A41='Rate Table Service Desc XWalk'!B:B)*("HCS"='Rate Table Service Desc XWalk'!A:A),0))} -> 3-1-23
A42: In Home Respite | B42: =SUMIFS('Fiscal Calculation'!AO:AO,'Fiscal Calculation'!J:J,'Fiscal by Program'!$J42) -> 0 | C42: =B42-D42 -> 0 | D42: =SUMIFS('Fiscal Calculation'!AP:AP,'Fiscal Calculation'!J:J,'Fiscal by Program'!$J42) -> 0 | E42: =SUMIFS('Fiscal Calculation'!AQ:AQ,'Fiscal Calculation'!J:J,'Fiscal by Program'!$J42) -> 0 | F42: =E42-G42 -> 0 | G42: =SUMIFS('Fiscal Calculation'!AR:AR,'Fiscal Calculation'!J:J,'Fiscal by Program'!$J42) -> 0 | H42: =IF(B42>0,SUMIFS('Fiscal Calculation'!AM:AM,'Fiscal Calculation'!J:J,'Fiscal by Program'!$J42),"") | I42: =IF(E42>0,SUMIFS('Fiscal Calculation'!AN:AN,'Fiscal Calculation'!J:J,'Fiscal by Program'!$J42),"") | J42: {=INDEX('Rate Table Service Desc XWalk'!F:F,MATCH(1,(A42='Rate Table Service Desc XWalk'!B:B)*("HCS"='Rate Table Service Desc XWalk'!A:A),0))} -> 3-1-39
A43: Individualized Skills and Socialization | B43: =SUMIFS('Fiscal Calculation'!AO:AO,'Fiscal Calculation'!J:J,'Fiscal by Program'!$J43) -> 0 | C43: =B43-D43 -> 0 | D43: =SUMIFS('Fiscal Calculation'!AP:AP,'Fiscal Calculation'!J:J,'Fiscal by Program'!$J43) -> 0 | E43: =SUMIFS('Fiscal Calculation'!AQ:AQ,'Fiscal Calculation'!J:J,'Fiscal by Program'!$J43) -> 0 | F43: =E43-G43 -> 0 | G43: =SUMIFS('Fiscal Calculation'!AR:AR,'Fiscal Calculation'!J:J,'Fiscal by Program'!$J43) -> 0 | H43: =IF(B43>0,SUMIFS('Fiscal Calculation'!AM:AM,'Fiscal Calculation'!J:J,'Fiscal by Program'!$J43),"") | I43: =IF(E43>0,SUMIFS('Fiscal Calculation'!AN:AN,'Fiscal Calculation'!J:J,'Fiscal by Program'!$J43),"") | J43: {=INDEX('Rate Table Service Desc XWalk'!F:F,MATCH(1,(A43='Rate Table Service Desc XWalk'!B:B)*("HCS"='Rate Table Service Desc XWalk'!A:A),0))} -> 3-1-45
A44: Out-of-Home Respite | B44: =SUMIFS('Fiscal Calculation'!AO:AO,'Fiscal Calculation'!J:J,'Fiscal by Program'!$J44) -> 0 | C44: =B44-D44 -> 0 | D44: =SUMIFS('Fiscal Calculation'!AP:AP,'Fiscal Calculation'!J:J,'Fiscal by Program'!$J44) -> 0 | E44: =SUMIFS('Fiscal Calculation'!AQ:AQ,'Fiscal Calculation'!J:J,'Fiscal by Program'!$J44) -> 0 | F44: =E44-G44 -> 0 | G44: =SUMIFS('Fiscal Calculation'!AR:AR,'Fiscal Calculation'!J:J,'Fiscal by Program'!$J44) -> 0 | H44: =IF(B44>0,SUMIFS('Fiscal Calculation'!AM:AM,'Fiscal Calculation'!J:J,'Fiscal by Program'!$J44),"") | I44: =IF(E44>0,SUMIFS('Fiscal Calculation'!AN:AN,'Fiscal Calculation'!J:J,'Fiscal by Program'!$J44),"") | J44: {=INDEX('Rate Table Service Desc XWalk'!F:F,MATCH(1,(A44='Rate Table Service Desc XWalk'!B:B)*("HCS"='Rate Table Service Desc XWalk'!A:A),0))} -> 3-1-74
A45: PAS/HAB (CFC) and Transportation | B45: =SUMIFS('Fiscal Calculation'!AO:AO,'Fiscal Calculation'!J:J,'Fiscal by Program'!$J45) -> 0 | C45: =B45-D45 -> 0 | D45: =SUMIFS('Fiscal Calculation'!AP:AP,'Fiscal Calculation'!J:J,'Fiscal by Program'!$J45) -> 0 | E45: =SUMIFS('Fiscal Calculation'!AQ:AQ,'Fiscal Calculation'!J:J,'Fiscal by Program'!$J45) -> 0 | F45: =E45-G45 -> 0 | G45: =SUMIFS('Fiscal Calculation'!AR:AR,'Fiscal Calculation'!J:J,'Fiscal by Program'!$J45) -> 0 | H45: =IF(B45>0,SUMIFS('Fiscal Calculation'!AM:AM,'Fiscal Calculation'!J:J,'Fiscal by Program'!$J45),"") | I45: =IF(E45>0,SUMIFS('Fiscal Calculation'!AN:AN,'Fiscal Calculation'!J:J,'Fiscal by Program'!$J45),"") | J45: {=INDEX('Rate Table Service Desc XWalk'!F:F,MATCH(1,(A45='Rate Table Service Desc XWalk'!B:B)*("HCS"='Rate Table Service Desc XWalk'!A:A),0))} -> 3-1-79
A46: Supervised Living and Residential Support Services | B46: =SUMIFS('Fiscal Calculation'!AO:AO,'Fiscal Calculation'!J:J,'Fiscal by Program'!$J46) -> 0 | C46: =B46-D46 -> 0 | D46: =SUMIFS('Fiscal Calculation'!AP:AP,'Fiscal Calculation'!J:J,'Fiscal by Program'!$J46) -> 0 | E46: =SUMIFS('Fiscal Calculation'!AQ:AQ,'Fiscal Calculation'!J:J,'Fiscal by Program'!$J46) -> 0 | F46: =E46-G46 -> 0 | G46: =SUMIFS('Fiscal Calculation'!AR:AR,'Fiscal Calculation'!J:J,'Fiscal by Program'!$J46) -> 0 | H46: =IF(B46>0,SUMIFS('Fiscal Calculation'!AM:AM,'Fiscal Calculation'!J:J,'Fiscal by Program'!$J46),"") | I46: =IF(E46>0,SUMIFS('Fiscal Calculation'!AN:AN,'Fiscal Calculation'!J:J,'Fiscal by Program'!$J46),"") | J46: {=INDEX('Rate Table Service Desc XWalk'!F:F,MATCH(1,(A46='Rate Table Service Desc XWalk'!B:B)*("HCS"='Rate Table Service Desc XWalk'!A:A),0))} -> 3-1-97
A47: CDS Employment Assistance and Supported Employment | B47: =SUMIFS('Fiscal Calculation'!AO:AO,'Fiscal Calculation'!J:J,'Fiscal by Program'!$J47) -> 0 | C47: =B47-D47 -> 0 | D47: =SUMIFS('Fiscal Calculation'!AP:AP,'Fiscal Calculation'!J:J,'Fiscal by Program'!$J47) -> 0 | E47: =SUMIFS('Fiscal Calculation'!AQ:AQ,'Fiscal Calculation'!J:J,'Fiscal by Program'!$J47) -> 0 | F47: =E47-G47 -> 0 | G47: =SUMIFS('Fiscal Calculation'!AR:AR,'Fiscal Calculation'!J:J,'Fiscal by Program'!$J47) -> 0 | H47: =IF(B47>0,SUMIFS('Fiscal Calculation'!AM:AM,'Fiscal Calculation'!J:J,'Fiscal by Program'!$J47),"") | I47: =IF(E47>0,SUMIFS('Fiscal Calculation'!AN:AN,'Fiscal Calculation'!J:J,'Fiscal by Program'!$J47),"") | J47: {=INDEX('Rate Table Service Desc XWalk'!F:F,MATCH(1,(A47='Rate Table Service Desc XWalk'!B:B)*("HCS"='Rate Table Service Desc XWalk'!A:A),0))} -> 3-5-121
A48: CDS In Home Respite | B48: =SUMIFS('Fiscal Calculation'!AO:AO,'Fiscal Calculation'!J:J,'Fiscal by Program'!$J48) -> 0 | C48: =B48-D48 -> 0 | D48: =SUMIFS('Fiscal Calculation'!AP:AP,'Fiscal Calculation'!J:J,'Fiscal by Program'!$J48) -> 0 | E48: =SUMIFS('Fiscal Calculation'!AQ:AQ,'Fiscal Calculation'!J:J,'Fiscal by Program'!$J48) -> 0 | F48: =E48-G48 -> 0 | G48: =SUMIFS('Fiscal Calculation'!AR:AR,'Fiscal Calculation'!J:J,'Fiscal by Program'!$J48) -> 0 | H48: =IF(B48>0,SUMIFS('Fiscal Calculation'!AM:AM,'Fiscal Calculation'!J:J,'Fiscal by Program'!$J48),"") | I48: =IF(E48>0,SUMIFS('Fiscal Calculation'!AN:AN,'Fiscal Calculation'!J:J,'Fiscal by Program'!$J48),"") | J48: {=INDEX('Rate Table Service Desc XWalk'!F:F,MATCH(1,(A48='Rate Table Service Desc XWalk'!B:B)*("HCS"='Rate Table Service Desc XWalk'!A:A),0))} -> 3-5-124
A49: CDS Out-of-Home Respite | B49: =SUMIFS('Fiscal Calculation'!AO:AO,'Fiscal Calculation'!J:J,'Fiscal by Program'!$J49) -> 0 | C49: =B49-D49 -> 0 | D49: =SUMIFS('Fiscal Calculation'!AP:AP,'Fiscal Calculation'!J:J,'Fiscal by Program'!$J49) -> 0 | E49: =SUMIFS('Fiscal Calculation'!AQ:AQ,'Fiscal Calculation'!J:J,'Fiscal by Program'!$J49) -> 0 | F49: =E49-G49 -> 0 | G49: =SUMIFS('Fiscal Calculation'!AR:AR,'Fiscal Calculation'!J:J,'Fiscal by Program'!$J49) -> 0 | H49: =IF(B49>0,SUMIFS('Fiscal Calculation'!AM:AM,'Fiscal Calculation'!J:J,'Fiscal by Program'!$J49),"") | I49: =IF(E49>0,SUMIFS('Fiscal Calculation'!AN:AN,'Fiscal Calculation'!J:J,'Fiscal by Program'!$J49),"") | J49: {=INDEX('Rate Table Service Desc XWalk'!F:F,MATCH(1,(A49='Rate Table Service Desc XWalk'!B:B)*("HCS"='Rate Table Service Desc XWalk'!A:A),0))} -> 3-5-139
A50: CDS PAS/HAB (CFC) and Transportation | B50: =SUMIFS('Fiscal Calculation'!AO:AO,'Fiscal Calculation'!J:J,'Fiscal by Program'!$J50) -> 0 | C50: =B50-D50 -> 0 | D50: =SUMIFS('Fiscal Calculation'!AP:AP,'Fiscal Calculation'!J:J,'Fiscal by Program'!$J50) -> 0 | E50: =SUMIFS('Fiscal Calculation'!AQ:AQ,'Fiscal Calculation'!J:J,'Fiscal by Program'!$J50) -> 0 | F50: =E50-G50 -> 0 | G50: =SUMIFS('Fiscal Calculation'!AR:AR,'Fiscal Calculation'!J:J,'Fiscal by Program'!$J50) -> 0 | H50: =IF(B50>0,SUMIFS('Fiscal Calculation'!AM:AM,'Fiscal Calculation'!J:J,'Fiscal by Program'!$J50),"") | I50: =IF(E50>0,SUMIFS('Fiscal Calculation'!AN:AN,'Fiscal Calculation'!J:J,'Fiscal by Program'!$J50),"") | J50: {=INDEX('Rate Table Service Desc XWalk'!F:F,MATCH(1,(A50='Rate Table Service Desc XWalk'!B:B)*("HCS"='Rate Table Service Desc XWalk'!A:A),0))} -> 3-5-143
A51: HCS Subtotal | B51: =SUM(B41:B50) -> 0 | C51: =SUM(C41:C50) -> 0 | D51: =SUM(D41:D50) -> 0 | E51: =SUM(E41:E50) -> 0 | F51: =SUM(F41:F50) -> 0 | G51: =SUM(G41:G50) -> 0 | H51: =SUM(H41:H50) -> 0 | I51: =SUM(I41:I50) -> 0
A52: Texas Home Living Waiver (TxHmL)
A53: Employment Assistance and Supported Employment | B53: =SUMIFS('Fiscal Calculation'!AO:AO,'Fiscal Calculation'!J:J,'Fiscal by Program'!$J53) -> 0 | C53: =B53-D53 -> 0 | D53: =SUMIFS('Fiscal Calculation'!AP:AP,'Fiscal Calculation'!J:J,'Fiscal by Program'!$J53) -> 0 | E53: =SUMIFS('Fiscal Calculation'!AQ:AQ,'Fiscal Calculation'!J:J,'Fiscal by Program'!$J53) -> 0 | F53: =E53-G53 -> 0 | G53: =SUMIFS('Fiscal Calculation'!AR:AR,'Fiscal Calculation'!J:J,'Fiscal by Program'!$J53) -> 0 | H53: =IF(B53>0,SUMIFS('Fiscal Calculation'!AM:AM,'Fiscal Calculation'!J:J,'Fiscal by Program'!$J53),"") | I53: =IF(E53>0,SUMIFS('Fiscal Calculation'!AN:AN,'Fiscal Calculation'!J:J,'Fiscal by Program'!$J53),"") | J53: {=INDEX('Rate Table Service Desc XWalk'!F:F,MATCH(1,(A53='Rate Table Service Desc XWalk'!B:B)*("TxHmL"='Rate Table Service Desc XWalk'!A:A),0))} -> 4-1-23
A54: In Home Respite | B54: =SUMIFS('Fiscal Calculation'!AO:AO,'Fiscal Calculation'!J:J,'Fiscal by Program'!$J54) -> 0 | C54: =B54-D54 -> 0 | D54: =SUMIFS('Fiscal Calculation'!AP:AP,'Fiscal Calculation'!J:J,'Fiscal by Program'!$J54) -> 0 | E54: =SUMIFS('Fiscal Calculation'!AQ:AQ,'Fiscal Calculation'!J:J,'Fiscal by Program'!$J54) -> 0 | F54: =E54-G54 -> 0 | G54: =SUMIFS('Fiscal Calculation'!AR:AR,'Fiscal Calculation'!J:J,'Fiscal by Program'!$J54) -> 0 | H54: =IF(B54>0,SUMIFS('Fiscal Calculation'!AM:AM,'Fiscal Calculation'!J:J,'Fiscal by Program'!$J54),"") | I54: =IF(E54>0,SUMIFS('Fiscal Calculation'!AN:AN,'Fiscal Calculation'!J:J,'Fiscal by Program'!$J54),"") | J54: {=INDEX('Rate Table Service Desc XWalk'!F:F,MATCH(1,(A54='Rate Table Service Desc XWalk'!B:B)*("TxHmL"='Rate Table Service Desc XWalk'!A:A),0))} -> 4-1-55
A55: Individualized Skills and Socialization | B55: =SUMIFS('Fiscal Calculation'!AO:AO,'Fiscal Calculation'!J:J,'Fiscal by Program'!$J55) -> 0 | C55: =B55-D55 -> 0 | D55: =SUMIFS('Fiscal Calculation'!AP:AP,'Fiscal Calculation'!J:J,'Fiscal by Program'!$J55) -> 0 | E55: =SUMIFS('Fiscal Calculation'!AQ:AQ,'Fiscal Calculation'!J:J,'Fiscal by Program'!$J55) -> 0 | F55: =E55-G55 -> 0 | G55: =SUMIFS('Fiscal Calculation'!AR:AR,'Fiscal Calculation'!J:J,'Fiscal by Program'!$J55) -> 0 | H55: =IF(B55>0,SUMIFS('Fiscal Calculation'!AM:AM,'Fiscal Calculation'!J:J,'Fiscal by Program'!$J55),"") | I55: =IF(E55>0,SUMIFS('Fiscal Calculation'!AN:AN,'Fiscal Calculation'!J:J,'Fiscal by Program'!$J55),"") | J55: {=INDEX('Rate Table Service Desc XWalk'!F:F,MATCH(1,(A55='Rate Table Service Desc XWalk'!B:B)*("TxHmL"='Rate Table Service Desc XWalk'!A:A),0))} -> 4-1-45
A56: Out-of-Home Respite | B56: =SUMIFS('Fiscal Calculation'!AO:AO,'Fiscal Calculation'!J:J,'Fiscal by Program'!$J56) -> 0 | C56: =B56-D56 -> 0 | D56: =SUMIFS('Fiscal Calculation'!AP:AP,'Fiscal Calculation'!J:J,'Fiscal by Program'!$J56) -> 0 | E56: =SUMIFS('Fiscal Calculation'!AQ:AQ,'Fiscal Calculation'!J:J,'Fiscal by Program'!$J56) -> 0 | F56: =E56-G56 -> 0 | G56: =SUMIFS('Fiscal Calculation'!AR:AR,'Fiscal Calculation'!J:J,'Fiscal by Program'!$J56) -> 0 | H56: =IF(B56>0,SUMIFS('Fiscal Calculation'!AM:AM,'Fiscal Calculation'!J:J,'Fiscal by Program'!$J56),"") | I56: =IF(E56>0,SUMIFS('Fiscal Calculation'!AN:AN,'Fiscal Calculation'!J:J,'Fiscal by Program'!$J56),"") | J56: {=INDEX('Rate Table Service Desc XWalk'!F:F,MATCH(1,(A56='Rate Table Service Desc XWalk'!B:B)*("TxHmL"='Rate Table Service Desc XWalk'!A:A),0))} -> 4-1-74
A57: PAS/HAB (CFC) and Transportation | B57: =SUMIFS('Fiscal Calculation'!AO:AO,'Fiscal Calculation'!J:J,'Fiscal by Program'!$J57) -> 0 | C57: =B57-D57 -> 0 | D57: =SUMIFS('Fiscal Calculation'!AP:AP,'Fiscal Calculation'!J:J,'Fiscal by Program'!$J57) -> 0 | E57: =SUMIFS('Fiscal Calculation'!AQ:AQ,'Fiscal Calculation'!J:J,'Fiscal by Program'!$J57) -> 0 | F57: =E57-G57 -> 0 | G57: =SUMIFS('Fiscal Calculation'!AR:AR,'Fiscal Calculation'!J:J,'Fiscal by Program'!$J57) -> 0 | H57: =IF(B57>0,SUMIFS('Fiscal Calculation'!AM:AM,'Fiscal Calculation'!J:J,'Fiscal by Program'!$J57),"") | I57: =IF(E57>0,SUMIFS('Fiscal Calculation'!AN:AN,'Fiscal Calculation'!J:J,'Fiscal by Program'!$J57),"") | J57: {=INDEX('Rate Table Service Desc XWalk'!F:F,MATCH(1,(A57='Rate Table Service Desc XWalk'!B:B)*("TxHmL"='Rate Table Service Desc XWalk'!A:A),0))} -> 4-1-79
A58: CDS Employment Assistance and Supported Employment | B58: =SUMIFS('Fiscal Calculation'!AO:AO,'Fiscal Calculation'!J:J,'Fiscal by Program'!$J58) -> 0 | C58: =B58-D58 -> 0 | D58: =SUMIFS('Fiscal Calculation'!AP:AP,'Fiscal Calculation'!J:J,'Fiscal by Program'!$J58) -> 0 | E58: =SUMIFS('Fiscal Calculation'!AQ:AQ,'Fiscal Calculation'!J:J,'Fiscal by Program'!$J58) -> 0 | F58: =E58-G58 -> 0 | G58: =SUMIFS('Fiscal Calculation'!AR:AR,'Fiscal Calculation'!J:J,'Fiscal by Program'!$J58) -> 0 | H58: =IF(B58>0,SUMIFS('Fiscal Calculation'!AM:AM,'Fiscal Calculation'!J:J,'Fiscal by Program'!$J58),"") | I58: =IF(E58>0,SUMIFS('Fiscal Calculation'!AN:AN,'Fiscal Calculation'!J:J,'Fiscal by Program'!$J58),"") | J58: {=INDEX('Rate Table Service Desc XWalk'!F:F,MATCH(1,(A58='Rate Table Service Desc XWalk'!B:B)*("TxHmL"='Rate Table Service Desc XWalk'!A:A),0))} -> 4-5-121
A59: CDS In Home Respite | B59: =SUMIFS('Fiscal Calculation'!AO:AO,'Fiscal Calculation'!J:J,'Fiscal by Program'!$J59) -> 0 | C59: =B59-D59 -> 0 | D59: =SUMIFS('Fiscal Calculation'!AP:AP,'Fiscal Calculation'!J:J,'Fiscal by Program'!$J59) -> 0 | E59: =SUMIFS('Fiscal Calculation'!AQ:AQ,'Fiscal Calculation'!J:J,'Fiscal by Program'!$J59) -> 0 | F59: =E59-G59 -> 0 | G59: =SUMIFS('Fiscal Calculation'!AR:AR,'Fiscal Calculation'!J:J,'Fiscal by Program'!$J59) -> 0 | H59: =IF(B59>0,SUMIFS('Fiscal Calculation'!AM:AM,'Fiscal Calculation'!J:J,'Fiscal by Program'!$J59),"") | I59: =IF(E59>0,SUMIFS('Fiscal Calculation'!AN:AN,'Fiscal Calculation'!J:J,'Fiscal by Program'!$J59),"") | J59: {=INDEX('Rate Table Service Desc XWalk'!F:F,MATCH(1,(A59='Rate Table Service Desc XWalk'!B:B)*("TxHmL"='Rate Table Service Desc XWalk'!A:A),0))} -> 4-5-124
A60: CDS Individualized Skills and Socialization | B60: =SUMIFS('Fiscal Calculation'!AO:AO,'Fiscal Calculation'!J:J,'Fiscal by Program'!$J60) -> 0 | C60: =B60-D60 -> 0 | D60: =SUMIFS('Fiscal Calculation'!AP:AP,'Fiscal Calculation'!J:J,'Fiscal by Program'!$J60) -> 0 | E60: =SUMIFS('Fiscal Calculation'!AQ:AQ,'Fiscal Calculation'!J:J,'Fiscal by Program'!$J60) -> 0 | F60: =E60-G60 -> 0 | G60: =SUMIFS('Fiscal Calculation'!AR:AR,'Fiscal Calculation'!J:J,'Fiscal by Program'!$J60) -> 0 | H60: =IF(B60>0,SUMIFS('Fiscal Calculation'!AM:AM,'Fiscal Calculation'!J:J,'Fiscal by Program'!$J60),"") | I60: =IF(E60>0,SUMIFS('Fiscal Calculation'!AN:AN,'Fiscal Calculation'!J:J,'Fiscal by Program'!$J60),"") | J60: {=INDEX('Rate Table Service Desc XWalk'!F:F,MATCH(1,(A60='Rate Table Service Desc XWalk'!B:B)*("TxHmL"='Rate Table Service Desc XWalk'!A:A),0))} -> 4-5-126
A61: CDS Out-of-Home Respite | B61: =SUMIFS('Fiscal Calculation'!AO:AO,'Fiscal Calculation'!J:J,'Fiscal by Program'!$J61) -> 0 | C61: =B61-D61 -> 0 | D61: =SUMIFS('Fiscal Calculation'!AP:AP,'Fiscal Calculation'!J:J,'Fiscal by Program'!$J61) -> 0 | E61: =SUMIFS('Fiscal Calculation'!AQ:AQ,'Fiscal Calculation'!J:J,'Fiscal by Program'!$J61) -> 0 | F61: =E61-G61 -> 0 | G61: =SUMIFS('Fiscal Calculation'!AR:AR,'Fiscal Calculation'!J:J,'Fiscal by Program'!$J61) -> 0 | H61: =IF(B61>0,SUMIFS('Fiscal Calculation'!AM:AM,'Fiscal Calculation'!J:J,'Fiscal by Program'!$J61),"") | I61: =IF(E61>0,SUMIFS('Fiscal Calculation'!AN:AN,'Fiscal Calculation'!J:J,'Fiscal by Program'!$J61),"") | J61: {=INDEX('Rate Table Service Desc XWalk'!F:F,MATCH(1,(A61='Rate Table Service Desc XWalk'!B:B)*("TxHmL"='Rate Table Service Desc XWalk'!A:A),0))} -> 4-5-139
A62: CDS PAS/HAB (CFC) and Transportation | B62: =SUMIFS('Fiscal Calculation'!AO:AO,'Fiscal Calculation'!J:J,'Fiscal by Program'!$J62) -> 0 | C62: =B62-D62 -> 0 | D62: =SUMIFS('Fiscal Calculation'!AP:AP,'Fiscal Calculation'!J:J,'Fiscal by Program'!$J62) -> 0 | E62: =SUMIFS('Fiscal Calculation'!AQ:AQ,'Fiscal Calculation'!J:J,'Fiscal by Program'!$J62) -> 0 | F62: =E62-G62 -> 0 | G62: =SUMIFS('Fiscal Calculation'!AR:AR,'Fiscal Calculation'!J:J,'Fiscal by Program'!$J62) -> 0 | H62: =IF(B62>0,SUMIFS('Fiscal Calculation'!AM:AM,'Fiscal Calculation'!J:J,'Fiscal by Program'!$J62),"") | I62: =IF(E62>0,SUMIFS('Fiscal Calculation'!AN:AN,'Fiscal Calculation'!J:J,'Fiscal by Program'!$J62),"") | J62: {=INDEX('Rate Table Service Desc XWalk'!F:F,MATCH(1,(A62='Rate Table Service Desc XWalk'!B:B)*("TxHmL"='Rate Table Service Desc XWalk'!A:A),0))} -> 4-5-143
A63: TxHmL Subtotal | B63: =SUM(B53:B62) -> 0 | C63: =SUM(C53:C62) -> 0 | D63: =SUM(D53:D62) -> 0 | E63: =SUM(E53:E62) -> 0 | F63: =SUM(F53:F62) -> 0 | G63: =SUM(G53:G62) -> 0 | H63: =SUM(H53:H62) -> 0 | I63: =SUM(I53:I62) -> 0
A64: STAR+PLUS Home and Community-based Services (HCBS)
A65: Assisted Living Services | B65: =SUMIFS('Fiscal Calculation'!AO:AO,'Fiscal Calculation'!J:J,'Fiscal by Program'!$J65) -> 0 | C65: =B65-D65 -> 0 | D65: =SUMIFS('Fiscal Calculation'!AP:AP,'Fiscal Calculation'!J:J,'Fiscal by Program'!$J65) -> 0 | E65: =SUMIFS('Fiscal Calculation'!AQ:AQ,'Fiscal Calculation'!J:J,'Fiscal by Program'!$J65) -> 0 | F65: =E65-G65 -> 0 | G65: =SUMIFS('Fiscal Calculation'!AR:AR,'Fiscal Calculation'!J:J,'Fiscal by Program'!$J65) -> 0 | H65: =IF(B65>0,SUMIFS('Fiscal Calculation'!AM:AM,'Fiscal Calculation'!J:J,'Fiscal by Program'!$J65),"") | I65: =IF(E65>0,SUMIFS('Fiscal Calculation'!AN:AN,'Fiscal Calculation'!J:J,'Fiscal by Program'!$J65),"") | J65: {=INDEX('Rate Table Service Desc XWalk'!F:F,MATCH(1,(A65='Rate Table Service Desc XWalk'!B:B)*("STAR+PLUS HCBS"='Rate Table Service Desc XWalk'!A:A),0))} -> 6-1-4
A66: Employment Assistance and Supported Employment | B66: =SUMIFS('Fiscal Calculation'!AO:AO,'Fiscal Calculation'!J:J,'Fiscal by Program'!$J66) -> 0 | C66: =B66-D66 -> 0 | D66: =SUMIFS('Fiscal Calculation'!AP:AP,'Fiscal Calculation'!J:J,'Fiscal by Program'!$J66) -> 0 | E66: =SUMIFS('Fiscal Calculation'!AQ:AQ,'Fiscal Calculation'!J:J,'Fiscal by Program'!$J66) -> 0 | F66: =E66-G66 -> 0 | G66: =SUMIFS('Fiscal Calculation'!AR:AR,'Fiscal Calculation'!J:J,'Fiscal by Program'!$J66) -> 0 | H66: =IF(B66>0,SUMIFS('Fiscal Calculation'!AM:AM,'Fiscal Calculation'!J:J,'Fiscal by Program'!$J66),"") | I66: =IF(E66>0,SUMIFS('Fiscal Calculation'!AN:AN,'Fiscal Calculation'!J:J,'Fiscal by Program'!$J66),"") | J66: {=INDEX('Rate Table Service Desc XWalk'!F:F,MATCH(1,(A66='Rate Table Service Desc XWalk'!B:B)*("STAR+PLUS HCBS"='Rate Table Service Desc XWalk'!A:A),0))} -> 6-1-23
A67: Habilitation (CFC) | B67: =SUMIFS('Fiscal Calculation'!AO:AO,'Fiscal Calculation'!J:J,'Fiscal by Program'!$J67) -> 0 | C67: =B67-D67 -> 0 | D67: =SUMIFS('Fiscal Calculation'!AP:AP,'Fiscal Calculation'!J:J,'Fiscal by Program'!$J67) -> 0 | E67: =SUMIFS('Fiscal Calculation'!AQ:AQ,'Fiscal Calculation'!J:J,'Fiscal by Program'!$J67) -> 0 | F67: =E67-G67 -> 0 | G67: =SUMIFS('Fiscal Calculation'!AR:AR,'Fiscal Calculation'!J:J,'Fiscal by Program'!$J67) -> 0 | H67: =IF(B67>0,SUMIFS('Fiscal Calculation'!AM:AM,'Fiscal Calculation'!J:J,'Fiscal by Program'!$J67),"") | I67: =IF(E67>0,SUMIFS('Fiscal Calculation'!AN:AN,'Fiscal Calculation'!J:J,'Fiscal by Program'!$J67),"") | J67: {=INDEX('Rate Table Service Desc XWalk'!F:F,MATCH(1,(A67='Rate Table Service Desc XWalk'!B:B)*("STAR+PLUS HCBS"='Rate Table Service Desc XWalk'!A:A),0))} -> 6-1-27
A68: In Home Respite | B68: =SUMIFS('Fiscal Calculation'!AO:AO,'Fiscal Calculation'!J:J,'Fiscal by Program'!$J68) -> 0 | C68: =B68-D68 -> 0 | D68: =SUMIFS('Fiscal Calculation'!AP:AP,'Fiscal Calculation'!J:J,'Fiscal by Program'!$J68) -> 0 | E68: =SUMIFS('Fiscal Calculation'!AQ:AQ,'Fiscal Calculation'!J:J,'Fiscal by Program'!$J68) -> 0 | F68: =E68-G68 -> 0 | G68: =SUMIFS('Fiscal Calculation'!AR:AR,'Fiscal Calculation'!J:J,'Fiscal by Program'!$J68) -> 0 | H68: =IF(B68>0,SUMIFS('Fiscal Calculation'!AM:AM,'Fiscal Calculation'!J:J,'Fiscal by Program'!$J68),"") | I68: =IF(E68>0,SUMIFS('Fiscal Calculation'!AN:AN,'Fiscal Calculation'!J:J,'Fiscal by Program'!$J68),"") | J68: {=INDEX('Rate Table Service Desc XWalk'!F:F,MATCH(1,(A68='Rate Table Service Desc XWalk'!B:B)*("STAR+PLUS HCBS"='Rate Table Service Desc XWalk'!A:A),0))} -> 6-1-55
A69: PAS/HAB (CFC and Non-CFC) | B69: =SUMIFS('Fiscal Calculation'!AO:AO,'Fiscal Calculation'!J:J,'Fiscal by Program'!$J69) -> 0 | C69: =B69-D69 -> 0 | D69: =SUMIFS('Fiscal Calculation'!AP:AP,'Fiscal Calculation'!J:J,'Fiscal by Program'!$J69) -> 0 | E69: =SUMIFS('Fiscal Calculation'!AQ:AQ,'Fiscal Calculation'!J:J,'Fiscal by Program'!$J69) -> 0 | F69: =E69-G69 -> 0 | G69: =SUMIFS('Fiscal Calculation'!AR:AR,'Fiscal Calculation'!J:J,'Fiscal by Program'!$J69) -> 0 | H69: =IF(B69>0,SUMIFS('Fiscal Calculation'!AM:AM,'Fiscal Calculation'!J:J,'Fiscal by Program'!$J69),"") | I69: =IF(E69>0,SUMIFS('Fiscal Calculation'!AN:AN,'Fiscal Calculation'!J:J,'Fiscal by Program'!$J69),"") | J69: {=INDEX('Rate Table Service Desc XWalk'!F:F,MATCH(1,(A69='Rate Table Service Desc XWalk'!B:B)*("STAR+PLUS HCBS"='Rate Table Service Desc XWalk'!A:A),0))} -> 6-1-77
A70: CDS Habilitation (CFC) | B70: =SUMIFS('Fiscal Calculation'!AO:AO,'Fiscal Calculation'!J:J,'Fiscal by Program'!$J70) -> 0 | C70: =B70-D70 -> 0 | D70: =SUMIFS('Fiscal Calculation'!AP:AP,'Fiscal Calculation'!J:J,'Fiscal by Program'!$J70) -> 0 | E70: =SUMIFS('Fiscal Calculation'!AQ:AQ,'Fiscal Calculation'!J:J,'Fiscal by Program'!$J70) -> 0 | F70: =E70-G70 -> 0 | G70: =SUMIFS('Fiscal Calculation'!AR:AR,'Fiscal Calculation'!J:J,'Fiscal by Program'!$J70) -> 0 | H70: =IF(B70>0,SUMIFS('Fiscal Calculation'!AM:AM,'Fiscal Calculation'!J:J,'Fiscal by Program'!$J70),"") | I70: =IF(E70>0,SUMIFS('Fiscal Calculation'!AN:AN,'Fiscal Calculation'!J:J,'Fiscal by Program'!$J70),"") | J70: {=INDEX('Rate Table Service Desc XWalk'!F:F,MATCH(1,(A70='Rate Table Service Desc XWalk'!B:B)*("STAR+PLUS HCBS"='Rate Table Service Desc XWalk'!A:A),0))} -> 6-5-123
A71: CDS In Home Respite | B71: =SUMIFS('Fiscal Calculation'!AO:AO,'Fiscal Calculation'!J:J,'Fiscal by Program'!$J71) -> 0 | C71: =B71-D71 -> 0 | D71: =SUMIFS('Fiscal Calculation'!AP:AP,'Fiscal Calculation'!J:J,'Fiscal by Program'!$J71) -> 0 | E71: =SUMIFS('Fiscal Calculation'!AQ:AQ,'Fiscal Calculation'!J:J,'Fiscal by Program'!$J71) -> 0 | F71: =E71-G71 -> 0 | G71: =SUMIFS('Fiscal Calculation'!AR:AR,'Fiscal Calculation'!J:J,'Fiscal by Program'!$J71) -> 0 | H71: =IF(B71>0,SUMIFS('Fiscal Calculation'!AM:AM,'Fiscal Calculation'!J:J,'Fiscal by Program'!$J71),"") | I71: =IF(E71>0,SUMIFS('Fiscal Calculation'!AN:AN,'Fiscal Calculation'!J:J,'Fiscal by Program'!$J71),"") | J71: {=INDEX('Rate Table Service Desc XWalk'!F:F,MATCH(1,(A71='Rate Table Service Desc XWalk'!B:B)*("STAR+PLUS HCBS"='Rate Table Service Desc XWalk'!A:A),0))} -> 6-5-136
A72: CDS PAS/HAB (CFC and Non-CFC) | B72: =SUMIFS('Fiscal Calculation'!AO:AO,'Fiscal Calculation'!J:J,'Fiscal by Program'!$J72) -> 0 | C72: =B72-D72 -> 0 | D72: =SUMIFS('Fiscal Calculation'!AP:AP,'Fiscal Calculation'!J:J,'Fiscal by Program'!$J72) -> 0 | E72: =SUMIFS('Fiscal Calculation'!AQ:AQ,'Fiscal Calculation'!J:J,'Fiscal by Program'!$J72) -> 0 | F72: =E72-G72 -> 0 | G72: =SUMIFS('Fiscal Calculation'!AR:AR,'Fiscal Calculation'!J:J,'Fiscal by Program'!$J72) -> 0 | H72: =IF(B72>0,SUMIFS('Fiscal Calculation'!AM:AM,'Fiscal Calculation'!J:J,'Fiscal by Program'!$J72),"") | I72: =IF(E72>0,SUMIFS('Fiscal Calculation'!AN:AN,'Fiscal Calculation'!J:J,'Fiscal by Program'!$J72),"") | J72: {=INDEX('Rate Table Service Desc XWalk'!F:F,MATCH(1,(A72='Rate Table Service Desc XWalk'!B:B)*("STAR+PLUS HCBS"='Rate Table Service Desc XWalk'!A:A),0))} -> 6-5-141
A73: STAR+PLUS HCBS Subtotal | B73: =SUM(B65:B72) -> 0 | C73: =SUM(C65:C72) -> 0 | D73: =SUM(D65:D72) -> 0 | E73: =SUM(E65:E72) -> 0 | F73: =SUM(F65:F72) -> 0 | G73: =SUM(G65:G72) -> 0 | H73: =SUM(H65:H72) -> 0 | I73: =SUM(I65:I72) -> 0
A74: STAR+PLUS Non-HCBS (State Plan)
A75: Day Activity and Health Services (DAHS) | B75: =SUMIFS('Fiscal Calculation'!AO:AO,'Fiscal Calculation'!J:J,'Fiscal by Program'!$J75) -> 0 | C75: =B75-D75 -> 0 | D75: =SUMIFS('Fiscal Calculation'!AP:AP,'Fiscal Calculation'!J:J,'Fiscal by Program'!$J75) -> 0 | E75: =SUMIFS('Fiscal Calculation'!AQ:AQ,'Fiscal Calculation'!J:J,'Fiscal by Program'!$J75) -> 0 | F75: =E75-G75 -> 0 | G75: =SUMIFS('Fiscal Calculation'!AR:AR,'Fiscal Calculation'!J:J,'Fiscal by Program'!$J75) -> 0 | H75: =IF(B75>0,SUMIFS('Fiscal Calculation'!AM:AM,'Fiscal Calculation'!J:J,'Fiscal by Program'!$J75),"") | I75: =IF(E75>0,SUMIFS('Fiscal Calculation'!AN:AN,'Fiscal Calculation'!J:J,'Fiscal by Program'!$J75),"") | J75: {=INDEX('Rate Table Service Desc XWalk'!F:F,MATCH(1,(A75='Rate Table Service Desc XWalk'!B:B)*("STAR+PLUS"='Rate Table Service Desc XWalk'!A:A),0))} -> 7-1-17
A76: Habilitation (CFC) | B76: =SUMIFS('Fiscal Calculation'!AO:AO,'Fiscal Calculation'!J:J,'Fiscal by Program'!$J76) -> 0 | C76: =B76-D76 -> 0 | D76: =SUMIFS('Fiscal Calculation'!AP:AP,'Fiscal Calculation'!J:J,'Fiscal by Program'!$J76) -> 0 | E76: =SUMIFS('Fiscal Calculation'!AQ:AQ,'Fiscal Calculation'!J:J,'Fiscal by Program'!$J76) -> 0 | F76: =E76-G76 -> 0 | G76: =SUMIFS('Fiscal Calculation'!AR:AR,'Fiscal Calculation'!J:J,'Fiscal by Program'!$J76) -> 0 | H76: =IF(B76>0,SUMIFS('Fiscal Calculation'!AM:AM,'Fiscal Calculation'!J:J,'Fiscal by Program'!$J76),"") | I76: =IF(E76>0,SUMIFS('Fiscal Calculation'!AN:AN,'Fiscal Calculation'!J:J,'Fiscal by Program'!$J76),"") | J76: {=INDEX('Rate Table Service Desc XWalk'!F:F,MATCH(1,(A76='Rate Table Service Desc XWalk'!B:B)*("STAR+PLUS"='Rate Table Service Desc XWalk'!A:A),0))} -> 7-1-27
A77: PAS/HAB (CFC and Non-CFC) | B77: =SUMIFS('Fiscal Calculation'!AO:AO,'Fiscal Calculation'!J:J,'Fiscal by Program'!$J77) -> 0 | C77: =B77-D77 -> 0 | D77: =SUMIFS('Fiscal Calculation'!AP:AP,'Fiscal Calculation'!J:J,'Fiscal by Program'!$J77) -> 0 | E77: =SUMIFS('Fiscal Calculation'!AQ:AQ,'Fiscal Calculation'!J:J,'Fiscal by Program'!$J77) -> 0 | F77: =E77-G77 -> 0 | G77: =SUMIFS('Fiscal Calculation'!AR:AR,'Fiscal Calculation'!J:J,'Fiscal by Program'!$J77) -> 0 | H77: =IF(B77>0,SUMIFS('Fiscal Calculation'!AM:AM,'Fiscal Calculation'!J:J,'Fiscal by Program'!$J77),"") | I77: =IF(E77>0,SUMIFS('Fiscal Calculation'!AN:AN,'Fiscal Calculation'!J:J,'Fiscal by Program'!$J77),"") | J77: {=INDEX('Rate Table Service Desc XWalk'!F:F,MATCH(1,(A77='Rate Table Service Desc XWalk'!B:B)*("STAR+PLUS"='Rate Table Service Desc XWalk'!A:A),0))} -> 7-1-77
A78: CDS Habilitation (CFC) | B78: =SUMIFS('Fiscal Calculation'!AO:AO,'Fiscal Calculation'!J:J,'Fiscal by Program'!$J78) -> 0 | C78: =B78-D78 -> 0 | D78: =SUMIFS('Fiscal Calculation'!AP:AP,'Fiscal Calculation'!J:J,'Fiscal by Program'!$J78) -> 0 | E78: =SUMIFS('Fiscal Calculation'!AQ:AQ,'Fiscal Calculation'!J:J,'Fiscal by Program'!$J78) -> 0 | F78: =E78-G78 -> 0 | G78: =SUMIFS('Fiscal Calculation'!AR:AR,'Fiscal Calculation'!J:J,'Fiscal by Program'!$J78) -> 0 | H78: =IF(B78>0,SUMIFS('Fiscal Calculation'!AM:AM,'Fiscal Calculation'!J:J,'Fiscal by Program'!$J78),"") | I78: =IF(E78>0,SUMIFS('Fiscal Calculation'!AN:AN,'Fiscal Calculation'!J:J,'Fiscal by Program'!$J78),"") | J78: {=INDEX('Rate Table Service Desc XWalk'!F:F,MATCH(1,(A78='Rate Table Service Desc XWalk'!B:B)*("STAR+PLUS"='Rate Table Service Desc XWalk'!A:A),0))} -> 7-5-123
A79: CDS PAS/HAB (CFC and Non-CFC) | B79: =SUMIFS('Fiscal Calculation'!AO:AO,'Fiscal Calculation'!J:J,'Fiscal by Program'!$J79) -> 0 | C79: =B79-D79 -> 0 | D79: =SUMIFS('Fiscal Calculation'!AP:AP,'Fiscal Calculation'!J:J,'Fiscal by Program'!$J79) -> 0 | E79: =SUMIFS('Fiscal Calculation'!AQ:AQ,'Fiscal Calculation'!J:J,'Fiscal by Program'!$J79) -> 0 | F79: =E79-G79 -> 0 | G79: =SUMIFS('Fiscal Calculation'!AR:AR,'Fiscal Calculation'!J:J,'Fiscal by Program'!$J79) -> 0 | H79: =IF(B79>0,SUMIFS('Fiscal Calculation'!AM:AM,'Fiscal Calculation'!J:J,'Fiscal by Program'!$J79),"") | I79: =IF(E79>0,SUMIFS('Fiscal Calculation'!AN:AN,'Fiscal Calculation'!J:J,'Fiscal by Program'!$J79),"") | J79: {=INDEX('Rate Table Service Desc XWalk'!F:F,MATCH(1,(A79='Rate Table Service Desc XWalk'!B:B)*("STAR+PLUS"='Rate Table Service Desc XWalk'!A:A),0))} -> 7-5-141
A80: STAR+PLUS Non-HCBS Subtotal | B80: =SUM(B75:B79) -> 0 | C80: =SUM(C75:C79) -> 0 | D80: =SUM(D75:D79) -> 0 | E80: =SUM(E75:E79) -> 0 | F80: =SUM(F75:F79) -> 0 | G80: =SUM(G75:G79) -> 0 | H80: =SUM(H75:H79) -> 0 | I80: =SUM(I75:I79) -> 0
A81: STAR Kids - Medically Dependent Children's Program (MDCP)
A82: CFC Habilitation and Attendant Care | B82: =SUMIFS('Fiscal Calculation'!AO:AO,'Fiscal Calculation'!J:J,'Fiscal by Program'!$J82) -> 0 | C82: =B82-D82 -> 0 | D82: =SUMIFS('Fiscal Calculation'!AP:AP,'Fiscal Calculation'!J:J,'Fiscal by Program'!$J82) -> 0 | E82: =SUMIFS('Fiscal Calculation'!AQ:AQ,'Fiscal Calculation'!J:J,'Fiscal by Program'!$J82) -> 0 | F82: =E82-G82 -> 0 | G82: =SUMIFS('Fiscal Calculation'!AR:AR,'Fiscal Calculation'!J:J,'Fiscal by Program'!$J82) -> 0 | H82: =IF(B82>0,SUMIFS('Fiscal Calculation'!AM:AM,'Fiscal Calculation'!J:J,'Fiscal by Program'!$J82),"") | I82: =IF(E82>0,SUMIFS('Fiscal Calculation'!AN:AN,'Fiscal Calculation'!J:J,'Fiscal by Program'!$J82),"") | J82: {=INDEX('Rate Table Service Desc XWalk'!F:F,MATCH(1,(A82='Rate Table Service Desc XWalk'!B:B)*("STAR Kids MDCP"='Rate Table Service Desc XWalk'!A:A),0))} -> 8-1-11
A83: In Home Respite and Flexible Family Support | B83: =SUMIFS('Fiscal Calculation'!AO:AO,'Fiscal Calculation'!J:J,'Fiscal by Program'!$J83) -> 0 | C83: =B83-D83 -> 0 | D83: =SUMIFS('Fiscal Calculation'!AP:AP,'Fiscal Calculation'!J:J,'Fiscal by Program'!$J83) -> 0 | E83: =SUMIFS('Fiscal Calculation'!AQ:AQ,'Fiscal Calculation'!J:J,'Fiscal by Program'!$J83) -> 0 | F83: =E83-G83 -> 0 | G83: =SUMIFS('Fiscal Calculation'!AR:AR,'Fiscal Calculation'!J:J,'Fiscal by Program'!$J83) -> 0 | H83: =IF(B83>0,SUMIFS('Fiscal Calculation'!AM:AM,'Fiscal Calculation'!J:J,'Fiscal by Program'!$J83),"") | I83: =IF(E83>0,SUMIFS('Fiscal Calculation'!AN:AN,'Fiscal Calculation'!J:J,'Fiscal by Program'!$J83),"") | J83: {=INDEX('Rate Table Service Desc XWalk'!F:F,MATCH(1,(A83='Rate Table Service Desc XWalk'!B:B)*("STAR Kids MDCP"='Rate Table Service Desc XWalk'!A:A),0))} -> 8-1-41
A84: PCS (CFC and Non-CFC) | B84: =SUMIFS('Fiscal Calculation'!AO:AO,'Fiscal Calculation'!J:J,'Fiscal by Program'!$J84) -> 0 | C84: =B84-D84 -> 0 | D84: =SUMIFS('Fiscal Calculation'!AP:AP,'Fiscal Calculation'!J:J,'Fiscal by Program'!$J84) -> 0 | E84: =SUMIFS('Fiscal Calculation'!AQ:AQ,'Fiscal Calculation'!J:J,'Fiscal by Program'!$J84) -> 0 | F84: =E84-G84 -> 0 | G84: =SUMIFS('Fiscal Calculation'!AR:AR,'Fiscal Calculation'!J:J,'Fiscal by Program'!$J84) -> 0 | H84: =IF(B84>0,SUMIFS('Fiscal Calculation'!AM:AM,'Fiscal Calculation'!J:J,'Fiscal by Program'!$J84),"") | I84: =IF(E84>0,SUMIFS('Fiscal Calculation'!AN:AN,'Fiscal Calculation'!J:J,'Fiscal by Program'!$J84),"") | J84: {=INDEX('Rate Table Service Desc XWalk'!F:F,MATCH(1,(A84='Rate Table Service Desc XWalk'!B:B)*("STAR Kids MDCP"='Rate Table Service Desc XWalk'!A:A),0))} -> 8-1-80
A85: CDS CFC Habilitation and Attendant Care | B85: =SUMIFS('Fiscal Calculation'!AO:AO,'Fiscal Calculation'!J:J,'Fiscal by Program'!$J85) -> 0 | C85: =B85-D85 -> 0 | D85: =SUMIFS('Fiscal Calculation'!AP:AP,'Fiscal Calculation'!J:J,'Fiscal by Program'!$J85) -> 0 | E85: =SUMIFS('Fiscal Calculation'!AQ:AQ,'Fiscal Calculation'!J:J,'Fiscal by Program'!$J85) -> 0 | F85: =E85-G85 -> 0 | G85: =SUMIFS('Fiscal Calculation'!AR:AR,'Fiscal Calculation'!J:J,'Fiscal by Program'!$J85) -> 0 | H85: =IF(B85>0,SUMIFS('Fiscal Calculation'!AM:AM,'Fiscal Calculation'!J:J,'Fiscal by Program'!$J85),"") | I85: =IF(E85>0,SUMIFS('Fiscal Calculation'!AN:AN,'Fiscal Calculation'!J:J,'Fiscal by Program'!$J85),"") | J85: {=INDEX('Rate Table Service Desc XWalk'!F:F,MATCH(1,(A85='Rate Table Service Desc XWalk'!B:B)*("STAR Kids MDCP"='Rate Table Service Desc XWalk'!A:A),0))} -> 8-5-118
A86: CDS In Home Respite and Flexible Family Support | B86: =SUMIFS('Fiscal Calculation'!AO:AO,'Fiscal Calculation'!J:J,'Fiscal by Program'!$J86) -> 0 | C86: =B86-D86 -> 0 | D86: =SUMIFS('Fiscal Calculation'!AP:AP,'Fiscal Calculation'!J:J,'Fiscal by Program'!$J86) -> 0 | E86: =SUMIFS('Fiscal Calculation'!AQ:AQ,'Fiscal Calculation'!J:J,'Fiscal by Program'!$J86) -> 0 | F86: =E86-G86 -> 0 | G86: =SUMIFS('Fiscal Calculation'!AR:AR,'Fiscal Calculation'!J:J,'Fiscal by Program'!$J86) -> 0 | H86: =IF(B86>0,SUMIFS('Fiscal Calculation'!AM:AM,'Fiscal Calculation'!J:J,'Fiscal by Program'!$J86),"") | I86: =IF(E86>0,SUMIFS('Fiscal Calculation'!AN:AN,'Fiscal Calculation'!J:J,'Fiscal by Program'!$J86),"") | J86: {=INDEX('Rate Table Service Desc XWalk'!F:F,MATCH(1,(A86='Rate Table Service Desc XWalk'!B:B)*("STAR Kids MDCP"='Rate Table Service Desc XWalk'!A:A),0))} -> 8-5-125
A87: CDS PCS (CFC and Non-CFC) | B87: =SUMIFS('Fiscal Calculation'!AO:AO,'Fiscal Calculation'!J:J,'Fiscal by Program'!$J87) -> 0 | C87: =B87-D87 -> 0 | D87: =SUMIFS('Fiscal Calculation'!AP:AP,'Fiscal Calculation'!J:J,'Fiscal by Program'!$J87) -> 0 | E87: =SUMIFS('Fiscal Calculation'!AQ:AQ,'Fiscal Calculation'!J:J,'Fiscal by Program'!$J87) -> 0 | F87: =E87-G87 -> 0 | G87: =SUMIFS('Fiscal Calculation'!AR:AR,'Fiscal Calculation'!J:J,'Fiscal by Program'!$J87) -> 0 | H87: =IF(B87>0,SUMIFS('Fiscal Calculation'!AM:AM,'Fiscal Calculation'!J:J,'Fiscal by Program'!$J87),"") | I87: =IF(E87>0,SUMIFS('Fiscal Calculation'!AN:AN,'Fiscal Calculation'!J:J,'Fiscal by Program'!$J87),"") | J87: {=INDEX('Rate Table Service Desc XWalk'!F:F,MATCH(1,(A87='Rate Table Service Desc XWalk'!B:B)*("STAR Kids MDCP"='Rate Table Service Desc XWalk'!A:A),0))} -> 8-5-144
A88: STAR Kids MDCP Subtotal | B88: =SUM(B82:B87) -> 0 | C88: =SUM(C82:C87) -> 0 | D88: =SUM(D82:D87) -> 0 | E88: =SUM(E82:E87) -> 0 | F88: =SUM(F82:F87) -> 0 | G88: =SUM(G82:G87) -> 0 | H88: =SUM(H82:H87) -> 0 | I88: =SUM(I82:I87) -> 0
A89: STAR Health - MDCP
A90: In Home Respite and Flexible Family Support | B90: =SUMIFS('Fiscal Calculation'!AO:AO,'Fiscal Calculation'!J:J,'Fiscal by Program'!$J90) -> 0 | C90: =B90-D90 -> 0 | D90: =SUMIFS('Fiscal Calculation'!AP:AP,'Fiscal Calculation'!J:J,'Fiscal by Program'!$J90) -> 0 | E90: =SUMIFS('Fiscal Calculation'!AQ:AQ,'Fiscal Calculation'!J:J,'Fiscal by Program'!$J90) -> 0 | F90: =E90-G90 -> 0 | G90: =SUMIFS('Fiscal Calculation'!AR:AR,'Fiscal Calculation'!J:J,'Fiscal by Program'!$J90) -> 0 | H90: =IF(B90>0,SUMIFS('Fiscal Calculation'!AM:AM,'Fiscal Calculation'!J:J,'Fiscal by Program'!$J90),"") | I90: =IF(E90>0,SUMIFS('Fiscal Calculation'!AN:AN,'Fiscal Calculation'!J:J,'Fiscal by Program'!$J90),"") | J90: {=INDEX('Rate Table Service Desc XWalk'!F:F,MATCH(1,(A90='Rate Table Service Desc XWalk'!B:B)*("STAR Health MDCP"='Rate Table Service Desc XWalk'!A:A),0))} -> 12-1-41
A91: CDS In Home Respite and Flexible Family Support | B91: =SUMIFS('Fiscal Calculation'!AO:AO,'Fiscal Calculation'!J:J,'Fiscal by Program'!$J91) -> 0 | C91: =B91-D91 -> 0 | D91: =SUMIFS('Fiscal Calculation'!AP:AP,'Fiscal Calculation'!J:J,'Fiscal by Program'!$J91) -> 0 | E91: =SUMIFS('Fiscal Calculation'!AQ:AQ,'Fiscal Calculation'!J:J,'Fiscal by Program'!$J91) -> 0 | F91: =E91-G91 -> 0 | G91: =SUMIFS('Fiscal Calculation'!AR:AR,'Fiscal Calculation'!J:J,'Fiscal by Program'!$J91) -> 0 | H91: =IF(B91>0,SUMIFS('Fiscal Calculation'!AM:AM,'Fiscal Calculation'!J:J,'Fiscal by Program'!$J91),"") | I91: =IF(E91>0,SUMIFS('Fiscal Calculation'!AN:AN,'Fiscal Calculation'!J:J,'Fiscal by Program'!$J91),"") | J91: {=INDEX('Rate Table Service Desc XWalk'!F:F,MATCH(1,(A91='Rate Table Service Desc XWalk'!B:B)*("STAR Health MDCP"='Rate Table Service Desc XWalk'!A:A),0))} -> 12-5-125
A92: STAR Health MDCP Subtotal | B92: =SUM(B90:B91) -> 0 | C92: =SUM(C90:C91) -> 0 | D92: =SUM(D90:D91) -> 0 | E92: =SUM(E90:E91) -> 0 | F92: =SUM(F90:F91) -> 0 | G92: =SUM(G90:G91) -> 0 | H92: =SUM(H90:H91) -> 0 | I92: =SUM(I90:I91) -> 0
A93: STAR Kids (Non-MDCP)
A94: CFC Habilitation and Attendant Care | B94: =SUMIFS('Fiscal Calculation'!AO:AO,'Fiscal Calculation'!J:J,'Fiscal by Program'!$J94) -> 0 | C94: =B94-D94 -> 0 | D94: =SUMIFS('Fiscal Calculation'!AP:AP,'Fiscal Calculation'!J:J,'Fiscal by Program'!$J94) -> 0 | E94: =SUMIFS('Fiscal Calculation'!AQ:AQ,'Fiscal Calculation'!J:J,'Fiscal by Program'!$J94) -> 0 | F94: =E94-G94 -> 0 | G94: =SUMIFS('Fiscal Calculation'!AR:AR,'Fiscal Calculation'!J:J,'Fiscal by Program'!$J94) -> 0 | H94: =IF(B94>0,SUMIFS('Fiscal Calculation'!AM:AM,'Fiscal Calculation'!J:J,'Fiscal by Program'!$J94),"") | I94: =IF(E94>0,SUMIFS('Fiscal Calculation'!AN:AN,'Fiscal Calculation'!J:J,'Fiscal by Program'!$J94),"") | J94: {=INDEX('Rate Table Service Desc XWalk'!F:F,MATCH(1,(A94='Rate Table Service Desc XWalk'!B:B)*("STAR Kids"='Rate Table Service Desc XWalk'!A:A),0))} -> 9-1-11
A95: Day Activity and Health Services (DAHS) | B95: =SUMIFS('Fiscal Calculation'!AO:AO,'Fiscal Calculation'!J:J,'Fiscal by Program'!$J95) -> 0 | C95: =B95-D95 -> 0 | D95: =SUMIFS('Fiscal Calculation'!AP:AP,'Fiscal Calculation'!J:J,'Fiscal by Program'!$J95) -> 0 | E95: =SUMIFS('Fiscal Calculation'!AQ:AQ,'Fiscal Calculation'!J:J,'Fiscal by Program'!$J95) -> 0 | F95: =E95-G95 -> 0 | G95: =SUMIFS('Fiscal Calculation'!AR:AR,'Fiscal Calculation'!J:J,'Fiscal by Program'!$J95) -> 0 | H95: =IF(B95>0,SUMIFS('Fiscal Calculation'!AM:AM,'Fiscal Calculation'!J:J,'Fiscal by Program'!$J95),"") | I95: =IF(E95>0,SUMIFS('Fiscal Calculation'!AN:AN,'Fiscal Calculation'!J:J,'Fiscal by Program'!$J95),"") | J95: {=INDEX('Rate Table Service Desc XWalk'!F:F,MATCH(1,(A95='Rate Table Service Desc XWalk'!B:B)*("STAR Kids"='Rate Table Service Desc XWalk'!A:A),0))} -> 9-1-17
A96: PCS (CFC and Non-CFC) | B96: =SUMIFS('Fiscal Calculation'!AO:AO,'Fiscal Calculation'!J:J,'Fiscal by Program'!$J96) -> 0 | C96: =B96-D96 -> 0 | D96: =SUMIFS('Fiscal Calculation'!AP:AP,'Fiscal Calculation'!J:J,'Fiscal by Program'!$J96) -> 0 | E96: =SUMIFS('Fiscal Calculation'!AQ:AQ,'Fiscal Calculation'!J:J,'Fiscal by Program'!$J96) -> 0 | F96: =E96-G96 -> 0 | G96: =SUMIFS('Fiscal Calculation'!AR:AR,'Fiscal Calculation'!J:J,'Fiscal by Program'!$J96) -> 0 | H96: =IF(B96>0,SUMIFS('Fiscal Calculation'!AM:AM,'Fiscal Calculation'!J:J,'Fiscal by Program'!$J96),"") | I96: =IF(E96>0,SUMIFS('Fiscal Calculation'!AN:AN,'Fiscal Calculation'!J:J,'Fiscal by Program'!$J96),"") | J96: {=INDEX('Rate Table Service Desc XWalk'!F:F,MATCH(1,(A96='Rate Table Service Desc XWalk'!B:B)*("STAR Kids"='Rate Table Service Desc XWalk'!A:A),0))} -> 9-1-80
A97: CDS CFC Habilitation and Attendant Care | B97: =SUMIFS('Fiscal Calculation'!AO:AO,'Fiscal Calculation'!J:J,'Fiscal by Program'!$J97) -> 0 | C97: =B97-D97 -> 0 | D97: =SUMIFS('Fiscal Calculation'!AP:AP,'Fiscal Calculation'!J:J,'Fiscal by Program'!$J97) -> 0 | E97: =SUMIFS('Fiscal Calculation'!AQ:AQ,'Fiscal Calculation'!J:J,'Fiscal by Program'!$J97) -> 0 | F97: =E97-G97 -> 0 | G97: =SUMIFS('Fiscal Calculation'!AR:AR,'Fiscal Calculation'!J:J,'Fiscal by Program'!$J97) -> 0 | H97: =IF(B97>0,SUMIFS('Fiscal Calculation'!AM:AM,'Fiscal Calculation'!J:J,'Fiscal by Program'!$J97),"") | I97: =IF(E97>0,SUMIFS('Fiscal Calculation'!AN:AN,'Fiscal Calculation'!J:J,'Fiscal by Program'!$J97),"") | J97: {=INDEX('Rate Table Service Desc XWalk'!F:F,MATCH(1,(A97='Rate Table Service Desc XWalk'!B:B)*("STAR Kids"='Rate Table Service Desc XWalk'!A:A),0))} -> 9-5-118
A98: CDS PCS (CFC and Non-CFC) | B98: =SUMIFS('Fiscal Calculation'!AO:AO,'Fiscal Calculation'!J:J,'Fiscal by Program'!$J98) -> 0 | C98: =B98-D98 -> 0 | D98: =SUMIFS('Fiscal Calculation'!AP:AP,'Fiscal Calculation'!J:J,'Fiscal by Program'!$J98) -> 0 | E98: =SUMIFS('Fiscal Calculation'!AQ:AQ,'Fiscal Calculation'!J:J,'Fiscal by Program'!$J98) -> 0 | F98: =E98-G98 -> 0 | G98: =SUMIFS('Fiscal Calculation'!AR:AR,'Fiscal Calculation'!J:J,'Fiscal by Program'!$J98) -> 0 | H98: =IF(B98>0,SUMIFS('Fiscal Calculation'!AM:AM,'Fiscal Calculation'!J:J,'Fiscal by Program'!$J98),"") | I98: =IF(E98>0,SUMIFS('Fiscal Calculation'!AN:AN,'Fiscal Calculation'!J:J,'Fiscal by Program'!$J98),"") | J98: {=INDEX('Rate Table Service Desc XWalk'!F:F,MATCH(1,(A98='Rate Table Service Desc XWalk'!B:B)*("STAR Kids"='Rate Table Service Desc XWalk'!A:A),0))} -> 9-5-144
A99: STAR Kids (Non-MDCP) | B99: =SUM(B94:B98) -> 0 | C99: =SUM(C94:C98) -> 0 | D99: =SUM(D94:D98) -> 0 | E99: =SUM(E94:E98) -> 0 | F99: =SUM(F94:F98) -> 0 | G99: =SUM(G94:G98) -> 0 | H99: =SUM(H94:H98) -> 0 | I99: =SUM(I94:I98) -> 0
A100: Community Attendant Services (CAS) / Family Care (FC) / Primary Home Care (PHC) / PCS Fee-For-Service (PCS FFS)
A101: CAS/FC/PAS/PHC NON-PRIORITY | B101: =SUMIFS('Fiscal Calculation'!AO:AO,'Fiscal Calculation'!J:J,'Fiscal by Program'!$J101) -> 0 | C101: =B101-D101 -> 0 | D101: =SUMIFS('Fiscal Calculation'!AP:AP,'Fiscal Calculation'!J:J,'Fiscal by Program'!$J101) -> 0 | E101: =SUMIFS('Fiscal Calculation'!AQ:AQ,'Fiscal Calculation'!J:J,'Fiscal by Program'!$J101) -> 0 | F101: =E101-G101 -> 0 | G101: =SUMIFS('Fiscal Calculation'!AR:AR,'Fiscal Calculation'!J:J,'Fiscal by Program'!$J101) -> 0 | H101: =IF(B101>0,SUMIFS('Fiscal Calculation'!AM:AM,'Fiscal Calculation'!J:J,'Fiscal by Program'!$J101),"") | I101: =IF(E101>0,SUMIFS('Fiscal Calculation'!AN:AN,'Fiscal Calculation'!J:J,'Fiscal by Program'!$J101),"") | J101: {=INDEX('Rate Table Service Desc XWalk'!F:F,MATCH(1,(A101='Rate Table Service Desc XWalk'!B:B)*("CAS"='Rate Table Service Desc XWalk'!A:A),0))} -> 13-1-7
A102: CAS/FC/PAS/PHC PRIORITY | B102: =SUMIFS('Fiscal Calculation'!AO:AO,'Fiscal Calculation'!J:J,'Fiscal by Program'!$J102) -> 0 | C102: =B102-D102 -> 0 | D102: =SUMIFS('Fiscal Calculation'!AP:AP,'Fiscal Calculation'!J:J,'Fiscal by Program'!$J102) -> 0 | E102: =SUMIFS('Fiscal Calculation'!AQ:AQ,'Fiscal Calculation'!J:J,'Fiscal by Program'!$J102) -> 0 | F102: =E102-G102 -> 0 | G102: =SUMIFS('Fiscal Calculation'!AR:AR,'Fiscal Calculation'!J:J,'Fiscal by Program'!$J102) -> 0 | H102: =IF(B102>0,SUMIFS('Fiscal Calculation'!AM:AM,'Fiscal Calculation'!J:J,'Fiscal by Program'!$J102),"") | I102: =IF(E102>0,SUMIFS('Fiscal Calculation'!AN:AN,'Fiscal Calculation'!J:J,'Fiscal by Program'!$J102),"") | J102: {=INDEX('Rate Table Service Desc XWalk'!F:F,MATCH(1,(A102='Rate Table Service Desc XWalk'!B:B)*("CAS"='Rate Table Service Desc XWalk'!A:A),0))} -> 13-1-8
A103: PCS (CFC and Non-CFC) | B103: =SUMIFS('Fiscal Calculation'!AO:AO,'Fiscal Calculation'!J:J,'Fiscal by Program'!$J103) -> 0 | C103: =B103-D103 -> 0 | D103: =SUMIFS('Fiscal Calculation'!AP:AP,'Fiscal Calculation'!J:J,'Fiscal by Program'!$J103) -> 0 | E103: =SUMIFS('Fiscal Calculation'!AQ:AQ,'Fiscal Calculation'!J:J,'Fiscal by Program'!$J103) -> 0 | F103: =E103-G103 -> 0 | G103: =SUMIFS('Fiscal Calculation'!AR:AR,'Fiscal Calculation'!J:J,'Fiscal by Program'!$J103) -> 0 | H103: =IF(B103>0,SUMIFS('Fiscal Calculation'!AM:AM,'Fiscal Calculation'!J:J,'Fiscal by Program'!$J103),"") | I103: =IF(E103>0,SUMIFS('Fiscal Calculation'!AN:AN,'Fiscal Calculation'!J:J,'Fiscal by Program'!$J103),"") | J103: 13-1-80
...

Sheet Fiscal Calculation
A1: Formulas | AE1: =1 / (1-0.0875) -> 1.0958904 | AF1: 0 or -0.06 | AV1: FMAP AS OF April 2024 (no change to account for updated FMAP in Dec 24) | AW1: 2024 | AX1: 2025 | AY1: 2026 | AZ1: 2027 | BA1: 2028
A2: 2024 Bill Code Combo | B2: Bill Code Combo or SK with Trend | C2: Attendant Service? | D2: Facility Based | E2: Program Name | F2: Service Category | G2: RT Service Description | H2: Bill Matrix Service Description | I2: CDS | J2: Rolled Up Section /Sort/ RT Descripton ID | K2: Funding Authority | L2: Unit Measure | M2: Units | N2: Adjusted Units (CDS and ISS services) | O2: Payment | P2: Current Rate Effective Date | Q2: Current Rate | R2: Current Attendant Cost | S2: Attendant Cost % | T2: Adjusted Attendant Hours Per Unit of Service | U2: Methodological Attendant Cost Per 15 Min Increment | V2: Methodological Attendant Cost Per Unit of Service | W2: Estimated Fiscal Impact Per Unit of Services | X2: Wages Required for Fiscal Impact | Y2: Rate after Increased Wages and PTB | Z2: Factor for conversion to 15 Min increments | AA2: Attendant hours per 15 Min Unit of Service | AB2: BE Methodological Rate ID | AC2: CFC | AD2: Name of Trend | AE2: MCO Gross up (1 / (1-0.0875)) or FFS 1.0 | AF2: CFC Reduction for FMAP | AG2: Base Year Trended to 2024 | AH2: Base Year Trended to 2025 | AI2: Base Year Trended to 2026 | AJ2: Base Year Trended to 2027 | AK2: Base Year Trended to 2028 | AL2: Title XX | AM2: SFY 26 Est Att Hours | AN2: SFY 27 Est Att Hours | AO2: AF Estimated 2026 Cost | AP2: GR Estimated 2026 Cost | AQ2: AF Estimated 2027 Cost | AR2: GR Estimated 2027 Cost | AV2: Regular | AW2: 0.3987 | AX2: 0.3999 | AY2: 0.4058 | AZ2: 0.4063 | BA2: 0.4063
A3: 717DG0742 | B3: 717DG0742 | C3: Yes | D3: No | E3: CAS | F3: CAS/FC/PHC PAS | G3: =INDEX('[4]RT Description to Bill Matix'!$D:$D,MATCH(A3,'[4]RT Description to Bill Matix'!$M:$M,0)) -> CAS/FC/PAS/PHC PRIORITY | H3: PAS COMMUNITY ATTENDANT SERVICES (1929B) LVL 2 (PRIORITY) (AO) | J3: {=INDEX('Rate Table Service Desc XWalk'!F:F,MATCH(1,(G3='Rate Table Service Desc XWalk'!B:B)*(E3='Rate Table Service Desc XWalk'!A:A),0))} -> 13-1-8 | K3: =INDEX('[5]Combined Bill Code List'!$A:$A,MATCH(A3,'[5]Combined Bill Code List'!$F:$F,0)) -> State Plan (Title XIX) | L3: =INDEX('[6]Rate History'!$P:$P,MATCH(A3,'[6]Rate History'!$F:$F,0)) -> 1 hour | M3: =INDEX('[7]PDF DB Service Pivot'!$C:$C,MATCH(B3,'[7]PDF DB Service Pivot'!$B:$B,0)) -> 670573.75 | N3: =IF(ISNUMBER(FIND("ISS",F3)),IF(I3="Yes",((M3/Q3)/6)*12,(M3/6)*12),IF(AND(I3="Yes",M3=O3),M3/Q3,M3)) -> 670573.75 | O3: =INDEX('[7]PDF DB Service Pivot'!$D:$D,MATCH(B3,'[7]PDF DB Service Pivot'!$B:$B,0)) -> 8827649.8 | P3: 45170 | Q3: 14 | R3: 11.75 | S3: =_xlfn.IFNA(R3/Q3,"") -> 0.83928571 | T3: =INDEX('[8]Billable Services'!$P:$P,MATCH(A3,'[8]Billable Services'!$S:$S,0)) -> 1 | U3: =ROUND(V3/Z3,2) -> 0 | V3: {=_xlfn.IFS('Fiscal by Program'!$B$7<10.61,0,'Fiscal by Program'!$B$7>10.6,(ROUND('Fiscal by Program'!$B$7*(1+IF(D3="Yes",'Fiscal by Program'!$B$9,'Fiscal by Program'!$B$8))*T3,2)))} -> 0 | W3: =IF(V3-R3<0,0,V3-R3) -> 0 | X3: =ROUND((R3/(1+IF(D3="Yes",'Fiscal by Program'!$B$9,'Fiscal by Program'!$B$8))),2)+0.01 -> 10.62 | Y3: =Q3+W3 -> 14 | Z3: 4 | AA3: =T3/Z3 -> 0.25 | AB3: =INDEX('[9]Service List'!$K:$K,MATCH(A3,'[9]Service List'!$F:$F,0)) -> 5 | AC3: =INDEX('[5]Combined Bill Code List'!$P:$P,MATCH(A3,'[5]Combined Bill Code List'!$F:$F,0)) -> 0 | AD3: CAS | AE3: 1 | AF3: 0 | AG3: =ROUND(INDEX('All Trends'!D:D,MATCH($AD3,'All Trends'!$C:$C,0)),4) -> 0.9428 | AH3: =ROUND(INDEX('All Trends'!E:E,MATCH($AD3,'All Trends'!$C:$C,0)),4) -> 1.049 | AI3: =ROUND(INDEX('All Trends'!F:F,MATCH($AD3,'All Trends'!$C:$C,0)),4) -> 1.0459 | AJ3: =ROUND(INDEX('All Trends'!G:G,MATCH($AD3,'All Trends'!$C:$C,0)),4) -> 1.0566 | AK3: =ROUND(INDEX('All Trends'!H:H,MATCH($AD3,'All Trends'!$C:$C,0)),4) -> 1.0747 | AL3: No | AM3: =IF(C3="Yes",ROUND(T3*N3*AI3,2),0) -> 701353.09 | AN3: =IF(C3="Yes",ROUND(T3*N3*AJ3,2),0) -> 708528.22 | AO3: =IF(C3="Yes",ROUND((W3*N3*AI3),2),0) -> 0 | AP3: =IF(C3="Yes",IF($AL3="No",ROUND(($AO3*($AY$2+$AF3)),2),ROUND($AO3,2)),0) -> 0 | AQ3: =IF(C3="Yes",ROUND((W3*N3*AJ3),2),0) -> 0 | AR3: =IF(C3="Yes",IF($AL3="No",ROUND(($AQ3*($AZ$2+$AF3)),2),ROUND($AQ3,2)),0) -> 0
A4: 717DG0743 | B4: 717DG0743 | C4: Yes | D4: No | E4: CAS | F4: CAS/FC/PHC PAS | G4: =INDEX('[4]RT Description to Bill Matix'!$D:$D,MATCH(A4,'[4]RT Description to Bill Matix'!$M:$M,0)) -> CAS/FC/PAS/PHC NON-PRIORITY | H4: PAS COMMUNITY ATTENDANT SERVICES (1929B) LVL 1 (NON-PRIORITY) (AO) | J4: {=INDEX('Rate Table Service Desc XWalk'!F:F,MATCH(1,(G4='Rate Table Service Desc XWalk'!B:B)*(E4='Rate Table Service Desc XWalk'!A:A),0))} -> 13-1-7 | K4: =INDEX('[5]Combined Bill Code List'!$A:$A,MATCH(A4,'[5]Combined Bill Code List'!$F:$F,0)) -> State Plan (Title XIX) | L4: =INDEX('[6]Rate History'!$P:$P,MATCH(A4,'[6]Rate History'!$F:$F,0)) -> 1 hour | M4: =INDEX('[7]PDF DB Service Pivot'!$C:$C,MATCH(B4,'[7]PDF DB Service Pivot'!$B:$B,0)) -> 73113779 | N4: =IF(ISNUMBER(FIND("ISS",F4)),IF(I4="Yes",((M4/Q4)/6)*12,(M4/6)*12),IF(AND(I4="Yes",M4=O4),M4/Q4,M4)) -> 73113779 | O4: =INDEX('[7]PDF DB Service Pivot'!$D:$D,MATCH(B4,'[7]PDF DB Service Pivot'!$B:$B,0)) -> 9.4913459e+08 | P4: 45170 | Q4: 13.84 | R4: 11.77 | S4: =_xlfn.IFNA(R4/Q4,"") -> 0.85043353 | T4: =INDEX('[8]Billable Services'!$P:$P,MATCH(A4,'[8]Billable Services'!$S:$S,0)) -> 1 | U4: =ROUND(V4/Z4,2) -> 0 | V4: {=_xlfn.IFS('Fiscal by Program'!$B$7<10.61,0,'Fiscal by Program'!$B$7>10.6,(ROUND('Fiscal by Program'!$B$7*(1+IF(D4="Yes",'Fiscal by Program'!$B$9,'Fiscal by Program'!$B$8))*T4,2)))} -> 0 | W4: =IF(V4-R4<0,0,V4-R4) -> 0 | X4: =ROUND((R4/(1+IF(D4="Yes",'Fiscal by Program'!$B$9,'Fiscal by Program'!$B$8))),2)+0.01 -> 10.64 | Y4: =Q4+W4 -> 13.84 | Z4: 4 | AA4: =T4/Z4 -> 0.25 | AB4: =INDEX('[9]Service List'!$K:$K,MATCH(A4,'[9]Service List'!$F:$F,0)) -> 4 | AC4: =INDEX('[5]Combined Bill Code List'!$P:$P,MATCH(A4,'[5]Combined Bill Code List'!$F:$F,0)) -> 0 | AD4: CAS | AE4: 1 | AF4: 0 | AG4: =ROUND(INDEX('All Trends'!D:D,MATCH($AD4,'All Trends'!$C:$C,0)),4) -> 0.9428 | AH4: =ROUND(INDEX('All Trends'!E:E,MATCH($AD4,'All Trends'!$C:$C,0)),4) -> 1.049 | AI4: =ROUND(INDEX('All Trends'!F:F,MATCH($AD4,'All Trends'!$C:$C,0)),4) -> 1.0459 | AJ4: =ROUND(INDEX('All Trends'!G:G,MATCH($AD4,'All Trends'!$C:$C,0)),4) -> 1.0566 | AK4: =ROUND(INDEX('All Trends'!H:H,MATCH($AD4,'All Trends'!$C:$C,0)),4) -> 1.0747 | AL4: No | AM4: =IF(C4="Yes",ROUND(T4*N4*AI4,2),0) -> 76469701 | AN4: =IF(C4="Yes",ROUND(T4*N4*AJ4,2),0) -> 77252018 | AO4: =IF(C4="Yes",ROUND((W4*N4*AI4),2),0) -> 0 | AP4: =IF(C4="Yes",IF($AL4="No",ROUND(($AO4*($AY$2+$AF4)),2),ROUND($AO4,2)),0) -> 0 | AQ4: =IF(C4="Yes",ROUND((W4*N4*AJ4),2),0) -> 0 | AR4: =IF(C4="Yes",IF($AL4="No",ROUND(($AQ4*($AZ$2+$AF4)),2),ROUND($AQ4,2)),0) -> 0
A5: 717DVG0748 | B5: 717DVG0748 | C5: Yes | D5: No | E5: CAS | F5: CAS/FC/PHC PAS | G5: =INDEX('[4]RT Description to Bill Matix'!$D:$D,MATCH(A5,'[4]RT Description to Bill Matix'!$M:$M,0)) -> CDS CAS/FC/PAS/PHC PRIORITY | H5: COMMUNITY ATTENDANT SERVICES (1929B) LEVEL 2 (PRIORITY) (CDS) | I5: Yes | J5: {=INDEX('Rate Table Service Desc XWalk'!F:F,MATCH(1,(G5='Rate Table Service Desc XWalk'!B:B)*(E5='Rate Table Service Desc XWalk'!A:A),0))} -> 13-5-117 | K5: =INDEX('[5]Combined Bill Code List'!$A:$A,MATCH(A5,'[5]Combined Bill Code List'!$F:$F,0)) -> State Plan (Title XIX) | L5: =INDEX('[6]Rate History'!$P:$P,MATCH(A5,'[6]Rate History'!$F:$F,0)) -> 1 hour | M5: =INDEX('[7]PDF DB Service Pivot'!$C:$C,MATCH(B5,'[7]PDF DB Service Pivot'!$B:$B,0)) -> 149974.35 | N5: =IF(ISNUMBER(FIND("ISS",F5)),IF(I5="Yes",((M5/Q5)/6)*12,(M5/6)*12),IF(AND(I5="Yes",M5=O5),M5/Q5,M5)) -> 11361.693 | O5: =INDEX('[7]PDF DB Service Pivot'!$D:$D,MATCH(B5,'[7]PDF DB Service Pivot'!$B:$B,0)) -> 149974.35 | P5: 45170 | Q5: 13.2 | R5: 11.75 | S5: =_xlfn.IFNA(R5/Q5,"") -> 0.89015152 | T5: 1 | U5: =ROUND(V5/Z5,2) -> 0 | V5: {=_xlfn.IFS('Fiscal by Program'!$B$7<10.61,0,'Fiscal by Program'!$B$7>10.6,(ROUND('Fiscal by Program'!$B$7*(1+IF(D5="Yes",'Fiscal by Program'!$B$9,'Fiscal by Program'!$B$8))*T5,2)))} -> 0 | W5: =IF(V5-R5<0,0,V5-R5) -> 0 | X5: =ROUND((R5/(1+IF(D5="Yes",'Fiscal by Program'!$B$9,'Fiscal by Program'!$B$8))),2)+0.01 -> 10.62 | Y5: =Q5+W5 -> 13.2 | Z5: 4 | AA5: =T5/Z5 -> 0.25 | AB5: =INDEX('[9]Service List'!$K:$K,MATCH(A5,'[9]Service List'!$F:$F,0)) -> 7 | AC5: =INDEX('[5]Combined Bill Code List'!$P:$P,MATCH(A5,'[5]Combined Bill Code List'!$F:$F,0)) -> 0 | AD5: CAS | AE5: 1 | AF5: 0 | AG5: =ROUND(INDEX('All Trends'!D:D,MATCH($AD5,'All Trends'!$C:$C,0)),4) -> 0.9428 | AH5: =ROUND(INDEX('All Trends'!E:E,MATCH($AD5,'All Trends'!$C:$C,0)),4) -> 1.049 | AI5: =ROUND(INDEX('All Trends'!F:F,MATCH($AD5,'All Trends'!$C:$C,0)),4) -> 1.0459 | AJ5: =ROUND(INDEX('All Trends'!G:G,MATCH($AD5,'All Trends'!$C:$C,0)),4) -> 1.0566 | AK5: =ROUND(INDEX('All Trends'!H:H,MATCH($AD5,'All Trends'!$C:$C,0)),4) -> 1.0747 | AL5: No | AM5: =IF(C5="Yes",ROUND(T5*N5*AI5,2),0) -> 11883.19 | AN5: =IF(C5="Yes",ROUND(T5*N5*AJ5,2),0) -> 12004.77 | AO5: =IF(C5="Yes",ROUND((W5*N5*AI5),2),0) -> 0 | AP5: =IF(C5="Yes",IF($AL5="No",ROUND(($AO5*($AY$2+$AF5)),2),ROUND($AO5,2)),0) -> 0 | AQ5: =IF(C5="Yes",ROUND((W5*N5*AJ5),2),0) -> 0 | AR5: =IF(C5="Yes",IF($AL5="No",ROUND(($AQ5*($AZ$2+$AF5)),2),ROUND($AQ5,2)),0) -> 0
A6: 717DVG0749 | B6: 717DVG0749 | C6: Yes | D6: No | E6: CAS | F6: CAS/FC/PHC PAS | G6: =INDEX('[4]RT Description to Bill Matix'!$D:$D,MATCH(A6,'[4]RT Description to Bill Matix'!$M:$M,0)) -> CDS CAS/FC/PAS/PHC NON-PRIORITY | H6: COMMUNITY ATTENDANT SERVICES (1929B) LEVEL 1 (NON-PRIORITY) (CDS) | I6: Yes | J6: {=INDEX('Rate Table Service Desc XWalk'!F:F,MATCH(1,(G6='Rate Table Service Desc XWalk'!B:B)*(E6='Rate Table Service Desc XWalk'!A:A),0))} -> 13-5-116 | K6: =INDEX('[5]Combined Bill Code List'!$A:$A,MATCH(A6,'[5]Combined Bill Code List'!$F:$F,0)) -> State Plan (Title XIX) | L6: =INDEX('[6]Rate History'!$P:$P,MATCH(A6,'[6]Rate History'!$F:$F,0)) -> 1 hour | M6: =INDEX('[7]PDF DB Service Pivot'!$C:$C,MATCH(B6,'[7]PDF DB Service Pivot'!$B:$B,0)) -> 6420811.2 | N6: =IF(ISNUMBER(FIND("ISS",F6)),IF(I6="Yes",((M6/Q6)/6)*12,(M6/6)*12),IF(AND(I6="Yes",M6=O6),M6/Q6,M6)) -> 492393.5 | O6: =INDEX('[7]PDF DB Service Pivot'!$D:$D,MATCH(B6,'[7]PDF DB Service Pivot'!$B:$B,0)) -> 6420811.2 | P6: 45170 | Q6: 13.04 | R6: 11.77 | S6: =_xlfn.IFNA(R6/Q6,"") -> 0.90260736 | T6: 1 | U6: =ROUND(V6/Z6,2) -> 0 | V6: {=_xlfn.IFS('Fiscal by Program'!$B$7<10.61,0,'Fiscal by Program'!$B$7>10.6,(ROUND('Fiscal by Program'!$B$7*(1+IF(D6="Yes",'Fiscal by Program'!$B$9,'Fiscal by Program'!$B$8))*T6,2)))} -> 0 | W6: =IF(V6-R6<0,0,V6-R6) -> 0 | X6: =ROUND((R6/(1+IF(D6="Yes",'Fiscal by Program'!$B$9,'Fiscal by Program'!$B$8))),2)+0.01 -> 10.64 | Y6: =Q6+W6 -> 13.04 | Z6: 4 | AA6: =T6/Z6 -> 0.25 | AB6: =INDEX('[9]Service List'!$K:$K,MATCH(A6,'[9]Service List'!$F:$F,0)) -> 6 | AC6: =INDEX('[5]Combined Bill Code List'!$P:$P,MATCH(A6,'[5]Combined Bill Code List'!$F:$F,0)) -> 0 | AD6: CAS | AE6: 1 | AF6: 0 | AG6: =ROUND(INDEX('All Trends'!D:D,MATCH($AD6,'All Trends'!$C:$C,0)),4) -> 0.9428 | AH6: =ROUND(INDEX('All Trends'!E:E,MATCH($AD6,'All Trends'!$C:$C,0)),4) -> 1.049 | AI6: =ROUND(INDEX('All Trends'!F:F,MATCH($AD6,'All Trends'!$C:$C,0)),4) -> 1.0459 | AJ6: =ROUND(INDEX('All Trends'!G:G,MATCH($AD6,'All Trends'!$C:$C,0)),4) -> 1.0566 | AK6: =ROUND(INDEX('All Trends'!H:H,MATCH($AD6,'All Trends'!$C:$C,0)),4) -> 1.0747 | AL6: No | AM6: =IF(C6="Yes",ROUND(T6*N6*AI6,2),0) -> 514994.36 | AN6: =IF(C6="Yes",ROUND(T6*N6*AJ6,2),0) -> 520262.97 | AO6: =IF(C6="Yes",ROUND((W6*N6*AI6),2),0) -> 0 | AP6: =IF(C6="Yes",IF($AL6="No",ROUND(($AO6*($AY$2+$AF6)),2),ROUND($AO6,2)),0) -> 0 | AQ6: =IF(C6="Yes",ROUND((W6*N6*AJ6),2),0) -> 0 | AR6: =IF(C6="Yes",IF($AL6="No",ROUND(($AQ6*($AZ$2+$AF6)),2),ROUND($AQ6,2)),0) -> 0
A7: 717DVG0750 | B7: 717DVG0750 | C7: Yes | D7: No | E7: CAS | F7: CAS/FC/PHC PAS | G7: =INDEX('[4]RT Description to Bill Matix'!$D:$D,MATCH(A7,'[4]RT Description to Bill Matix'!$M:$M,0)) -> CDS CAS/FC/PAS/PHC NON-PRIORITY | H7: PAS COMMUNITY ATTENDANT SERVICES (CDS) | I7: Yes | J7: {=INDEX('Rate Table Service Desc XWalk'!F:F,MATCH(1,(G7='Rate Table Service Desc XWalk'!B:B)*(E7='Rate Table Service Desc XWalk'!A:A),0))} -> 13-5-116 | K7: =INDEX('[5]Combined Bill Code List'!$A:$A,MATCH(A7,'[5]Combined Bill Code List'!$F:$F,0)) -> State Plan (Title XIX) | L7: =INDEX('[6]Rate History'!$P:$P,MATCH(A7,'[6]Rate History'!$F:$F,0)) -> 1 hour | M7: =INDEX('[7]PDF DB Service Pivot'!$C:$C,MATCH(B7,'[7]PDF DB Service Pivot'!$B:$B,0)) -> 83175.02 | N7: =IF(ISNUMBER(FIND("ISS",F7)),IF(I7="Yes",((M7/Q7)/6)*12,(M7/6)*12),IF(AND(I7="Yes",M7=O7),M7/Q7,M7)) -> 6378.4525 | O7: =INDEX('[7]PDF DB Service Pivot'!$D:$D,MATCH(B7,'[7]PDF DB Service Pivot'!$B:$B,0)) -> 83175.02 | P7: =P6 -> 45170 | Q7: 13.04 | R7: 11.77 | S7: =_xlfn.IFNA(R7/Q7,"") -> 0.90260736 | T7: 1 | U7: =ROUND(V7/Z7,2) -> 0 | V7: {=_xlfn.IFS('Fiscal by Program'!$B$7<10.61,0,'Fiscal by Program'!$B$7>10.6,(ROUND('Fiscal by Program'!$B$7*(1+IF(D7="Yes",'Fiscal by Program'!$B$9,'Fiscal by Program'!$B$8))*T7,2)))} -> 0 | W7: =IF(V7-R7<0,0,V7-R7) -> 0 | X7: =ROUND((R7/(1+IF(D7="Yes",'Fiscal by Program'!$B$9,'Fiscal by Program'!$B$8))),2)+0.01 -> 10.64 | Y7: =Q7+W7 -> 13.04 | Z7: 4 | AA7: =T7/Z7 -> 0.25 | AB7: =INDEX('[9]Service List'!$K:$K,MATCH(A7,'[9]Service List'!$F:$F,0)) -> 1356 | AC7: =INDEX('[5]Combined Bill Code List'!$P:$P,MATCH(A7,'[5]Combined Bill Code List'!$F:$F,0)) -> 0 | AD7: CAS | AE7: 1 | AF7: 0 | AG7: =ROUND(INDEX('All Trends'!D:D,MATCH($AD7,'All Trends'!$C:$C,0)),4) -> 0.9428 | AH7: =ROUND(INDEX('All Trends'!E:E,MATCH($AD7,'All Trends'!$C:$C,0)),4) -> 1.049 | AI7: =ROUND(INDEX('All Trends'!F:F,MATCH($AD7,'All Trends'!$C:$C,0)),4) -> 1.0459 | AJ7: =ROUND(INDEX('All Trends'!G:G,MATCH($AD7,'All Trends'!$C:$C,0)),4) -> 1.0566 | AK7: =ROUND(INDEX('All Trends'!H:H,MATCH($AD7,'All Trends'!$C:$C,0)),4) -> 1.0747 | AL7: No | AM7: =IF(C7="Yes",ROUND(T7*N7*AI7,2),0) -> 6671.22 | AN7: =IF(C7="Yes",ROUND(T7*N7*AJ7,2),0) -> 6739.47 | AO7: =IF(C7="Yes",ROUND((W7*N7*AI7),2),0) -> 0 | AP7: =IF(C7="Yes",IF($AL7="No",ROUND(($AO7*($AY$2+$AF7)),2),ROUND($AO7,2)),0) -> 0 | AQ7: =IF(C7="Yes",ROUND((W7*N7*AJ7),2),0) -> 0 | AR7: =IF(C7="Yes",IF($AL7="No",ROUND(($AQ7*($AZ$2+$AF7)),2),ROUND($AQ7,2)),0) -> 0
A8: 210BS0107 | B8: 210BS0107 | C8: Yes | D8: No | E8: CLASS | F8: PAS/HAB | G8: =INDEX('[4]RT Description to Bill Matix'!$D:$D,MATCH(A8,'[4]RT Description to Bill Matix'!$M:$M,0)) -> Habilitation | H8: HABILITATION PREVOCATIONAL | J8: {=INDEX('Rate Table Service Desc XWalk'!F:F,MATCH(1,(G8='Rate Table Service Desc XWalk'!B:B)*(E8='Rate Table Service Desc XWalk'!A:A),0))} -> 1-1-26 | K8: =INDEX('[5]Combined Bill Code List'!$A:$A,MATCH(A8,'[5]Combined Bill Code List'!$F:$F,0)) -> 1915(c) waiver | L8: =INDEX('[6]Rate History'!$P:$P,MATCH(A8,'[6]Rate History'!$F:$F,0)) -> 1 hour (ceiling) | M8: =INDEX('[7]PDF DB Service Pivot'!$C:$C,MATCH(B8,'[7]PDF DB Service Pivot'!$B:$B,0)) -> 4952394.6 | N8: =O8/Q8 -> 332505.48 | O8: =INDEX('[7]PDF DB Service Pivot'!$D:$D,MATCH(B8,'[7]PDF DB Service Pivot'!$B:$B,0)) -> 4974282 | P8: 45170 | Q8: 14.96 | R8: 11.75 | S8: =_xlfn.IFNA(R8/Q8,"") -> 0.78542781 | T8: =INDEX('[8]Billable Services'!$P:$P,MATCH(B8,'[8]Billable Services'!$S:$S,0)) -> 1 | U8: =ROUND(V8/Z8,2) -> 0 | V8: {=_xlfn.IFS('Fiscal by Program'!$B$7<10.61,0,'Fiscal by Program'!$B$7>10.6,(ROUND('Fiscal by Program'!$B$7*(1+IF(D8="Yes",'Fiscal by Program'!$B$9,'Fiscal by Program'!$B$8))*T8,2)))} -> 0 | W8: =IF(V8-R8<0,0,V8-R8) -> 0 | X8: =ROUND((R8/(1+IF(D8="Yes",'Fiscal by Program'!$B$9,'Fiscal by Program'!$B$8))),2)+0.01 -> 10.62 | Y8: =Q8+W8 -> 14.96 | Z8: 4 | AA8: =T8/Z8 -> 0.25 | AB8: =INDEX('[9]Service List'!$K:$K,MATCH(A8,'[9]Service List'!$F:$F,0)) -> 36 | AC8: =INDEX('[5]Combined Bill Code List'!$P:$P,MATCH(A8,'[5]Combined Bill Code List'!$F:$F,0)) -> 0 | AD8: CLASS | AE8: 1 | AF8: 0 | AG8: =ROUND(INDEX('All Trends'!D:D,MATCH($AD8,'All Trends'!$C:$C,0)),4) -> 0.9708 | AH8: =ROUND(INDEX('All Trends'!E:E,MATCH($AD8,'All Trends'!$C:$C,0)),4) -> 1.003 | AI8: =ROUND(INDEX('All Trends'!F:F,MATCH($AD8,'All Trends'!$C:$C,0)),4) -> 1.0231 | AJ8: =ROUND(INDEX('All Trends'!G:G,MATCH($AD8,'All Trends'!$C:$C,0)),4) -> 1.0231 | AK8: =ROUND(INDEX('All Trends'!H:H,MATCH($AD8,'All Trends'!$C:$C,0)),4) -> 1.0231 | AL8: No | AM8: =IF(C8="Yes",ROUND(T8*N8*AI8,2),0) -> 340186.36 | AN8: =IF(C8="Yes",ROUND(T8*N8*AJ8,2),0) -> 340186.36 | AO8: =IF(C8="Yes",ROUND((W8*N8*AI8),2),0) -> 0 | AP8: =IF(C8="Yes",IF($AL8="No",ROUND(($AO8*($AY$2+$AF8)),2),ROUND($AO8,2)),0) -> 0 | AQ8: =IF(C8="Yes",ROUND((W8*N8*AJ8),2),0) -> 0 | AR8: =IF(C8="Yes",IF($AL8="No",ROUND(($AQ8*($AZ$2+$AF8)),2),ROUND($AQ8,2)),0) -> 0
A9: 210CFCG1108 | B9: 210CFCG1108 | C9: Yes | D9: No | E9: CLASS | F9: PAS/HAB | G9: =INDEX('[4]RT Description to Bill Matix'!$D:$D,MATCH(A9,'[4]RT Description to Bill Matix'!$M:$M,0)) -> PAS/HAB (CFC) | H9: CFC PAS/HAB | J9: {=INDEX('Rate Table Service Desc XWalk'!F:F,MATCH(1,(G9='Rate Table Service Desc XWalk'!B:B)*(E9='Rate Table Service Desc XWalk'!A:A),0))} -> 1-1-78 | K9: =INDEX('[5]Combined Bill Code List'!$A:$A,MATCH(A9,'[5]Combined Bill Code List'!$F:$F,0)) -> State Plan (Title XIX) | L9: =INDEX('[6]Rate History'!$P:$P,MATCH(A9,'[6]Rate History'!$F:$F,0)) -> 1 hour | M9: =INDEX('[7]PDF DB Service Pivot'!$C:$C,MATCH(B9,'[7]PDF DB Service Pivot'!$B:$B,0)) -> 8801962.1 | N9: =IF(ISNUMBER(FIND("ISS",F9)),IF(I9="Yes",((M9/Q9)/6)*12,(M9/6)*12),IF(AND(I9="Yes",M9=O9),M9/Q9,M9)) -> 8801962.1 | O9: =INDEX('[7]PDF DB Service Pivot'!$D:$D,MATCH(B9,'[7]PDF DB Service Pivot'!$B:$B,0)) -> 1.3646574e+08 | P9: 45170 | Q9: 14.96 | R9: 11.75 | S9: =_xlfn.IFNA(R9/Q9,"") -> 0.78542781 | T9: =INDEX('[8]Billable Services'!$P:$P,MATCH(B9,'[8]Billable Services'!$S:$S,0)) -> 1 | U9: =ROUND(V9/Z9,2) -> 0 | V9: {=_xlfn.IFS('Fiscal by Program'!$B$7<10.61,0,'Fiscal by Program'!$B$7>10.6,(ROUND('Fiscal by Program'!$B$7*(1+IF(D9="Yes",'Fiscal by Program'!$B$9,'Fiscal by Program'!$B$8))*T9,2)))} -> 0 | W9: =IF(V9-R9<0,0,V9-R9) -> 0 | X9: =ROUND((R9/(1+IF(D9="Yes",'Fiscal by Program'!$B$9,'Fiscal by Program'!$B$8))),2)+0.01 -> 10.62 | Y9: =Q9+W9 -> 14.96 | Z9: 4 | AA9: =T9/Z9 -> 0.25 | AB9: =INDEX('[9]Service List'!$K:$K,MATCH(A9,'[9]Service List'!$F:$F,0)) -> 53 | AC9: CFC | AD9: CLASS | AE9: 1 | AF9: -0.06 | AG9: =ROUND(INDEX('All Trends'!D:D,MATCH($AD9,'All Trends'!$C:$C,0)),4) -> 0.9708 | AH9: =ROUND(INDEX('All Trends'!E:E,MATCH($AD9,'All Trends'!$C:$C,0)),4) -> 1.003 | AI9: =ROUND(INDEX('All Trends'!F:F,MATCH($AD9,'All Trends'!$C:$C,0)),4) -> 1.0231 | AJ9: =ROUND(INDEX('All Trends'!G:G,MATCH($AD9,'All Trends'!$C:$C,0)),4) -> 1.0231 | AK9: =ROUND(INDEX('All Trends'!H:H,MATCH($AD9,'All Trends'!$C:$C,0)),4) -> 1.0231 | AL9: No | AM9: =IF(C9="Yes",ROUND(T9*N9*AI9,2),0) -> 9005287.4 | AN9: =IF(C9="Yes",ROUND(T9*N9*AJ9,2),0) -> 9005287.4 | AO9: =IF(C9="Yes",ROUND((W9*N9*AI9),2),0) -> 0 | AP9: =IF(C9="Yes",IF($AL9="No",ROUND(($AO9*($AY$2+$AF9)),2),ROUND($AO9,2)),0) -> 0 | AQ9: =IF(C9="Yes",ROUND((W9*N9*AJ9),2),0) -> 0 | AR9: =IF(C9="Yes",IF($AL9="No",ROUND(($AQ9*($AZ$2+$AF9)),2),ROUND($AQ9,2)),0) -> 0
A10: 210CFVG1109 | B10: 210CFVG1109 | C10: Yes | D10: No | E10: CLASS | F10: PAS/HAB | G10: =INDEX('[4]RT Description to Bill Matix'!$D:$D,MATCH(A10,'[4]RT Description to Bill Matix'!$M:$M,0)) -> CDS PAS/HAB (CFC) | H10: CFC PAS/HAB (CDS) | I10: Yes | J10: {=INDEX('Rate Table Service Desc XWalk'!F:F,MATCH(1,(G10='Rate Table Service Desc XWalk'!B:B)*(E10='Rate Table Service Desc XWalk'!A:A),0))} -> 1-5-142 | K10: =INDEX('[5]Combined Bill Code List'!$A:$A,MATCH(A10,'[5]Combined Bill Code List'!$F:$F,0)) -> State Plan (Title XIX) | L10: =INDEX('[6]Rate History'!$P:$P,MATCH(A10,'[6]Rate History'!$F:$F,0)) -> 1 hour | M10: =INDEX('[7]PDF DB Service Pivot'!$C:$C,MATCH(B10,'[7]PDF DB Service Pivot'!$B:$B,0)) -> 87110157 | N10: =IF(ISNUMBER(FIND("ISS",F10)),IF(I10="Yes",((M10/Q10)/6)*12,(M10/6)*12),IF(AND(I10="Yes",M10=O10),M10/Q10,M10)) -> 6151847.2 | O10: =INDEX('[7]PDF DB Service Pivot'!$D:$D,MATCH(B10,'[7]PDF DB Service Pivot'!$B:$B,0)) -> 87110157 | P10: 45170 | Q10: 14.16 | R10: 11.75 | S10: =_xlfn.IFNA(R10/Q10,"") -> 0.82980226 | T10: 1 | U10: =ROUND(V10/Z10,2) -> 0 | V10: {=_xlfn.IFS('Fiscal by Program'!$B$7<10.61,0,'Fiscal by Program'!$B$7>10.6,(ROUND('Fiscal by Program'!$B$7*(1+IF(D10="Yes",'Fiscal by Program'!$B$9,'Fiscal by Program'!$B$8))*T10,2)))} -> 0 | W10: =IF(V10-R10<0,0,V10-R10) -> 0 | X10: =ROUND((R10/(1+IF(D10="Yes",'Fiscal by Program'!$B$9,'Fiscal by Program'!$B$8))),2)+0.01 -> 10.62 | Y10: =Q10+W10 -> 14.16 | Z10: 4 | AA10: =T10/Z10 -> 0.25 | AB10: =INDEX('[9]Service List'!$K:$K,MATCH(A10,'[9]Service List'!$F:$F,0)) -> 52 | AC10: CFC | AD10: CLASS | AE10: 1 | AF10: -0.06 | AG10: =ROUND(INDEX('All Trends'!D:D,MATCH($AD10,'All Trends'!$C:$C,0)),4) -> 0.9708 | AH10: =ROUND(INDEX('All Trends'!E:E,MATCH($AD10,'All Trends'!$C:$C,0)),4) -> 1.003 | AI10: =ROUND(INDEX('All Trends'!F:F,MATCH($AD10,'All Trends'!$C:$C,0)),4) -> 1.0231 | AJ10: =ROUND(INDEX('All Trends'!G:G,MATCH($AD10,'All Trends'!$C:$C,0)),4) -> 1.0231 | AK10: =ROUND(INDEX('All Trends'!H:H,MATCH($AD10,'All Trends'!$C:$C,0)),4) -> 1.0231 | AL10: No | AM10: =IF(C10="Yes",ROUND(T10*N10*AI10,2),0) -> 6293954.9 | AN10: =IF(C10="Yes",ROUND(T10*N10*AJ10,2),0) -> 6293954.9 | AO10: =IF(C10="Yes",ROUND((W10*N10*AI10),2),0) -> 0 | AP10: =IF(C10="Yes",IF($AL10="No",ROUND(($AO10*($AY$2+$AF10)),2),ROUND($AO10,2)),0) -> 0 | AQ10: =IF(C10="Yes",ROUND((W10*N10*AJ10),2),0) -> 0 | AR10: =IF(C10="Yes",IF($AL10="No",ROUND(($AQ10*($AZ$2+$AF10)),2),ROUND($AQ10,2)),0) -> 0
A11: 211G0100 | B11: 211G0100 | C11: Yes | D11: No | E11: CLASS | F11: In Home Respite | G11: =INDEX('[4]RT Description to Bill Matix'!$D:$D,MATCH(A11,'[4]RT Description to Bill Matix'!$M:$M,0)) -> In Home Respite | H11: RESPITE-IN HOME RESPITE-DSA | J11: {=INDEX('Rate Table Service Desc XWalk'!F:F,MATCH(1,(G11='Rate Table Service Desc XWalk'!B:B)*(E11='Rate Table Service Desc XWalk'!A:A),0))} -> 1-1-55 | K11: =INDEX('[5]Combined Bill Code List'!$A:$A,MATCH(A11,'[5]Combined Bill Code List'!$F:$F,0)) -> 1915(c) waiver | L11: =INDEX('[6]Rate History'!$P:$P,MATCH(A11,'[6]Rate History'!$F:$F,0)) -> 1 day | M11: =INDEX('[7]PDF DB Service Pivot'!$C:$C,MATCH(B11,'[7]PDF DB Service Pivot'!$B:$B,0)) -> 22044.16 | N11: =IF(ISNUMBER(FIND("ISS",F11)),IF(I11="Yes",((M11/Q11)/6)*12,(M11/6)*12),IF(AND(I11="Yes",M11=O11),M11/Q11,M11)) -> 22044.16 | O11: =INDEX('[7]PDF DB Service Pivot'!$D:$D,MATCH(B11,'[7]PDF DB Service Pivot'!$B:$B,0)) -> 5323900.5 | P11: 45170 | Q11: 311.12 | R11: 281.78 | S11: =_xlfn.IFNA(R11/Q11,"") -> 0.90569555 | T11: 24 | U11: =ROUND(V11/Z11,2) -> 0 | V11: {=_xlfn.IFS('Fiscal by Program'!$B$7<10.61,0,'Fiscal by Program'!$B$7>10.6,(ROUND('Fiscal by Program'!$B$7*(1+IF(D11="Yes",'Fiscal by Program'!$B$9,'Fiscal by Program'!$B$8))*T11,2)))} -> 0 | W11: =IF(V11-R11<0,0,V11-R11) -> 0 | X11: =ROUND((R11/(1+IF(D11="Yes",'Fiscal by Program'!$B$9,'Fiscal by Program'!$B$8))),2)+0.01 -> 254.44 | Y11: =Q11+W11 -> 311.12 | Z11: 96 | AA11: =T11/Z11 -> 0.25 | AB11: =INDEX('[9]Service List'!$K:$K,MATCH(A11,'[9]Service List'!$F:$F,0)) -> 39 | AC11: =INDEX('[5]Combined Bill Code List'!$P:$P,MATCH(A11,'[5]Combined Bill Code List'!$F:$F,0)) -> 0 | AD11: CLASS | AE11: 1 | AF11: 0 | AG11: =ROUND(INDEX('All Trends'!D:D,MATCH($AD11,'All Trends'!$C:$C,0)),4) -> 0.9708 | AH11: =ROUND(INDEX('All Trends'!E:E,MATCH($AD11,'All Trends'!$C:$C,0)),4) -> 1.003 | AI11: =ROUND(INDEX('All Trends'!F:F,MATCH($AD11,'All Trends'!$C:$C,0)),4) -> 1.0231 | AJ11: =ROUND(INDEX('All Trends'!G:G,MATCH($AD11,'All Trends'!$C:$C,0)),4) -> 1.0231 | AK11: =ROUND(INDEX('All Trends'!H:H,MATCH($AD11,'All Trends'!$C:$C,0)),4) -> 1.0231 | AL11: No | AM11: =IF(C11="Yes",ROUND(T11*N11*AI11,2),0) -> 541281.12 | AN11: =IF(C11="Yes",ROUND(T11*N11*AJ11,2),0) -> 541281.12 | AO11: =IF(C11="Yes",ROUND((W11*N11*AI11),2),0) -> 0 | AP11: =IF(C11="Yes",IF($AL11="No",ROUND(($AO11*($AY$2+$AF11)),2),ROUND($AO11,2)),0) -> 0 | AQ11: =IF(C11="Yes",ROUND((W11*N11*AJ11),2),0) -> 0 | AR11: =IF(C11="Yes",IF($AL11="No",ROUND(($AQ11*($AZ$2+$AF11)),2),ROUND($AQ11,2)),0) -> 0
A12: 211PVG0197 | B12: 211PVG0197 | C12: Yes | D12: No | E12: CLASS | F12: In Home Respite | G12: =INDEX('[4]RT Description to Bill Matix'!$D:$D,MATCH(A12,'[4]RT Description to Bill Matix'!$M:$M,0)) -> CDS In Home Respite | H12: RESPITE IN-HOME (CDS) | I12: Yes | J12: {=INDEX('Rate Table Service Desc XWalk'!F:F,MATCH(1,(G12='Rate Table Service Desc XWalk'!B:B)*(E12='Rate Table Service Desc XWalk'!A:A),0))} -> 1-5-136 | K12: =INDEX('[5]Combined Bill Code List'!$A:$A,MATCH(A12,'[5]Combined Bill Code List'!$F:$F,0)) -> 1915(c) waiver | L12: =INDEX('[6]Rate History'!$P:$P,MATCH(A12,'[6]Rate History'!$F:$F,0)) -> 1 day | M12: =INDEX('[7]PDF DB Service Pivot'!$C:$C,MATCH(B12,'[7]PDF DB Service Pivot'!$B:$B,0)) -> 5354163.9 | N12: =IF(ISNUMBER(FIND("ISS",F12)),IF(I12="Yes",((M12/Q12)/6)*12,(M12/6)*12),IF(AND(I12="Yes",M12=O12),M12/Q12,M12)) -> 18647.826 | O12: =INDEX('[7]PDF DB Service Pivot'!$D:$D,MATCH(B12,'[7]PDF DB Service Pivot'!$B:$B,0)) -> 5354163.9 | P12: 45170 | Q12: 287.12 | R12: 281.78 | S12: =_xlfn.IFNA(R12/Q12,"") -> 0.9814015 | T12: 24 | U12: =ROUND(V12/Z12,2) -> 0 | V12: {=_xlfn.IFS('Fiscal by Program'!$B$7<10.61,0,'Fiscal by Program'!$B$7>10.6,(ROUND('Fiscal by Program'!$B$7*(1+IF(D12="Yes",'Fiscal by Program'!$B$9,'Fiscal by Program'!$B$8))*T12,2)))} -> 0 | W12: =IF(V12-R12<0,0,V12-R12) -> 0 | X12: =ROUND((R12/(1+IF(D12="Yes",'Fiscal by Program'!$B$9,'Fiscal by Program'!$B$8))),2)+0.01 -> 254.44 | Y12: =Q12+W12 -> 287.12 | Z12: 96 | AA12: =T12/Z12 -> 0.25 | AB12: =INDEX('[9]Service List'!$K:$K,MATCH(A12,'[9]Service List'!$F:$F,0)) -> 38 | AC12: =INDEX('[5]Combined Bill Code List'!$P:$P,MATCH(A12,'[5]Combined Bill Code List'!$F:$F,0)) -> 0 | AD12: CLASS | AE12: 1 | AF12: 0 | AG12: =ROUND(INDEX('All Trends'!D:D,MATCH($AD12,'All Trends'!$C:$C,0)),4) -> 0.9708 | AH12: =ROUND(INDEX('All Trends'!E:E,MATCH($AD12,'All Trends'!$C:$C,0)),4) -> 1.003 | AI12: =ROUND(INDEX('All Trends'!F:F,MATCH($AD12,'All Trends'!$C:$C,0)),4) -> 1.0231 | AJ12: =ROUND(INDEX('All Trends'!G:G,MATCH($AD12,'All Trends'!$C:$C,0)),4) -> 1.0231 | AK12: =ROUND(INDEX('All Trends'!H:H,MATCH($AD12,'All Trends'!$C:$C,0)),4) -> 1.0231 | AL12: No | AM12: =IF(C12="Yes",ROUND(T12*N12*AI12,2),0) -> 457886.18 | AN12: =IF(C12="Yes",ROUND(T12*N12*AJ12,2),0) -> 457886.18 | AO12: =IF(C12="Yes",ROUND((W12*N12*AI12),2),0) -> 0 | AP12: =IF(C12="Yes",IF($AL12="No",ROUND(($AO12*($AY$2+$AF12)),2),ROUND($AO12,2)),0) -> 0 | AQ12: =IF(C12="Yes",ROUND((W12*N12*AJ12),2),0) -> 0 | AR12: =IF(C12="Yes",IF($AL12="No",ROUND(($AQ12*($AZ$2+$AF12)),2),ROUND($AQ12,2)),0) -> 0
A13: 237H2025 | B13: 237H2025 | C13: Yes | D13: No | E13: CLASS | F13: Employment Services | G13: =INDEX('[4]RT Description to Bill Matix'!$D:$D,MATCH(A13,'[4]RT Description to Bill Matix'!$M:$M,0)) -> Employment Assistance and Supported Employment | H13: CLASS SUPPORTED EMPLOYMENT (AO) | J13: {=INDEX('Rate Table Service Desc XWalk'!F:F,MATCH(1,(G13='Rate Table Service Desc XWalk'!B:B)*(E13='Rate Table Service Desc XWalk'!A:A),0))} -> 1-1-23 | K13: =INDEX('[5]Combined Bill Code List'!$A:$A,MATCH(A13,'[5]Combined Bill Code List'!$F:$F,0)) -> 1915(c) waiver | L13: =INDEX('[6]Rate History'!$P:$P,MATCH(A13,'[6]Rate History'!$F:$F,0)) -> 1 hour | M13: =INDEX('[7]PDF DB Service Pivot'!$C:$C,MATCH(B13,'[7]PDF DB Service Pivot'!$B:$B,0)) -> 696 | N13: =IF(ISNUMBER(FIND("ISS",F13)),IF(I13="Yes",((M13/Q13)/6)*12,(M13/6)*12),IF(AND(I13="Yes",M13=O13),M13/Q13,M13)) -> 696 | O13: =INDEX('[7]PDF DB Service Pivot'!$D:$D,MATCH(B13,'[7]PDF DB Service Pivot'!$B:$B,0)) -> 19362.72 | P13: 41518 | Q13: 26.07 | R13: 19.07 | S13: =_xlfn.IFNA(R13/Q13,"") -> 0.73149214 | T13: =INDEX('[8]Billable Services'!$P:$P,MATCH(B13,'[8]Billable Services'!$S:$S,0)) -> 1 | U13: =ROUND(V13/Z13,2) -> 0 | V13: {=_xlfn.IFS('Fiscal by Program'!$B$7<10.61,0,'Fiscal by Program'!$B$7>10.6,(ROUND('Fiscal by Program'!$B$7*(1+IF(D13="Yes",'Fiscal by Program'!$B$9,'Fiscal by Program'!$B$8))*T13,2)))} -> 0 | W13: =IF(V13-R13<0,0,V13-R13) -> 0 | X13: =ROUND((R13/(1+IF(D13="Yes",'Fiscal by Program'!$B$9,'Fiscal by Program'!$B$8))),2)+0.01 -> 17.23 | Y13: =Q13+W13 -> 26.07 | Z13: 4 | AA13: =T13/Z13 -> 0.25 | AB13: =INDEX('[9]Service List'!$K:$K,MATCH(A13,'[9]Service List'!$F:$F,0)) -> 24 | AC13: =INDEX('[5]Combined Bill Code List'!$P:$P,MATCH(A13,'[5]Combined Bill Code List'!$F:$F,0)) -> 0 | AD13: CLASS | AE13: 1 | AF13: 0 | AG13: =ROUND(INDEX('All Trends'!D:D,MATCH($AD13,'All Trends'!$C:$C,0)),4) -> 0.9708 | AH13: =ROUND(INDEX('All Trends'!E:E,MATCH($AD13,'All Trends'!$C:$C,0)),4) -> 1.003 | AI13: =ROUND(INDEX('All Trends'!F:F,MATCH($AD13,'All Trends'!$C:$C,0)),4) -> 1.0231 | AJ13: =ROUND(INDEX('All Trends'!G:G,MATCH($AD13,'All Trends'!$C:$C,0)),4) -> 1.0231 | AK13: =ROUND(INDEX('All Trends'!H:H,MATCH($AD13,'All Trends'!$C:$C,0)),4) -> 1.0231 | AL13: No | AM13: =IF(C13="Yes",ROUND(T13*N13*AI13,2),0) -> 712.08 | AN13: =IF(C13="Yes",ROUND(T13*N13*AJ13,2),0) -> 712.08 | AO13: =IF(C13="Yes",ROUND((W13*N13*AI13),2),0) -> 0 | AP13: =IF(C13="Yes",IF($AL13="No",ROUND(($AO13*($AY$2+$AF13)),2),ROUND($AO13,2)),0) -> 0 | AQ13: =IF(C13="Yes",ROUND((W13*N13*AJ13),2),0) -> 0 | AR13: =IF(C13="Yes",IF($AL13="No",ROUND(($AQ13*($AZ$2+$AF13)),2),ROUND($AQ13,2)),0) -> 0
A14: 237VH2027 | B14: 237VH2027 | C14: Yes | D14: No | E14: CLASS | F14: Employment Services | G14: =INDEX('[4]RT Description to Bill Matix'!$D:$D,MATCH(A14,'[4]RT Description to Bill Matix'!$M:$M,0)) -> CDS Employment Assistance and Supported Employment | H14: CLASS (CDS) -SUPPORTED EMPLOYMENT | I14: Yes | J14: {=INDEX('Rate Table Service Desc XWalk'!F:F,MATCH(1,(G14='Rate Table Service Desc XWalk'!B:B)*(E14='Rate Table Service Desc XWalk'!A:A),0))} -> 1-5-121 | K14: =INDEX('[5]Combined Bill Code List'!$A:$A,MATCH(A14,'[5]Combined Bill Code List'!$F:$F,0)) -> 1915(c) waiver | L14: =INDEX('[6]Rate History'!$P:$P,MATCH(A14,'[6]Rate History'!$F:$F,0)) -> 1 hour | M14: =INDEX('[7]PDF DB Service Pivot'!$C:$C,MATCH(B14,'[7]PDF DB Service Pivot'!$B:$B,0)) -> 260896.24 | N14: =IF(ISNUMBER(FIND("ISS",F14)),IF(I14="Yes",((M14/Q14)/6)*12,(M14/6)*12),IF(AND(I14="Yes",M14=O14),M14/Q14,M14)) -> 10324.347 | O14: =INDEX('[7]PDF DB Service Pivot'!$D:$D,MATCH(B14,'[7]PDF DB Service Pivot'!$B:$B,0)) -> 260896.24 | P14: 41518 | Q14: 25.27 | R14: 18.484806 | S14: =_xlfn.IFNA(R14/Q14,"") -> 0.73149214 | T14: 1 | U14: =ROUND(V14/Z14,2) -> 0 | V14: {=_xlfn.IFS('Fiscal by Program'!$B$7<10.61,0,'Fiscal by Program'!$B$7>10.6,(ROUND('Fiscal by Program'!$B$7*(1+IF(D14="Yes",'Fiscal by Program'!$B$9,'Fiscal by Program'!$B$8))*T14,2)))} -> 0 | W14: =IF(V14-R14<0,0,V14-R14) -> 0 | X14: =ROUND((R14/(1+IF(D14="Yes",'Fiscal by Program'!$B$9,'Fiscal by Program'!$B$8))),2)+0.01 -> 16.7 | Y14: =Q14+W14 -> 25.27 | Z14: 4 | AA14: =T14/Z14 -> 0.25 | AB14: =INDEX('[9]Service List'!$K:$K,MATCH(A14,'[9]Service List'!$F:$F,0)) -> 23 | AC14: =INDEX('[5]Combined Bill Code List'!$P:$P,MATCH(A14,'[5]Combined Bill Code List'!$F:$F,0)) -> 0 | AD14: CLASS | AE14: 1 | AF14: 0 | AG14: =ROUND(INDEX('All Trends'!D:D,MATCH($AD14,'All Trends'!$C:$C,0)),4) -> 0.9708 | AH14: =ROUND(INDEX('All Trends'!E:E,MATCH($AD14,'All Trends'!$C:$C,0)),4) -> 1.003 | AI14: =ROUND(INDEX('All Trends'!F:F,MATCH($AD14,'All Trends'!$C:$C,0)),4) -> 1.0231 | AJ14: =ROUND(INDEX('All Trends'!G:G,MATCH($AD14,'All Trends'!$C:$C,0)),4) -> 1.0231 | AK14: =ROUND(INDEX('All Trends'!H:H,MATCH($AD14,'All Trends'!$C:$C,0)),4) -> 1.0231 | AL14: No | AM14: =IF(C14="Yes",ROUND(T14*N14*AI14,2),0) -> 10562.84 | AN14: =IF(C14="Yes",ROUND(T14*N14*AJ14,2),0) -> 10562.84 | AO14: =IF(C14="Yes",ROUND((W14*N14*AI14),2),0) -> 0 | AP14: =IF(C14="Yes",IF($AL14="No",ROUND(($AO14*($AY$2+$AF14)),2),ROUND($AO14,2)),0) -> 0 | AQ14: =IF(C14="Yes",ROUND((W14*N14*AJ14),2),0) -> 0 | AR14: =IF(C14="Yes",IF($AL14="No",ROUND(($AQ14*($AZ$2+$AF14)),2),ROUND($AQ14,2)),0) -> 0
A15: 248G0248 | B15: 248G0248 | C15: Yes | D15: No | E15: CLASS | F15: PAS/HAB | G15: =INDEX('[4]RT Description to Bill Matix'!$D:$D,MATCH(A15,'[4]RT Description to Bill Matix'!$M:$M,0)) -> Habilitation | H15: HAB TRANSPORTATION | J15: {=INDEX('Rate Table Service Desc XWalk'!F:F,MATCH(1,(G15='Rate Table Service Desc XWalk'!B:B)*(E15='Rate Table Service Desc XWalk'!A:A),0))} -> 1-1-26 | K15: =INDEX('[5]Combined Bill Code List'!$A:$A,MATCH(A15,'[5]Combined Bill Code List'!$F:$F,0)) -> 1915(c) waiver | L15: =INDEX('[6]Rate History'!$P:$P,MATCH(A15,'[6]Rate History'!$F:$F,0)) -> 1 hour | M15: =INDEX('[7]PDF DB Service Pivot'!$C:$C,MATCH(B15,'[7]PDF DB Service Pivot'!$B:$B,0)) -> 3931.65 | N15: =IF(ISNUMBER(FIND("ISS",F15)),IF(I15="Yes",((M15/Q15)/6)*12,(M15/6)*12),IF(AND(I15="Yes",M15=O15),M15/Q15,M15)) -> 3931.65 | O15: =INDEX('[7]PDF DB Service Pivot'!$D:$D,MATCH(B15,'[7]PDF DB Service Pivot'!$B:$B,0)) -> 60328.66 | P15: 45170 | Q15: 14.96 | R15: 11.75 | S15: =_xlfn.IFNA(R15/Q15,"") -> 0.78542781 | T15: =INDEX('[8]Billable Services'!$P:$P,MATCH(B15,'[8]Billable Services'!$S:$S,0)) -> 1 | U15: =ROUND(V15/Z15,2) -> 0 | V15: {=_xlfn.IFS('Fiscal by Program'!$B$7<10.61,0,'Fiscal by Program'!$B$7>10.6,(ROUND('Fiscal by Program'!$B$7*(1+IF(D15="Yes",'Fiscal by Program'!$B$9,'Fiscal by Program'!$B$8))*T15,2)))} -> 0 | W15: =IF(V15-R15<0,0,V15-R15) -> 0 | X15: =ROUND((R15/(1+IF(D15="Yes",'Fiscal by Program'!$B$9,'Fiscal by Program'!$B$8))),2)+0.01 -> 10.62 | Y15: =Q15+W15 -> 14.96 | Z15: 4 | AA15: =T15/Z15 -> 0.25 | AB15: =INDEX('[9]Service List'!$K:$K,MATCH(A15,'[9]Service List'!$F:$F,0)) -> 35 | AC15: =INDEX('[5]Combined Bill Code List'!$P:$P,MATCH(A15,'[5]Combined Bill Code List'!$F:$F,0)) -> 0 | AD15: CLASS | AE15: 1 | AF15: 0 | AG15: =ROUND(INDEX('All Trends'!D:D,MATCH($AD15,'All Trends'!$C:$C,0)),4) -> 0.9708 | AH15: =ROUND(INDEX('All Trends'!E:E,MATCH($AD15,'All Trends'!$C:$C,0)),4) -> 1.003 | AI15: =ROUND(INDEX('All Trends'!F:F,MATCH($AD15,'All Trends'!$C:$C,0)),4) -> 1.0231 | AJ15: =ROUND(INDEX('All Trends'!G:G,MATCH($AD15,'All Trends'!$C:$C,0)),4) -> 1.0231 | AK15: =ROUND(INDEX('All Trends'!H:H,MATCH($AD15,'All Trends'!$C:$C,0)),4) -> 1.0231 | AL15: No | AM15: =IF(C15="Yes",ROUND(T15*N15*AI15,2),0) -> 4022.47 | AN15: =IF(C15="Yes",ROUND(T15*N15*AJ15,2),0) -> 4022.47 | AO15: =IF(C15="Yes",ROUND((W15*N15*AI15),2),0) -> 0 | AP15: =IF(C15="Yes",IF($AL15="No",ROUND(($AO15*($AY$2+$AF15)),2),ROUND($AO15,2)),0) -> 0 | AQ15: =IF(C15="Yes",ROUND((W15*N15*AJ15),2),0) -> 0 | AR15: =IF(C15="Yes",IF($AL15="No",ROUND(($AQ15*($AZ$2+$AF15)),2),ROUND($AQ15,2)),0) -> 0
A16: 248VG0249 | B16: 248VG0249 | C16: Yes | D16: No | E16: CLASS | F16: PAS/HAB | G16: =INDEX('[4]RT Description to Bill Matix'!$D:$D,MATCH(A16,'[4]RT Description to Bill Matix'!$M:$M,0)) -> CDS Habilitation | H16: HAB TRANSPORTATION (CDS) | I16: Yes | J16: {=INDEX('Rate Table Service Desc XWalk'!F:F,MATCH(1,(G16='Rate Table Service Desc XWalk'!B:B)*(E16='Rate Table Service Desc XWalk'!A:A),0))} -> 1-5-122 | K16: =INDEX('[5]Combined Bill Code List'!$A:$A,MATCH(A16,'[5]Combined Bill Code List'!$F:$F,0)) -> 1915(c) waiver | L16: =INDEX('[6]Rate History'!$P:$P,MATCH(A16,'[6]Rate History'!$F:$F,0)) -> 1 hour | M16: =INDEX('[7]PDF DB Service Pivot'!$C:$C,MATCH(B16,'[7]PDF DB Service Pivot'!$B:$B,0)) -> 171886.79 | N16: =IF(ISNUMBER(FIND("ISS",F16)),IF(I16="Yes",((M16/Q16)/6)*12,(M16/6)*12),IF(AND(I16="Yes",M16=O16),M16/Q16,M16)) -> 12138.898 | O16: =INDEX('[7]PDF DB Service Pivot'!$D:$D,MATCH(B16,'[7]PDF DB Service Pivot'!$B:$B,0)) -> 171886.79 | P16: 45170 | Q16: 14.16 | R16: 11.75 | S16: =_xlfn.IFNA(R16/Q16,"") -> 0.82980226 | T16: 1 | U16: =ROUND(V16/Z16,2) -> 0 | V16: {=_xlfn.IFS('Fiscal by Program'!$B$7<10.61,0,'Fiscal by Program'!$B$7>10.6,(ROUND('Fiscal by Program'!$B$7*(1+IF(D16="Yes",'Fiscal by Program'!$B$9,'Fiscal by Program'!$B$8))*T16,2)))} -> 0 | W16: =IF(V16-R16<0,0,V16-R16) -> 0 | X16: =ROUND((R16/(1+IF(D16="Yes",'Fiscal by Program'!$B$9,'Fiscal by Program'!$B$8))),2)+0.01 -> 10.62 | Y16: =Q16+W16 -> 14.16 | Z16: 4 | AA16: =T16/Z16 -> 0.25 | AB16: =INDEX('[9]Service List'!$K:$K,MATCH(A16,'[9]Service List'!$F:$F,0)) -> 33 | AC16: =INDEX('[5]Combined Bill Code List'!$P:$P,MATCH(A16,'[5]Combined Bill Code List'!$F:$F,0)) -> 0 | AD16: CLASS | AE16: 1 | AF16: 0 | AG16: =ROUND(INDEX('All Trends'!D:D,MATCH($AD16,'All Trends'!$C:$C,0)),4) -> 0.9708 | AH16: =ROUND(INDEX('All Trends'!E:E,MATCH($AD16,'All Trends'!$C:$C,0)),4) -> 1.003 | AI16: =ROUND(INDEX('All Trends'!F:F,MATCH($AD16,'All Trends'!$C:$C,0)),4) -> 1.0231 | AJ16: =ROUND(INDEX('All Trends'!G:G,MATCH($AD16,'All Trends'!$C:$C,0)),4) -> 1.0231 | AK16: =ROUND(INDEX('All Trends'!H:H,MATCH($AD16,'All Trends'!$C:$C,0)),4) -> 1.0231 | AL16: No | AM16: =IF(C16="Yes",ROUND(T16*N16*AI16,2),0) -> 12419.31 | AN16: =IF(C16="Yes",ROUND(T16*N16*AJ16,2),0) -> 12419.31 | AO16: =IF(C16="Yes",ROUND((W16*N16*AI16),2),0) -> 0 | AP16: =IF(C16="Yes",IF($AL16="No",ROUND(($AO16*($AY$2+$AF16)),2),ROUND($AO16,2)),0) -> 0 | AQ16: =IF(C16="Yes",ROUND((W16*N16*AJ16),2),0) -> 0 | AR16: =IF(C16="Yes",IF($AL16="No",ROUND(($AQ16*($AZ$2+$AF16)),2),ROUND($AQ16,2)),0) -> 0
A17: 729AC0202 | B17: 729AC0202 | C17: Yes | D17: Yes | E17: DAHS | F17: DAHS | G17: =INDEX('[4]RT Description to Bill Matix'!$D:$D,MATCH(A17,'[4]RT Description to Bill Matix'!$M:$M,0)) -> Day Activity and Health Services (DAHS) Title XIX and Title XX | H17: DAY ACTIVITY/HEALTH SERVICES (DAHS) TITLE XX | J17: {=INDEX('Rate Table Service Desc XWalk'!F:F,MATCH(1,(G17='Rate Table Service Desc XWalk'!B:B)*(E17='Rate Table Service Desc XWalk'!A:A),0))} -> 10-1-18 | K17: =INDEX('[5]Combined Bill Code List'!$A:$A,MATCH(A17,'[5]Combined Bill Code List'!$F:$F,0)) -> Title XX | L17: =INDEX('[6]Rate History'!$P:$P,MATCH(A17,'[6]Rate History'!$F:$F,0)) -> 3-5 hours = 1 unit; 6+ hours = 2 units | M17: =INDEX('[7]PDF DB Service Pivot'!$C:$C,MATCH(B17,'[7]PDF DB Service Pivot'!$B:$B,0)) -> 776159.03 | N17: =IF(ISNUMBER(FIND("ISS",F17)),IF(I17="Yes",((M17/Q17)/6)*12,(M17/6)*12),IF(AND(I17="Yes",M17=O17),M17/Q17,M17)) -> 776159.03 | O17: =INDEX('[7]PDF DB Service Pivot'!$D:$D,MATCH(B17,'[7]PDF DB Service Pivot'!$B:$B,0)) -> 12282455 | P17: 45170 | Q17: 16.72 | R17: 5.87 | S17: =_xlfn.IFNA(R17/Q17,"") -> 0.35107656 | T17: 0.5 | U17: =ROUND(V17/Z17,2) -> 0 | V17: {=_xlfn.IFS('Fiscal by Program'!$B$7<10.61,0,'Fiscal by Program'!$B$7>10.6,(ROUND('Fiscal by Program'!$B$7*(1+IF(D17="Yes",'Fiscal by Program'!$B$9,'Fiscal by Program'!$B$8))*T17,2)))} -> 0 | W17: =IF(V17-R17<0,0,V17-R17) -> 0 | X17: =ROUND((R17/(1+IF(D17="Yes",'Fiscal by Program'!$B$9,'Fiscal by Program'!$B$8))),2)+0.01 -> 5.31 | Y17: =Q17+W17 -> 16.72 | Z17: 16 | AA17: =T17/Z17 -> 0.03125 | AB17: =INDEX('[9]Service List'!$K:$K,MATCH(A17,'[9]Service List'!$F:$F,0)) -> 82 | AC17: =INDEX('[5]Combined Bill Code List'!$P:$P,MATCH(A17,'[5]Combined Bill Code List'!$F:$F,0)) -> 0 | AD17: Title XX Flat | AE17: 1 | AF17: 0 | AG17: =ROUND(INDEX('All Trends'!D:D,MATCH($AD17,'All Trends'!$C:$C,0)),4) -> 1 | AH17: =ROUND(INDEX('All Trends'!E:E,MATCH($AD17,'All Trends'!$C:$C,0)),4) -> 1 | AI17: =ROUND(INDEX('All Trends'!F:F,MATCH($AD17,'All Trends'!$C:$C,0)),4) -> 1 | AJ17: =ROUND(INDEX('All Trends'!G:G,MATCH($AD17,'All Trends'!$C:$C,0)),4) -> 1 | AK17: =ROUND(INDEX('All Trends'!H:H,MATCH($AD17,'All Trends'!$C:$C,0)),4) -> 1 | AL17: Yes | AM17: =IF(C17="Yes",ROUND(T17*N17*AI17,2),0) -> 388079.52 | AN17: =IF(C17="Yes",ROUND(T17*N17*AJ17,2),0) -> 388079.52 | AO17: =IF(C17="Yes",ROUND((W17*N17*AI17),2),0) -> 0 | AP17: =IF(C17="Yes",IF($AL17="No",ROUND(($AO17*($AY$2+$AF17)),2),ROUND($AO17,2)),0) -> 0 | AQ17: =IF(C17="Yes",ROUND((W17*N17*AJ17),2),0) -> 0 | AR17: =IF(C17="Yes",IF($AL17="No",ROUND(($AQ17*($AZ$2+$AF17)),2),ROUND($AQ17,2)),0) -> 0
A18: 729C0200 | B18: 729C0200 | C18: Yes | D18: Yes | E18: DAHS | F18: DAHS | G18: =INDEX('[4]RT Description to Bill Matix'!$D:$D,MATCH(A18,'[4]RT Description to Bill Matix'!$M:$M,0)) -> Day Activity and Health Services (DAHS) Title XIX and Title XX | H18: DAY ACTIVITY AND HEALTH SERVICES (DAHS) TITLE XIX | J18: {=INDEX('Rate Table Service Desc XWalk'!F:F,MATCH(1,(G18='Rate Table Service Desc XWalk'!B:B)*(E18='Rate Table Service Desc XWalk'!A:A),0))} -> 10-1-18 | K18: =INDEX('[5]Combined Bill Code List'!$A:$A,MATCH(A18,'[5]Combined Bill Code List'!$F:$F,0)) -> State Plan (Title XIX) | L18: =INDEX('[6]Rate History'!$P:$P,MATCH(A18,'[6]Rate History'!$F:$F,0)) -> 3-5 hours = 1 unit; 6+ hours = 2 units | M18: =INDEX('[7]PDF DB Service Pivot'!$C:$C,MATCH(B18,'[7]PDF DB Service Pivot'!$B:$B,0)) -> 409682.57 | N18: =IF(ISNUMBER(FIND("ISS",F18)),IF(I18="Yes",((M18/Q18)/6)*12,(M18/6)*12),IF(AND(I18="Yes",M18=O18),M18/Q18,M18)) -> 409682.57 | O18: =INDEX('[7]PDF DB Service Pivot'!$D:$D,MATCH(B18,'[7]PDF DB Service Pivot'!$B:$B,0)) -> 6478119.5 | P18: 45170 | Q18: 16.72 | R18: 5.87 | S18: =_xlfn.IFNA(R18/Q18,"") -> 0.35107656 | T18: 0.5 | U18: =ROUND(V18/Z18,2) -> 0 | V18: {=_xlfn.IFS('Fiscal by Program'!$B$7<10.61,0,'Fiscal by Program'!$B$7>10.6,(ROUND('Fiscal by Program'!$B$7*(1+IF(D18="Yes",'Fiscal by Program'!$B$9,'Fiscal by Program'!$B$8))*T18,2)))} -> 0 | W18: =IF(V18-R18<0,0,V18-R18) -> 0 | X18: =ROUND((R18/(1+IF(D18="Yes",'Fiscal by Program'!$B$9,'Fiscal by Program'!$B$8))),2)+0.01 -> 5.31 | Y18: =Q18+W18 -> 16.72 | Z18: 16 | AA18: =T18/Z18 -> 0.03125 | AB18: =INDEX('[9]Service List'!$K:$K,MATCH(A18,'[9]Service List'!$F:$F,0)) -> 81 | AC18: =INDEX('[5]Combined Bill Code List'!$P:$P,MATCH(A18,'[5]Combined Bill Code List'!$F:$F,0)) -> 0 | AD18: DAHS | AE18: 1 | AF18: 0 | AG18: =ROUND(INDEX('All Trends'!D:D,MATCH($AD18,'All Trends'!$C:$C,0)),4) -> 1.0082 | AH18: =ROUND(INDEX('All Trends'!E:E,MATCH($AD18,'All Trends'!$C:$C,0)),4) -> 1.1385 | AI18: =ROUND(INDEX('All Trends'!F:F,MATCH($AD18,'All Trends'!$C:$C,0)),4) -> 1.2662 | AJ18: =ROUND(INDEX('All Trends'!G:G,MATCH($AD18,'All Trends'!$C:$C,0)),4) -> 1.2662 | AK18: =ROUND(INDEX('All Trends'!H:H,MATCH($AD18,'All Trends'!$C:$C,0)),4) -> 1.2662 | AL18: No | AM18: =IF(C18="Yes",ROUND(T18*N18*AI18,2),0) -> 259370.04 | AN18: =IF(C18="Yes",ROUND(T18*N18*AJ18,2),0) -> 259370.04 | AO18: =IF(C18="Yes",ROUND((W18*N18*AI18),2),0) -> 0 | AP18: =IF(C18="Yes",IF($AL18="No",ROUND(($AO18*($AY$2+$AF18)),2),ROUND($AO18,2)),0) -> 0 | AQ18: =IF(C18="Yes",ROUND((W18*N18*AJ18),2),0) -> 0 | AR18: =IF(C18="Yes",IF($AL18="No",ROUND(($AQ18*($AZ$2+$AF18)),2),ROUND($AQ18,2)),0) -> 0
A19: 1610CFCG1108 | B19: 1610CFCG1108 | C19: Yes | D19: No | E19: DBMD | F19: PAS/HAB | G19: =INDEX('[4]RT Description to Bill Matix'!$D:$D,MATCH(A19,'[4]RT Description to Bill Matix'!$M:$M,0)) -> PAS/HAB (CFC) and Transportation | H19: CFC PAS/HAB | J19: {=INDEX('Rate Table Service Desc XWalk'!F:F,MATCH(1,(G19='Rate Table Service Desc XWalk'!B:B)*(E19='Rate Table Service Desc XWalk'!A:A),0))} -> 2-1-79 | K19: =INDEX('[5]Combined Bill Code List'!$A:$A,MATCH(A19,'[5]Combined Bill Code List'!$F:$F,0)) -> State Plan (Title XIX) | L19: =INDEX('[6]Rate History'!$P:$P,MATCH(A19,'[6]Rate History'!$F:$F,0)) -> 1 hour | M19: =INDEX('[7]PDF DB Service Pivot'!$C:$C,MATCH(B19,'[7]PDF DB Service Pivot'!$B:$B,0)) -> 234124.25 | N19: =IF(ISNUMBER(FIND("ISS",F19)),IF(I19="Yes",((M19/Q19)/6)*12,(M19/6)*12),IF(AND(I19="Yes",M19=O19),M19/Q19,M19)) -> 234124.25 | O19: =INDEX('[7]PDF DB Service Pivot'!$D:$D,MATCH(B19,'[7]PDF DB Service Pivot'!$B:$B,0)) -> 3880163.8 | P19: 45170 | Q19: 16.48 | R19: 13.27 | S19: =_xlfn.IFNA(R19/Q19,"") -> 0.80521845 | T19: 1 | U19: =ROUND(V19/Z19,2) -> 0 | V19: {=_xlfn.IFS('Fiscal by Program'!$B$7<10.61,0,'Fiscal by Program'!$B$7>10.6,(ROUND('Fiscal by Program'!$B$7*(1+IF(D19="Yes",'Fiscal by Program'!$B$9,'Fiscal by Program'!$B$8))*T19,2)))} -> 0 | W19: =IF(V19-R19<0,0,V19-R19) -> 0 | X19: =ROUND((R19/(1+IF(D19="Yes",'Fiscal by Program'!$B$9,'Fiscal by Program'!$B$8))),2)+0.01 -> 11.99 | Y19: =Q19+W19 -> 16.48 | Z19: 4 | AA19: =T19/Z19 -> 0.25 | AB19: =INDEX('[9]Service List'!$K:$K,MATCH(A19,'[9]Service List'!$F:$F,0)) -> 127 | AC19: CFC | AD19: DBMD | AE19: 1 | AF19: -0.06 | AG19: =ROUND(INDEX('All Trends'!D:D,MATCH($AD19,'All Trends'!$C:$C,0)),4) -> 0.9076 | AH19: =ROUND(INDEX('All Trends'!E:E,MATCH($AD19,'All Trends'!$C:$C,0)),4) -> 0.8915 | AI19: =ROUND(INDEX('All Trends'!F:F,MATCH($AD19,'All Trends'!$C:$C,0)),4) -> 0.9927 | AJ19: =ROUND(INDEX('All Trends'!G:G,MATCH($AD19,'All Trends'!$C:$C,0)),4) -> 0.9927 | AK19: =ROUND(INDEX('All Trends'!H:H,MATCH($AD19,'All Trends'!$C:$C,0)),4) -> 0.9927 | AL19: No | AM19: =IF(C19="Yes",ROUND(T19*N19*AI19,2),0) -> 232415.14 | AN19: =IF(C19="Yes",ROUND(T19*N19*AJ19,2),0) -> 232415.14 | AO19: =IF(C19="Yes",ROUND((W19*N19*AI19),2),0) -> 0 | AP19: =IF(C19="Yes",IF($AL19="No",ROUND(($AO19*($AY$2+$AF19)),2),ROUND($AO19,2)),0) -> 0 | AQ19: =IF(C19="Yes",ROUND((W19*N19*AJ19),2),0) -> 0 | AR19: =IF(C19="Yes",IF($AL19="No",ROUND(($AQ19*($AZ$2+$AF19)),2),ROUND($AQ19,2)),0) -> 0
A20: 1610CFVG1109 | B20: 1610CFVG1109 | C20: Yes | D20: No | E20: DBMD | F20: PAS/HAB | G20: =INDEX('[4]RT Description to Bill Matix'!$D:$D,MATCH(A20,'[4]RT Description to Bill Matix'!$M:$M,0)) -> CDS PAS/HAB (CFC) and Transportation | H20: CFC PAS/HAB (CDS) | I20: Yes | J20: {=INDEX('Rate Table Service Desc XWalk'!F:F,MATCH(1,(G20='Rate Table Service Desc XWalk'!B:B)*(E20='Rate Table Service Desc XWalk'!A:A),0))} -> 2-5-143 | K20: =INDEX('[5]Combined Bill Code List'!$A:$A,MATCH(A20,'[5]Combined Bill Code List'!$F:$F,0)) -> State Plan (Title XIX) | L20: =INDEX('[6]Rate History'!$P:$P,MATCH(A20,'[6]Rate History'!$F:$F,0)) -> 1 hour | M20: =INDEX('[7]PDF DB Service Pivot'!$C:$C,MATCH(B20,'[7]PDF DB Service Pivot'!$B:$B,0)) -> 2532627.4 | N20: =IF(ISNUMBER(FIND("ISS",F20)),IF(I20="Yes",((M20/Q20)/6)*12,(M20/6)*12),IF(AND(I20="Yes",M20=O20),M20/Q20,M20)) -> 153678.85 | O20: =INDEX('[7]PDF DB Service Pivot'!$D:$D,MATCH(B20,'[7]PDF DB Service Pivot'!$B:$B,0)) -> 2532627.4 | P20: 45170 | Q20: 16.48 | R20: 13.27 | S20: =_xlfn.IFNA(R20/Q20,"") -> 0.80521845 | T20: 1 | U20: =ROUND(V20/Z20,2) -> 0 | V20: {=_xlfn.IFS('Fiscal by Program'!$B$7<10.61,0,'Fiscal by Program'!$B$7>10.6,(ROUND('Fiscal by Program'!$B$7*(1+IF(D20="Yes",'Fiscal by Program'!$B$9,'Fiscal by Program'!$B$8))*T20,2)))} -> 0 | W20: =IF(V20-R20<0,0,V20-R20) -> 0 | X20: =ROUND((R20/(1+IF(D20="Yes",'Fiscal by Program'!$B$9,'Fiscal by Program'!$B$8))),2)+0.01 -> 11.99 | Y20: =Q20+W20 -> 16.48 | Z20: 4 | AA20: =T20/Z20 -> 0.25 | AB20: =INDEX('[9]Service List'!$K:$K,MATCH(A20,'[9]Service List'!$F:$F,0)) -> 125 | AC20: CFC | AD20: DBMD | AE20: 1 | AF20: -0.06 | AG20: =ROUND(INDEX('All Trends'!D:D,MATCH($AD20,'All Trends'!$C:$C,0)),4) -> 0.9076 | AH20: =ROUND(INDEX('All Trends'!E:E,MATCH($AD20,'All Trends'!$C:$C,0)),4) -> 0.8915 | AI20: =ROUND(INDEX('All Trends'!F:F,MATCH($AD20,'All Trends'!$C:$C,0)),4) -> 0.9927 | AJ20: =ROUND(INDEX('All Trends'!G:G,MATCH($AD20,'All Trends'!$C:$C,0)),4) -> 0.9927 | AK20: =ROUND(INDEX('All Trends'!H:H,MATCH($AD20,'All Trends'!$C:$C,0)),4) -> 0.9927 | AL20: No | AM20: =IF(C20="Yes",ROUND(T20*N20*AI20,2),0) -> 152556.99 | AN20: =IF(C20="Yes",ROUND(T20*N20*AJ20,2),0) -> 152556.99 | AO20: =IF(C20="Yes",ROUND((W20*N20*AI20),2),0) -> 0 | AP20: =IF(C20="Yes",IF($AL20="No",ROUND(($AO20*($AY$2+$AF20)),2),ROUND($AO20,2)),0) -> 0 | AQ20: =IF(C20="Yes",ROUND((W20*N20*AJ20),2),0) -> 0 | AR20: =IF(C20="Yes",IF($AL20="No",ROUND(($AQ20*($AZ$2+$AF20)),2),ROUND($AQ20,2)),0) -> 0
A21: 1611G0100 | B21: 1611G0100 | C21: Yes | D21: No | E21: DBMD | F21: In Home Respite | G21: =INDEX('[4]RT Description to Bill Matix'!$D:$D,MATCH(A21,'[4]RT Description to Bill Matix'!$M:$M,0)) -> In Home Respite | H21: Respite In Home | J21: {=INDEX('Rate Table Service Desc XWalk'!F:F,MATCH(1,(G21='Rate Table Service Desc XWalk'!B:B)*(E21='Rate Table Service Desc XWalk'!A:A),0))} -> 2-1-55 | K21: =INDEX('[5]Combined Bill Code List'!$A:$A,MATCH(A21,'[5]Combined Bill Code List'!$F:$F,0)) -> 1915(c) waiver | L21: =INDEX('[6]Rate History'!$P:$P,MATCH(A21,'[6]Rate History'!$F:$F,0)) -> 1 day | M21: =INDEX('[7]PDF DB Service Pivot'!$C:$C,MATCH(B21,'[7]PDF DB Service Pivot'!$B:$B,0)) -> 508.67 | N21: =IF(ISNUMBER(FIND("ISS",F21)),IF(I21="Yes",((M21/Q21)/6)*12,(M21/6)*12),IF(AND(I21="Yes",M21=O21),M21/Q21,M21)) -> 508.67 | O21: =INDEX('[7]PDF DB Service Pivot'!$D:$D,MATCH(B21,'[7]PDF DB Service Pivot'!$B:$B,0)) -> 132840.79 | P21: 45170 | Q21: 313.76 | R21: 281.77 | S21: =_xlfn.IFNA(R21/Q21,"") -> 0.89804309 | T21: 24 | U21: =ROUND(V21/Z21,2) -> 0 | V21: {=_xlfn.IFS('Fiscal by Program'!$B$7<10.61,0,'Fiscal by Program'!$B$7>10.6,(ROUND('Fiscal by Program'!$B$7*(1+IF(D21="Yes",'Fiscal by Program'!$B$9,'Fiscal by Program'!$B$8))*T21,2)))} -> 0 | W21: =IF(V21-R21<0,0,V21-R21) -> 0 | X21: =ROUND((R21/(1+IF(D21="Yes",'Fiscal by Program'!$B$9,'Fiscal by Program'!$B$8))),2)+0.01 -> 254.43 | Y21: =Q21+W21 -> 313.76 | Z21: 96 | AA21: =T21/Z21 -> 0.25 | AB21: =INDEX('[9]Service List'!$K:$K,MATCH(A21,'[9]Service List'!$F:$F,0)) -> 105 | AC21: =INDEX('[5]Combined Bill Code List'!$P:$P,MATCH(A21,'[5]Combined Bill Code List'!$F:$F,0)) -> 0 | AD21: DBMD | AE21: 1 | AF21: 0 | AG21: =ROUND(INDEX('All Trends'!D:D,MATCH($AD21,'All Trends'!$C:$C,0)),4) -> 0.9076 | AH21: =ROUND(INDEX('All Trends'!E:E,MATCH($AD21,'All Trends'!$C:$C,0)),4) -> 0.8915 | AI21: =ROUND(INDEX('All Trends'!F:F,MATCH($AD21,'All Trends'!$C:$C,0)),4) -> 0.9927 | AJ21: =ROUND(INDEX('All Trends'!G:G,MATCH($AD21,'All Trends'!$C:$C,0)),4) -> 0.9927 | AK21: =ROUND(INDEX('All Trends'!H:H,MATCH($AD21,'All Trends'!$C:$C,0)),4) -> 0.9927 | AL21: No | AM21: =IF(C21="Yes",ROUND(T21*N21*AI21,2),0) -> 12118.96 | AN21: =IF(C21="Yes",ROUND(T21*N21*AJ21,2),0) -> 12118.96 | AO21: =IF(C21="Yes",ROUND((W21*N21*AI21),2),0) -> 0 | AP21: =IF(C21="Yes",IF($AL21="No",ROUND(($AO21*($AY$2+$AF21)),2),ROUND($AO21,2)),0) -> 0 | AQ21: =IF(C21="Yes",ROUND((W21*N21*AJ21),2),0) -> 0 | AR21: =IF(C21="Yes",IF($AL21="No",ROUND(($AQ21*($AZ$2+$AF21)),2),ROUND($AQ21,2)),0) -> 0
A22: 1611PVG0197 | B22: 1611PVG0197 | C22: Yes | D22: No | E22: DBMD | F22: In Home Respite | G22: =INDEX('[4]RT Description to Bill Matix'!$D:$D,MATCH(A22,'[4]RT Description to Bill Matix'!$M:$M,0)) -> CDS In Home Respite | H22: RESPITE IN-HOME (CDS) | I22: Yes | J22: {=INDEX('Rate Table Service Desc XWalk'!F:F,MATCH(1,(G22='Rate Table Service Desc XWalk'!B:B)*(E22='Rate Table Service Desc XWalk'!A:A),0))} -> 2-5-136 | K22: =INDEX('[5]Combined Bill Code List'!$A:$A,MATCH(A22,'[5]Combined Bill Code List'!$F:$F,0)) -> 1915(c) waiver | L22: =INDEX('[6]Rate History'!$P:$P,MATCH(A22,'[6]Rate History'!$F:$F,0)) -> 1 day | M22: =INDEX('[7]PDF DB Service Pivot'!$C:$C,MATCH(B22,'[7]PDF DB Service Pivot'!$B:$B,0)) -> 224265.8 | N22: =IF(ISNUMBER(FIND("ISS",F22)),IF(I22="Yes",((M22/Q22)/6)*12,(M22/6)*12),IF(AND(I22="Yes",M22=O22),M22/Q22,M22)) -> 773.97087 | O22: =INDEX('[7]PDF DB Service Pivot'!$D:$D,MATCH(B22,'[7]PDF DB Service Pivot'!$B:$B,0)) -> 224265.8 | P22: 45170 | Q22: 289.76 | R22: 281.77 | S22: =_xlfn.IFNA(R22/Q22,"") -> 0.97242546 | T22: 24 | U22: =ROUND(V22/Z22,2) -> 0 | V22: {=_xlfn.IFS('Fiscal by Program'!$B$7<10.61,0,'Fiscal by Program'!$B$7>10.6,(ROUND('Fiscal by Program'!$B$7*(1+IF(D22="Yes",'Fiscal by Program'!$B$9,'Fiscal by Program'!$B$8))*T22,2)))} -> 0 | W22: =IF(V22-R22<0,0,V22-R22) -> 0 | X22: =ROUND((R22/(1+IF(D22="Yes",'Fiscal by Program'!$B$9,'Fiscal by Program'!$B$8))),2)+0.01 -> 254.43 | Y22: =Q22+W22 -> 289.76 | Z22: 96 | AA22: =T22/Z22 -> 0.25 | AB22: =INDEX('[9]Service List'!$K:$K,MATCH(A22,'[9]Service List'!$F:$F,0)) -> 104 | AC22: =INDEX('[5]Combined Bill Code List'!$P:$P,MATCH(A22,'[5]Combined Bill Code List'!$F:$F,0)) -> 0 | AD22: DBMD | AE22: 1 | AF22: 0 | AG22: =ROUND(INDEX('All Trends'!D:D,MATCH($AD22,'All Trends'!$C:$C,0)),4) -> 0.9076 | AH22: =ROUND(INDEX('All Trends'!E:E,MATCH($AD22,'All Trends'!$C:$C,0)),4) -> 0.8915 | AI22: =ROUND(INDEX('All Trends'!F:F,MATCH($AD22,'All Trends'!$C:$C,0)),4) -> 0.9927 | AJ22: =ROUND(INDEX('All Trends'!G:G,MATCH($AD22,'All Trends'!$C:$C,0)),4) -> 0.9927 | AK22: =ROUND(INDEX('All Trends'!H:H,MATCH($AD22,'All Trends'!$C:$C,0)),4) -> 0.9927 | AL22: No | AM22: =IF(C22="Yes",ROUND(T22*N22*AI22,2),0) -> 18439.7 | AN22: =IF(C22="Yes",ROUND(T22*N22*AJ22,2),0) -> 18439.7 | AO22: =IF(C22="Yes",ROUND((W22*N22*AI22),2),0) -> 0 | AP22: =IF(C22="Yes",IF($AL22="No",ROUND(($AO22*($AY$2+$AF22)),2),ROUND($AO22,2)),0) -> 0 | AQ22: =IF(C22="Yes",ROUND((W22*N22*AJ22),2),0) -> 0 | AR22: =IF(C22="Yes",IF($AL22="No",ROUND(($AQ22*($AZ$2+$AF22)),2),ROUND($AQ22,2)),0) -> 0
A23: 1617EG0744 | B23: 1617EG0744 | C23: Yes | D23: No | E23: DBMD | F23: Chore Services | G23: =INDEX('[4]RT Description to Bill Matix'!$D:$D,MATCH(A23,'[4]RT Description to Bill Matix'!$M:$M,0)) -> Chore Services | H23: PAS CHORE | J23: {=INDEX('Rate Table Service Desc XWalk'!F:F,MATCH(1,(G23='Rate Table Service Desc XWalk'!B:B)*(E23='Rate Table Service Desc XWalk'!A:A),0))} -> 2-1-12 | K23: =INDEX('[5]Combined Bill Code List'!$A:$A,MATCH(A23,'[5]Combined Bill Code List'!$F:$F,0)) -> 1915(c) waiver | L23: =INDEX('[6]Rate History'!$P:$P,MATCH(A23,'[6]Rate History'!$F:$F,0)) -> 1 hour | M23: =INDEX('[7]PDF DB Service Pivot'!$C:$C,MATCH(B23,'[7]PDF DB Service Pivot'!$B:$B,0)) -> 1013 | N23: =IF(ISNUMBER(FIND("ISS",F23)),IF(I23="Yes",((M23/Q23)/6)*12,(M23/6)*12),IF(AND(I23="Yes",M23=O23),M23/Q23,M23)) -> 1013 | O23: =INDEX('[7]PDF DB Service Pivot'!$D:$D,MATCH(B23,'[7]PDF DB Service Pivot'!$B:$B,0)) -> 15196.62 | P23: 45170 | Q23: 14.08 | R23: 11.74 | S23: =_xlfn.IFNA(R23/Q23,"") -> 0.83380682 | T23: 1 | U23: =ROUND(V23/Z23,2) -> 0 | V23: {=_xlfn.IFS('Fiscal by Program'!$B$7<10.61,0,'Fiscal by Program'!$B$7>10.6,(ROUND('Fiscal by Program'!$B$7*(1+IF(D23="Yes",'Fiscal by Program'!$B$9,'Fiscal by Program'!$B$8))*T23,2)))} -> 0 | W23: =IF(V23-R23<0,0,V23-R23) -> 0 | X23: =ROUND((R23/(1+IF(D23="Yes",'Fiscal by Program'!$B$9,'Fiscal by Program'!$B$8))),2)+0.01 -> 10.61 | Y23: =Q23+W23 -> 14.08 | Z23: 4 | AA23: =T23/Z23 -> 0.25 | AB23: =INDEX('[9]Service List'!$K:$K,MATCH(A23,'[9]Service List'!$F:$F,0)) -> 91 | AC23: =INDEX('[5]Combined Bill Code List'!$P:$P,MATCH(A23,'[5]Combined Bill Code List'!$F:$F,0)) -> 0 | AD23: DBMD | AE23: 1 | AF23: 0 | AG23: =ROUND(INDEX('All Trends'!D:D,MATCH($AD23,'All Trends'!$C:$C,0)),4) -> 0.9076 | AH23: =ROUND(INDEX('All Trends'!E:E,MATCH($AD23,'All Trends'!$C:$C,0)),4) -> 0.8915 | AI23: =ROUND(INDEX('All Trends'!F:F,MATCH($AD23,'All Trends'!$C:$C,0)),4) -> 0.9927 | AJ23: =ROUND(INDEX('All Trends'!G:G,MATCH($AD23,'All Trends'!$C:$C,0)),4) -> 0.9927 | AK23: =ROUND(INDEX('All Trends'!H:H,MATCH($AD23,'All Trends'!$C:$C,0)),4) -> 0.9927 | AL23: No | AM23: =IF(C23="Yes",ROUND(T23*N23*AI23,2),0) -> 1005.61 | AN23: =IF(C23="Yes",ROUND(T23*N23*AJ23,2),0) -> 1005.61 | AO23: =IF(C23="Yes",ROUND((W23*N23*AI23),2),0) -> 0 | AP23: =IF(C23="Yes",IF($AL23="No",ROUND(($AO23*($AY$2+$AF23)),2),ROUND($AO23,2)),0) -> 0 | AQ23: =IF(C23="Yes",ROUND((W23*N23*AJ23),2),0) -> 0 | AR23: =IF(C23="Yes",IF($AL23="No",ROUND(($AQ23*($AZ$2+$AF23)),2),ROUND($AQ23,2)),0) -> 0
A24: 1619EG0937 | B24: 1619EG0937 | C24: Yes | D24: No | E24: DBMD | F24: DBMD Assisted Living | G24: =INDEX('[4]RT Description to Bill Matix'!$D:$D,MATCH(A24,'[4]RT Description to Bill Matix'!$M:$M,0)) -> Assisted Living | H24: ASSISTED LIVING HABILITATION 24 HR | J24: {=INDEX('Rate Table Service Desc XWalk'!F:F,MATCH(1,(G24='Rate Table Service Desc XWalk'!B:B)*(E24='Rate Table Service Desc XWalk'!A:A),0))} -> 2-1-3 | K24: =INDEX('[5]Combined Bill Code List'!$A:$A,MATCH(A24,'[5]Combined Bill Code List'!$F:$F,0)) -> 1915(c) waiver | L24: =INDEX('[6]Rate History'!$P:$P,MATCH(A24,'[6]Rate History'!$F:$F,0)) -> 1 day | M24: =INDEX('[7]PDF DB Service Pivot'!$C:$C,MATCH(B24,'[7]PDF DB Service Pivot'!$B:$B,0)) -> 926 | N24: =IF(ISNUMBER(FIND("ISS",F24)),IF(I24="Yes",((M24/Q24)/6)*12,(M24/6)*12),IF(AND(I24="Yes",M24=O24),M24/Q24,M24)) -> 926 | O24: =INDEX('[7]PDF DB Service Pivot'!$D:$D,MATCH(B24,'[7]PDF DB Service Pivot'!$B:$B,0)) -> 133019.9 | P24: 45170 | Q24: 145.6 | R24: 83.83 | S24: =_xlfn.IFNA(R24/Q24,"") -> 0.57575549 | T24: =T175 -> 0.25 | U24: =ROUND(V24/Z24,2) -> 0 | V24: {=_xlfn.IFS('Fiscal by Program'!$B$7<10.61,0,'Fiscal by Program'!$B$7>10.6,(ROUND('Fiscal by Program'!$B$7*(1+IF(D24="Yes",'Fiscal by Program'!$B$9,'Fiscal by Program'!$B$8))*T24,2)))} -> 0 | W24: =IF(V24-R24<0,0,V24-R24) -> 0 | X24: =ROUND((R24/(1+IF(D24="Yes",'Fiscal by Program'!$B$9,'Fiscal by Program'!$B$8))),2)+0.01 -> 75.7 | Y24: =Q24+W24 -> 145.6 | Z24: =24*4 -> 96 | AA24: =T24/Z24 -> 0.0026041667 | AB24: =INDEX('[9]Service List'!$K:$K,MATCH(A24,'[9]Service List'!$F:$F,0)) -> 95 | AC24: =INDEX('[5]Combined Bill Code List'!$P:$P,MATCH(A24,'[5]Combined Bill Code List'!$F:$F,0)) -> 0 | AD24: DBMD | AE24: 1 | AF24: 0 | AG24: =ROUND(INDEX('All Trends'!D:D,MATCH($AD24,'All Trends'!$C:$C,0)),4) -> 0.9076 | AH24: =ROUND(INDEX('All Trends'!E:E,MATCH($AD24,'All Trends'!$C:$C,0)),4) -> 0.8915 | AI24: =ROUND(INDEX('All Trends'!F:F,MATCH($AD24,'All Trends'!$C:$C,0)),4) -> 0.9927 | AJ24: =ROUND(INDEX('All Trends'!G:G,MATCH($AD24,'All Trends'!$C:$C,0)),4) -> 0.9927 | AK24: =ROUND(INDEX('All Trends'!H:H,MATCH($AD24,'All Trends'!$C:$C,0)),4) -> 0.9927 | AL24: No | AM24: =IF(C24="Yes",ROUND(T24*N24*AI24,2),0) -> 229.81 | AN24: =IF(C24="Yes",ROUND(T24*N24*AJ24,2),0) -> 229.81 | AO24: =IF(C24="Yes",ROUND((W24*N24*AI24),2),0) -> 0 | AP24: =IF(C24="Yes",IF($AL24="No",ROUND(($AO24*($AY$2+$AF24)),2),ROUND($AO24,2)),0) -> 0 | AQ24: =IF(C24="Yes",ROUND((W24*N24*AJ24),2),0) -> 0 | AR24: =IF(C24="Yes",IF($AL24="No",ROUND(($AQ24*($AZ$2+$AF24)),2),ROUND($AQ24,2)),0) -> 0
A25: 1619FG0938 | B25: 1619FG0938 | C25: Yes | D25: No | E25: DBMD | F25: DBMD Assisted Living | G25: =INDEX('[4]RT Description to Bill Matix'!$D:$D,MATCH(A25,'[4]RT Description to Bill Matix'!$M:$M,0)) -> Assisted Living | H25: 18 HOUR ASSISTED LIVING | J25: {=INDEX('Rate Table Service Desc XWalk'!F:F,MATCH(1,(G25='Rate Table Service Desc XWalk'!B:B)*(E25='Rate Table Service Desc XWalk'!A:A),0))} -> 2-1-3 | K25: =INDEX('[5]Combined Bill Code List'!$A:$A,MATCH(A25,'[5]Combined Bill Code List'!$F:$F,0)) -> 1915(c) waiver | L25: =INDEX('[6]Rate History'!$P:$P,MATCH(A25,'[6]Rate History'!$F:$F,0)) -> 1 day | M25: =INDEX('[7]PDF DB Service Pivot'!$C:$C,MATCH(B25,'[7]PDF DB Service Pivot'!$B:$B,0)) -> 5612 | N25: =IF(ISNUMBER(FIND("ISS",F25)),IF(I25="Yes",((M25/Q25)/6)*12,(M25/6)*12),IF(AND(I25="Yes",M25=O25),M25/Q25,M25)) -> 5612 | O25: =INDEX('[7]PDF DB Service Pivot'!$D:$D,MATCH(B25,'[7]PDF DB Service Pivot'!$B:$B,0)) -> 695270.68 | P25: 45170 | Q25: 125.84 | R25: 72.57 | S25: =_xlfn.IFNA(R25/Q25,"") -> 0.57668468 | T25: =T174 -> 0.25 | U25: =ROUND(V25/Z25,2) -> 0 | V25: {=_xlfn.IFS('Fiscal by Program'!$B$7<10.61,0,'Fiscal by Program'!$B$7>10.6,(ROUND('Fiscal by Program'!$B$7*(1+IF(D25="Yes",'Fiscal by Program'!$B$9,'Fiscal by Program'!$B$8))*T25,2)))} -> 0 | W25: =IF(V25-R25<0,0,V25-R25) -> 0 | X25: =ROUND((R25/(1+IF(D25="Yes",'Fiscal by Program'!$B$9,'Fiscal by Program'!$B$8))),2)+0.01 -> 65.54 | Y25: =Q25+W25 -> 125.84 | Z25: =18*4 -> 72 | AA25: =T25/Z25 -> 0.0034722222 | AB25: =INDEX('[9]Service List'!$K:$K,MATCH(A25,'[9]Service List'!$F:$F,0)) -> 93 | AC25: =INDEX('[5]Combined Bill Code List'!$P:$P,MATCH(A25,'[5]Combined Bill Code List'!$F:$F,0)) -> 0 | AD25: DBMD | AE25: 1 | AF25: 0 | AG25: =ROUND(INDEX('All Trends'!D:D,MATCH($AD25,'All Trends'!$C:$C,0)),4) -> 0.9076 | AH25: =ROUND(INDEX('All Trends'!E:E,MATCH($AD25,'All Trends'!$C:$C,0)),4) -> 0.8915 | AI25: =ROUND(INDEX('All Trends'!F:F,MATCH($AD25,'All Trends'!$C:$C,0)),4) -> 0.9927 | AJ25: =ROUND(INDEX('All Trends'!G:G,MATCH($AD25,'All Trends'!$C:$C,0)),4) -> 0.9927 | AK25: =ROUND(INDEX('All Trends'!H:H,MATCH($AD25,'All Trends'!$C:$C,0)),4) -> 0.9927 | AL25: No | AM25: =IF(C25="Yes",ROUND(T25*N25*AI25,2),0) -> 1392.76 | AN25: =IF(C25="Yes",ROUND(T25*N25*AJ25,2),0) -> 1392.76 | AO25: =IF(C25="Yes",ROUND((W25*N25*AI25),2),0) -> 0 | AP25: =IF(C25="Yes",IF($AL25="No",ROUND(($AO25*($AY$2+$AF25)),2),ROUND($AO25,2)),0) -> 0 | AQ25: =IF(C25="Yes",ROUND((W25*N25*AJ25),2),0) -> 0 | AR25: =IF(C25="Yes",IF($AL25="No",ROUND(($AQ25*($AZ$2+$AF25)),2),ROUND($AQ25,2)),0) -> 0
A26: 1619G0900 | B26: 1619G0900 | C26: Yes | D26: No | E26: DBMD | F26: DBMD Assisted Living | G26: =INDEX('[4]RT Description to Bill Matix'!$D:$D,MATCH(A26,'[4]RT Description to Bill Matix'!$M:$M,0)) -> Assisted Living | H26: ASSISTED LIVING APT (LEVEL 6) | J26: {=INDEX('Rate Table Service Desc XWalk'!F:F,MATCH(1,(G26='Rate Table Service Desc XWalk'!B:B)*(E26='Rate Table Service Desc XWalk'!A:A),0))} -> 2-1-3 | K26: =INDEX('[5]Combined Bill Code List'!$A:$A,MATCH(A26,'[5]Combined Bill Code List'!$F:$F,0)) -> 1915(c) waiver | L26: =INDEX('[6]Rate History'!$P:$P,MATCH(A26,'[6]Rate History'!$F:$F,0)) -> 1 day | M26: =INDEX('[7]PDF DB Service Pivot'!$C:$C,MATCH(B26,'[7]PDF DB Service Pivot'!$B:$B,0)) -> 7509 | N26: =IF(ISNUMBER(FIND("ISS",F26)),IF(I26="Yes",((M26/Q26)/6)*12,(M26/6)*12),IF(AND(I26="Yes",M26=O26),M26/Q26,M26)) -> 7509 | O26: =INDEX('[7]PDF DB Service Pivot'!$D:$D,MATCH(B26,'[7]PDF DB Service Pivot'!$B:$B,0)) -> 1078667.9 | P26: 45170 | Q26: 145.6 | R26: 83.83 | S26: =_xlfn.IFNA(R26/Q26,"") -> 0.57575549 | T26: =T174 -> 0.25 | U26: =ROUND(V26/Z26,2) -> 0 | V26: {=_xlfn.IFS('Fiscal by Program'!$B$7<10.61,0,'Fiscal by Program'!$B$7>10.6,(ROUND('Fiscal by Program'!$B$7*(1+IF(D26="Yes",'Fiscal by Program'!$B$9,'Fiscal by Program'!$B$8))*T26,2)))} -> 0 | W26: =IF(V26-R26<0,0,V26-R26) -> 0 | X26: =ROUND((R26/(1+IF(D26="Yes",'Fiscal by Program'!$B$9,'Fiscal by Program'!$B$8))),2)+0.01 -> 75.7 | Y26: =Q26+W26 -> 145.6 | Z26: 96 | AA26: =T26/Z26 -> 0.0026041667 | AB26: =INDEX('[9]Service List'!$K:$K,MATCH(A26,'[9]Service List'!$F:$F,0)) -> 94 | AC26: =INDEX('[5]Combined Bill Code List'!$P:$P,MATCH(A26,'[5]Combined Bill Code List'!$F:$F,0)) -> 0 | AD26: DBMD | AE26: 1 | AF26: 0 | AG26: =ROUND(INDEX('All Trends'!D:D,MATCH($AD26,'All Trends'!$C:$C,0)),4) -> 0.9076 | AH26: =ROUND(INDEX('All Trends'!E:E,MATCH($AD26,'All Trends'!$C:$C,0)),4) -> 0.8915 | AI26: =ROUND(INDEX('All Trends'!F:F,MATCH($AD26,'All Trends'!$C:$C,0)),4) -> 0.9927 | AJ26: =ROUND(INDEX('All Trends'!G:G,MATCH($AD26,'All Trends'!$C:$C,0)),4) -> 0.9927 | AK26: =ROUND(INDEX('All Trends'!H:H,MATCH($AD26,'All Trends'!$C:$C,0)),4) -> 0.9927 | AL26: No | AM26: =IF(C26="Yes",ROUND(T26*N26*AI26,2),0) -> 1863.55 | AN26: =IF(C26="Yes",ROUND(T26*N26*AJ26,2),0) -> 1863.55 | AO26: =IF(C26="Yes",ROUND((W26*N26*AI26),2),0) -> 0 | AP26: =IF(C26="Yes",IF($AL26="No",ROUND(($AO26*($AY$2+$AF26)),2),ROUND($AO26,2)),0) -> 0 | AQ26: =IF(C26="Yes",ROUND((W26*N26*AJ26),2),0) -> 0 | AR26: =IF(C26="Yes",IF($AL26="No",ROUND(($AQ26*($AZ$2+$AF26)),2),ROUND($AQ26,2)),0) -> 0
A27: 1623S0312 | B27: 1623S0312 | C27: Yes | D27: No | E27: DBMD | F27: ISS | G27: =INDEX('[4]RT Description to Bill Matix'!$D:$D,MATCH(A27,'[4]RT Description to Bill Matix'!$M:$M,0)) -> Individualized Skills and Socialization - On-Site and Off-Site | H27: Individualized Skills and Socialization (ISS) On-Site | J27: {=INDEX('Rate Table Service Desc XWalk'!F:F,MATCH(1,(G27='Rate Table Service Desc XWalk'!B:B)*(E27='Rate Table Service Desc XWalk'!A:A),0))} -> 2-1-44 | K27: =INDEX('[5]Combined Bill Code List'!$A:$A,MATCH(A27,'[5]Combined Bill Code List'!$F:$F,0)) -> 1915(c) waiver | L27: =INDEX('[6]Rate History'!$P:$P,MATCH(A27,'[6]Rate History'!$F:$F,0)) -> 1 hour | M27: =INDEX('[7]PDF DB Service Pivot'!$C:$C,MATCH(B27,'[7]PDF DB Service Pivot'!$B:$B,0)) -> 20352.5 | N27: =IF(ISNUMBER(FIND("ISS",F27)),IF(I27="Yes",((M27/Q27)/6)*12,(M27/6)*12),IF(AND(I27="Yes",M27=O27),M27/Q27,M27)) -> 40705 | O27: =INDEX('[7]PDF DB Service Pivot'!$D:$D,MATCH(B27,'[7]PDF DB Service Pivot'!$B:$B,0)) -> 507184.3 | P27: 44927 | Q27: 24.92 | R27: 17.93 | S27: =_xlfn.IFNA(R27/Q27,"") -> 0.71950241 | T27: 1 | U27: =ROUND(V27/Z27,2) -> 0 | V27: {=_xlfn.IFS('Fiscal by Program'!$B$7<10.61,0,'Fiscal by Program'!$B$7>10.6,(ROUND('Fiscal by Program'!$B$7*(1+IF(D27="Yes",'Fiscal by Program'!$B$9,'Fiscal by Program'!$B$8))*T27,2)))} -> 0 | W27: =IF(V27-R27<0,0,V27-R27) -> 0 | X27: =ROUND((R27/(1+IF(D27="Yes",'Fiscal by Program'!$B$9,'Fiscal by Program'!$B$8))),2)+0.01 -> 16.2 | Y27: =Q27+W27 -> 24.92 | Z27: 4 | AA27: =T27/Z27 -> 0.25 | AB27: =INDEX('[9]Service List'!$K:$K,MATCH(A27,'[9]Service List'!$F:$F,0)) -> 114 | AC27: =INDEX('[5]Combined Bill Code List'!$P:$P,MATCH(A27,'[5]Combined Bill Code List'!$F:$F,0)) -> 0 | AD27: DBMD | AE27: 1 | AF27: 0 | AG27: =ROUND(INDEX('All Trends'!D:D,MATCH($AD27,'All Trends'!$C:$C,0)),4) -> 0.9076 | AH27: =ROUND(INDEX('All Trends'!E:E,MATCH($AD27,'All Trends'!$C:$C,0)),4) -> 0.8915 | AI27: =ROUND(INDEX('All Trends'!F:F,MATCH($AD27,'All Trends'!$C:$C,0)),4) -> 0.9927 | AJ27: =ROUND(INDEX('All Trends'!G:G,MATCH($AD27,'All Trends'!$C:$C,0)),4) -> 0.9927 | AK27: =ROUND(INDEX('All Trends'!H:H,MATCH($AD27,'All Trends'!$C:$C,0)),4) -> 0.9927 | AL27: No | AM27: =IF(C27="Yes",ROUND(T27*N27*AI27,2),0) -> 40407.85 | AN27: =IF(C27="Yes",ROUND(T27*N27*AJ27,2),0) -> 40407.85 | AO27: =IF(C27="Yes",ROUND((W27*N27*AI27),2),0) -> 0 | AP27: =IF(C27="Yes",IF($AL27="No",ROUND(($AO27*($AY$2+$AF27)),2),ROUND($AO27,2)),0) -> 0 | AQ27: =IF(C27="Yes",ROUND((W27*N27*AJ27),2),0) -> 0 | AR27: =IF(C27="Yes",IF($AL27="No",ROUND(($AQ27*($AZ$2+$AF27)),2),ROUND($AQ27,2)),0) -> 0
A28: 1623S0313 | B28: 1623S0313 | C28: Yes | D28: No | E28: DBMD | F28: ISS | G28: =INDEX('[4]RT Description to Bill Matix'!$D:$D,MATCH(A28,'[4]RT Description to Bill Matix'!$M:$M,0)) -> Individualized Skills and Socialization - On-Site and Off-Site | H28: Individualized Skills and Socialization (ISS) Off-Site | J28: {=INDEX('Rate Table Service Desc XWalk'!F:F,MATCH(1,(G28='Rate Table Service Desc XWalk'!B:B)*(E28='Rate Table Service Desc XWalk'!A:A),0))} -> 2-1-44 | K28: =INDEX('[5]Combined Bill Code List'!$A:$A,MATCH(A28,'[5]Combined Bill Code List'!$F:$F,0)) -> 1915(c) waiver | L28: =INDEX('[6]Rate History'!$P:$P,MATCH(A28,'[6]Rate History'!$F:$F,0)) -> 1 hour | M28: =INDEX('[7]PDF DB Service Pivot'!$C:$C,MATCH(B28,'[7]PDF DB Service Pivot'!$B:$B,0)) -> 1035.25 | N28: =IF(ISNUMBER(FIND("ISS",F28)),IF(I28="Yes",((M28/Q28)/6)*12,(M28/6)*12),IF(AND(I28="Yes",M28=O28),M28/Q28,M28)) -> 2070.5 | O28: =INDEX('[7]PDF DB Service Pivot'!$D:$D,MATCH(B28,'[7]PDF DB Service Pivot'!$B:$B,0)) -> 25798.43 | P28: 44927 | Q28: 24.92 | R28: 17.93 | S28: =_xlfn.IFNA(R28/Q28,"") -> 0.71950241 | T28: 1 | U28: =ROUND(V28/Z28,2) -> 0 | V28: {=_xlfn.IFS('Fiscal by Program'!$B$7<10.61,0,'Fiscal by Program'!$B$7>10.6,(ROUND('Fiscal by Program'!$B$7*(1+IF(D28="Yes",'Fiscal by Program'!$B$9,'Fiscal by Program'!$B$8))*T28,2)))} -> 0 | W28: =IF(V28-R28<0,0,V28-R28) -> 0 | X28: =ROUND((R28/(1+IF(D28="Yes",'Fiscal by Program'!$B$9,'Fiscal by Program'!$B$8))),2)+0.01 -> 16.2 | Y28: =Q28+W28 -> 24.92 | Z28: 4 | AA28: =T28/Z28 -> 0.25 | AB28: =INDEX('[9]Service List'!$K:$K,MATCH(A28,'[9]Service List'!$F:$F,0)) -> 115 | AC28: =INDEX('[5]Combined Bill Code List'!$P:$P,MATCH(A28,'[5]Combined Bill Code List'!$F:$F,0)) -> 0 | AD28: DBMD | AE28: 1 | AF28: 0 | AG28: =ROUND(INDEX('All Trends'!D:D,MATCH($AD28,'All Trends'!$C:$C,0)),4) -> 0.9076 | AH28: =ROUND(INDEX('All Trends'!E:E,MATCH($AD28,'All Trends'!$C:$C,0)),4) -> 0.8915 | AI28: =ROUND(INDEX('All Trends'!F:F,MATCH($AD28,'All Trends'!$C:$C,0)),4) -> 0.9927 | AJ28: =ROUND(INDEX('All Trends'!G:G,MATCH($AD28,'All Trends'!$C:$C,0)),4) -> 0.9927 | AK28: =ROUND(INDEX('All Trends'!H:H,MATCH($AD28,'All Trends'!$C:$C,0)),4) -> 0.9927 | AL28: No | AM28: =IF(C28="Yes",ROUND(T28*N28*AI28,2),0) -> 2055.39 | AN28: =IF(C28="Yes",ROUND(T28*N28*AJ28,2),0) -> 2055.39 | AO28: =IF(C28="Yes",ROUND((W28*N28*AI28),2),0) -> 0 | AP28: =IF(C28="Yes",IF($AL28="No",ROUND(($AO28*($AY$2+$AF28)),2),ROUND($AO28,2)),0) -> 0 | AQ28: =IF(C28="Yes",ROUND((W28*N28*AJ28),2),0) -> 0 | AR28: =IF(C28="Yes",IF($AL28="No",ROUND(($AQ28*($AZ$2+$AF28)),2),ROUND($AQ28,2)),0) -> 0
A29: 1648G0252 | B29: 1648G0252 | C29: Yes | D29: No | E29: DBMD | F29: HAB Transportation | G29: =INDEX('[4]RT Description to Bill Matix'!$D:$D,MATCH(A29,'[4]RT Description to Bill Matix'!$M:$M,0)) -> PAS/HAB (CFC) and Transportation | H29: HAB TRANSPORTATION | J29: {=INDEX('Rate Table Service Desc XWalk'!F:F,MATCH(1,(G29='Rate Table Service Desc XWalk'!B:B)*(E29='Rate Table Service Desc XWalk'!A:A),0))} -> 2-1-79 | K29: =INDEX('[5]Combined Bill Code List'!$A:$A,MATCH(A29,'[5]Combined Bill Code List'!$F:$F,0)) -> 1915(c) waiver | L29: =INDEX('[6]Rate History'!$P:$P,MATCH(A29,'[6]Rate History'!$F:$F,0)) -> 1 hour | M29: =INDEX('[7]PDF DB Service Pivot'!$C:$C,MATCH(B29,'[7]PDF DB Service Pivot'!$B:$B,0)) -> 4.5 | N29: =IF(ISNUMBER(FIND("ISS",F29)),IF(I29="Yes",((M29/Q29)/6)*12,(M29/6)*12),IF(AND(I29="Yes",M29=O29),M29/Q29,M29)) -> 4.5 | O29: =INDEX('[7]PDF DB Service Pivot'!$D:$D,MATCH(B29,'[7]PDF DB Service Pivot'!$B:$B,0)) -> 74.03 | P29: 45170 | Q29: 16.48 | R29: 13.27 | S29: =_xlfn.IFNA(R29/Q29,"") -> 0.80521845 | T29: 1 | U29: =ROUND(V29/Z29,2) -> 0 | V29: {=_xlfn.IFS('Fiscal by Program'!$B$7<10.61,0,'Fiscal by Program'!$B$7>10.6,(ROUND('Fiscal by Program'!$B$7*(1+IF(D29="Yes",'Fiscal by Program'!$B$9,'Fiscal by Program'!$B$8))*T29,2)))} -> 0 | W29: =IF(V29-R29<0,0,V29-R29) -> 0 | X29: =ROUND((R29/(1+IF(D29="Yes",'Fiscal by Program'!$B$9,'Fiscal by Program'!$B$8))),2)+0.01 -> 11.99 | Y29: =Q29+W29 -> 16.48 | Z29: 4 | AA29: =T29/Z29 -> 0.25 | AB29: =INDEX('[9]Service List'!$K:$K,MATCH(A29,'[9]Service List'!$F:$F,0)) -> 103 | AC29: =INDEX('[5]Combined Bill Code List'!$P:$P,MATCH(A29,'[5]Combined Bill Code List'!$F:$F,0)) -> 0 | AD29: DBMD | AE29: 1 | AF29: 0 | AG29: =ROUND(INDEX('All Trends'!D:D,MATCH($AD29,'All Trends'!$C:$C,0)),4) -> 0.9076 | AH29: =ROUND(INDEX('All Trends'!E:E,MATCH($AD29,'All Trends'!$C:$C,0)),4) -> 0.8915 | AI29: =ROUND(INDEX('All Trends'!F:F,MATCH($AD29,'All Trends'!$C:$C,0)),4) -> 0.9927 | AJ29: =ROUND(INDEX('All Trends'!G:G,MATCH($AD29,'All Trends'!$C:$C,0)),4) -> 0.9927 | AK29: =ROUND(INDEX('All Trends'!H:H,MATCH($AD29,'All Trends'!$C:$C,0)),4) -> 0.9927 | AL29: No | AM29: =IF(C29="Yes",ROUND(T29*N29*AI29,2),0) -> 4.47 | AN29: =IF(C29="Yes",ROUND(T29*N29*AJ29,2),0) -> 4.47 | AO29: =IF(C29="Yes",ROUND((W29*N29*AI29),2),0) -> 0 | AP29: =IF(C29="Yes",IF($AL29="No",ROUND(($AO29*($AY$2+$AF29)),2),ROUND($AO29,2)),0) -> 0 | AQ29: =IF(C29="Yes",ROUND((W29*N29*AJ29),2),0) -> 0 | AR29: =IF(C29="Yes",IF($AL29="No",ROUND(($AQ29*($AZ$2+$AF29)),2),ROUND($AQ29,2)),0) -> 0
A30: 1648VG0253 | B30: 1648VG0253 | C30: Yes | D30: No | E30: DBMD | F30: HAB Transportation | G30: =INDEX('[4]RT Description to Bill Matix'!$D:$D,MATCH(A30,'[4]RT Description to Bill Matix'!$M:$M,0)) -> CDS PAS/HAB (CFC) and Transportation | H30: HAB TRANSPORTATION (CDS) | I30: Yes | J30: {=INDEX('Rate Table Service Desc XWalk'!F:F,MATCH(1,(G30='Rate Table Service Desc XWalk'!B:B)*(E30='Rate Table Service Desc XWalk'!A:A),0))} -> 2-5-143 | K30: =INDEX('[5]Combined Bill Code List'!$A:$A,MATCH(A30,'[5]Combined Bill Code List'!$F:$F,0)) -> 1915(c) waiver | L30: =INDEX('[6]Rate History'!$P:$P,MATCH(A30,'[6]Rate History'!$F:$F,0)) -> 1 hour | M30: =INDEX('[7]PDF DB Service Pivot'!$C:$C,MATCH(B30,'[7]PDF DB Service Pivot'!$B:$B,0)) -> 673 | N30: =IF(ISNUMBER(FIND("ISS",F30)),IF(I30="Yes",((M30/Q30)/6)*12,(M30/6)*12),IF(AND(I30="Yes",M30=O30),M30/Q30,M30)) -> 40.837379 | O30: =INDEX('[7]PDF DB Service Pivot'!$D:$D,MATCH(B30,'[7]PDF DB Service Pivot'!$B:$B,0)) -> 673 | P30: 45170 | Q30: 16.48 | R30: 13.27 | S30: =_xlfn.IFNA(R30/Q30,"") -> 0.80521845 | T30: 1 | U30: =ROUND(V30/Z30,2) -> 0 | V30: {=_xlfn.IFS('Fiscal by Program'!$B$7<10.61,0,'Fiscal by Program'!$B$7>10.6,(ROUND('Fiscal by Program'!$B$7*(1+IF(D30="Yes",'Fiscal by Program'!$B$9,'Fiscal by Program'!$B$8))*T30,2)))} -> 0 | W30: =IF(V30-R30<0,0,V30-R30) -> 0 | X30: =ROUND((R30/(1+IF(D30="Yes",'Fiscal by Program'!$B$9,'Fiscal by Program'!$B$8))),2)+0.01 -> 11.99 | Y30: =Q30+W30 -> 16.48 | Z30: 4 | AA30: =T30/Z30 -> 0.25 | AB30: =INDEX('[9]Service List'!$K:$K,MATCH(A30,'[9]Service List'!$F:$F,0)) -> 102 | AC30: =INDEX('[5]Combined Bill Code List'!$P:$P,MATCH(A30,'[5]Combined Bill Code List'!$F:$F,0)) -> 0 | AD30: DBMD | AE30: 1 | AF30: 0 | AG30: =ROUND(INDEX('All Trends'!D:D,MATCH($AD30,'All Trends'!$C:$C,0)),4) -> 0.9076 | AH30: =ROUND(INDEX('All Trends'!E:E,MATCH($AD30,'All Trends'!$C:$C,0)),4) -> 0.8915 | AI30: =ROUND(INDEX('All Trends'!F:F,MATCH($AD30,'All Trends'!$C:$C,0)),4) -> 0.9927 | AJ30: =ROUND(INDEX('All Trends'!G:G,MATCH($AD30,'All Trends'!$C:$C,0)),4) -> 0.9927 | AK30: =ROUND(INDEX('All Trends'!H:H,MATCH($AD30,'All Trends'!$C:$C,0)),4) -> 0.9927 | AL30: No | AM30: =IF(C30="Yes",ROUND(T30*N30*AI30,2),0) -> 40.54 | AN30: =IF(C30="Yes",ROUND(T30*N30*AJ30,2),0) -> 40.54 | AO30: =IF(C30="Yes",ROUND((W30*N30*AI30),2),0) -> 0 | AP30: =IF(C30="Yes",IF($AL30="No",ROUND(($AO30*($AY$2+$AF30)),2),ROUND($AO30,2)),0) -> 0 | AQ30: =IF(C30="Yes",ROUND((W30*N30*AJ30),2),0) -> 0 | AR30: =IF(C30="Yes",IF($AL30="No",ROUND(($AQ30*($AZ$2+$AF30)),2),ROUND($AQ30,2)),0) -> 0
A31: 717CG0740 | B31: 717CG0740 | C31: Yes | D31: No | E31: FC | F31: CAS/FC/PHC PAS | G31: =INDEX('[4]RT Description to Bill Matix'!$D:$D,MATCH(A31,'[4]RT Description to Bill Matix'!$M:$M,0)) -> CAS/FC/PAS/PHC PRIORITY | H31: PAS FAMILY CARE LVL 2 (PRIORITY) (AO) | J31: {=INDEX('Rate Table Service Desc XWalk'!F:F,MATCH(1,(G31='Rate Table Service Desc XWalk'!B:B)*(E31='Rate Table Service Desc XWalk'!A:A),0))} -> 13-1-8 | K31: =INDEX('[5]Combined Bill Code List'!$A:$A,MATCH(A31,'[5]Combined Bill Code List'!$F:$F,0)) -> Title XX | L31: =INDEX('[6]Rate History'!$P:$P,MATCH(A31,'[6]Rate History'!$F:$F,0)) -> 1 hour | M31: =INDEX('[7]PDF DB Service Pivot'!$C:$C,MATCH(B31,'[7]PDF DB Service Pivot'!$B:$B,0)) -> 41066.25 | N31: =IF(ISNUMBER(FIND("ISS",F31)),IF(I31="Yes",((M31/Q31)/6)*12,(M31/6)*12),IF(AND(I31="Yes",M31=O31),M31/Q31,M31)) -> 41066.25 | O31: =INDEX('[7]PDF DB Service Pivot'!$D:$D,MATCH(B31,'[7]PDF DB Service Pivot'!$B:$B,0)) -> 543104.29 | P31: 45170 | Q31: 14 | R31: 11.75 | S31: =_xlfn.IFNA(R31/Q31,"") -> 0.83928571 | T31: =INDEX('[8]Billable Services'!$P:$P,MATCH(B31,'[8]Billable Services'!$S:$S,0)) -> 1 | U31: =ROUND(V31/Z31,2) -> 0 | V31: {=_xlfn.IFS('Fiscal by Program'!$B$7<10.61,0,'Fiscal by Program'!$B$7>10.6,(ROUND('Fiscal by Program'!$B$7*(1+IF(D31="Yes",'Fiscal by Program'!$B$9,'Fiscal by Program'!$B$8))*T31,2)))} -> 0 | W31: =IF(V31-R31<0,0,V31-R31) -> 0 | X31: =ROUND((R31/(1+IF(D31="Yes",'Fiscal by Program'!$B$9,'Fiscal by Program'!$B$8))),2)+0.01 -> 10.62 | Y31: =Q31+W31 -> 14 | Z31: 4 | AA31: =T31/Z31 -> 0.25 | AB31: =INDEX('[9]Service List'!$K:$K,MATCH(A31,'[9]Service List'!$F:$F,0)) -> 168 | AC31: =INDEX('[5]Combined Bill Code List'!$P:$P,MATCH(A31,'[5]Combined Bill Code List'!$F:$F,0)) -> 0 | AD31: Title XX Flat | AE31: 1 | AF31: 0 | AG31: =ROUND(INDEX('All Trends'!D:D,MATCH($AD31,'All Trends'!$C:$C,0)),4) -> 1 | AH31: =ROUND(INDEX('All Trends'!E:E,MATCH($AD31,'All Trends'!$C:$C,0)),4) -> 1 | AI31: =ROUND(INDEX('All Trends'!F:F,MATCH($AD31,'All Trends'!$C:$C,0)),4) -> 1 | AJ31: =ROUND(INDEX('All Trends'!G:G,MATCH($AD31,'All Trends'!$C:$C,0)),4) -> 1 | AK31: =ROUND(INDEX('All Trends'!H:H,MATCH($AD31,'All Trends'!$C:$C,0)),4) -> 1 | AL31: Yes | AM31: =IF(C31="Yes",ROUND(T31*N31*AI31,2),0) -> 41066.25 | AN31: =IF(C31="Yes",ROUND(T31*N31*AJ31,2),0) -> 41066.25 | AO31: =IF(C31="Yes",ROUND((W31*N31*AI31),2),0) -> 0 | AP31: =IF(C31="Yes",IF($AL31="No",ROUND(($AO31*($AY$2+$AF31)),2),ROUND($AO31,2)),0) -> 0 | AQ31: =IF(C31="Yes",ROUND((W31*N31*AJ31),2),0) -> 0 | AR31: =IF(C31="Yes",IF($AL31="No",ROUND(($AQ31*($AZ$2+$AF31)),2),ROUND($AQ31,2)),0) -> 0
A32: 717CG0741 | B32: 717CG0741 | C32: Yes | D32: No | E32: FC | F32: CAS/FC/PHC PAS | G32: =INDEX('[4]RT Description to Bill Matix'!$D:$D,MATCH(A32,'[4]RT Description to Bill Matix'!$M:$M,0)) -> CAS/FC/PAS/PHC NON-PRIORITY | H32: PAS FAMILY CARE LVL 1 (NON-PRIORITY) (AO) | J32: {=INDEX('Rate Table Service Desc XWalk'!F:F,MATCH(1,(G32='Rate Table Service Desc XWalk'!B:B)*(E32='Rate Table Service Desc XWalk'!A:A),0))} -> 13-1-7 | K32: =INDEX('[5]Combined Bill Code List'!$A:$A,MATCH(A32,'[5]Combined Bill Code List'!$F:$F,0)) -> Title XX | L32: =INDEX('[6]Rate History'!$P:$P,MATCH(A32,'[6]Rate History'!$F:$F,0)) -> 1 hour | M32: =INDEX('[7]PDF DB Service Pivot'!$C:$C,MATCH(B32,'[7]PDF DB Service Pivot'!$B:$B,0)) -> 3035010.4 | N32: =IF(ISNUMBER(FIND("ISS",F32)),IF(I32="Yes",((M32/Q32)/6)*12,(M32/6)*12),IF(AND(I32="Yes",M32=O32),M32/Q32,M32)) -> 3035010.4 | O32: =INDEX('[7]PDF DB Service Pivot'!$D:$D,MATCH(B32,'[7]PDF DB Service Pivot'!$B:$B,0)) -> 39362252 | P32: 45170 | Q32: 13.84 | R32: 11.77 | S32: =_xlfn.IFNA(R32/Q32,"") -> 0.85043353 | T32: =INDEX('[8]Billable Services'!$P:$P,MATCH(B32,'[8]Billable Services'!$S:$S,0)) -> 1 | U32: =ROUND(V32/Z32,2) -> 0 | V32: {=_xlfn.IFS('Fiscal by Program'!$B$7<10.61,0,'Fiscal by Program'!$B$7>10.6,(ROUND('Fiscal by Program'!$B$7*(1+IF(D32="Yes",'Fiscal by Program'!$B$9,'Fiscal by Program'!$B$8))*T32,2)))} -> 0 | W32: =IF(V32-R32<0,0,V32-R32) -> 0 | X32: =ROUND((R32/(1+IF(D32="Yes",'Fiscal by Program'!$B$9,'Fiscal by Program'!$B$8))),2)+0.01 -> 10.64 | Y32: =Q32+W32 -> 13.84 | Z32: 4 | AA32: =T32/Z32 -> 0.25 | AB32: =INDEX('[9]Service List'!$K:$K,MATCH(A32,'[9]Service List'!$F:$F,0)) -> 167 | AC32: =INDEX('[5]Combined Bill Code List'!$P:$P,MATCH(A32,'[5]Combined Bill Code List'!$F:$F,0)) -> 0 | AD32: Title XX Flat | AE32: 1 | AF32: 0 | AG32: =ROUND(INDEX('All Trends'!D:D,MATCH($AD32,'All Trends'!$C:$C,0)),4) -> 1 | AH32: =ROUND(INDEX('All Trends'!E:E,MATCH($AD32,'All Trends'!$C:$C,0)),4) -> 1 | AI32: =ROUND(INDEX('All Trends'!F:F,MATCH($AD32,'All Trends'!$C:$C,0)),4) -> 1 | AJ32: =ROUND(INDEX('All Trends'!G:G,MATCH($AD32,'All Trends'!$C:$C,0)),4) -> 1 | AK32: =ROUND(INDEX('All Trends'!H:H,MATCH($AD32,'All Trends'!$C:$C,0)),4) -> 1 | AL32: Yes | AM32: =IF(C32="Yes",ROUND(T32*N32*AI32,2),0) -> 3035010.4 | AN32: =IF(C32="Yes",ROUND(T32*N32*AJ32,2),0) -> 3035010.4 | AO32: =IF(C32="Yes",ROUND((W32*N32*AI32),2),0) -> 0 | AP32: =IF(C32="Yes",IF($AL32="No",ROUND(($AO32*($AY$2+$AF32)),2),ROUND($AO32,2)),0) -> 0 | AQ32: =IF(C32="Yes",ROUND((W32*N32*AJ32),2),0) -> 0 | AR32: =IF(C32="Yes",IF($AL32="No",ROUND(($AQ32*($AZ$2+$AF32)),2),ROUND($AQ32,2)),0) -> 0
A33: 717CVG0745 | B33: 717CVG0745 | C33: Yes | D33: No | E33: FC | F33: CAS/FC/PHC PAS | G33: =INDEX('[4]RT Description to Bill Matix'!$D:$D,MATCH(A33,'[4]RT Description to Bill Matix'!$M:$M,0)) -> CDS CAS/FC/PAS/PHC PRIORITY | H33: PARTICIPANT PAS FAMILY CARE (CDS) LVL 2 (PRIORITY) | I33: Yes | J33: {=INDEX('Rate Table Service Desc XWalk'!F:F,MATCH(1,(G33='Rate Table Service Desc XWalk'!B:B)*(E33='Rate Table Service Desc XWalk'!A:A),0))} -> 13-5-117 | K33: =INDEX('[5]Combined Bill Code List'!$A:$A,MATCH(A33,'[5]Combined Bill Code List'!$F:$F,0)) -> Title XX | L33: =INDEX('[6]Rate History'!$P:$P,MATCH(A33,'[6]Rate History'!$F:$F,0)) -> 1 hour | M33: =INDEX('[7]PDF DB Service Pivot'!$C:$C,MATCH(B33,'[7]PDF DB Service Pivot'!$B:$B,0)) -> 6431.27 | N33: =IF(ISNUMBER(FIND("ISS",F33)),IF(I33="Yes",((M33/Q33)/6)*12,(M33/6)*12),IF(AND(I33="Yes",M33=O33),M33/Q33,M33)) -> 487.21742 | O33: =INDEX('[7]PDF DB Service Pivot'!$D:$D,MATCH(B33,'[7]PDF DB Service Pivot'!$B:$B,0)) -> 6431.27 | P33: 45170 | Q33: 13.2 | R33: 11.75 | S33: =_xlfn.IFNA(R33/Q33,"") -> 0.89015152 | T33: 1 | U33: =ROUND(V33/Z33,2) -> 0 | V33: {=_xlfn.IFS('Fiscal by Program'!$B$7<10.61,0,'Fiscal by Program'!$B$7>10.6,(ROUND('Fiscal by Program'!$B$7*(1+IF(D33="Yes",'Fiscal by Program'!$B$9,'Fiscal by Program'!$B$8))*T33,2)))} -> 0 | W33: =IF(V33-R33<0,0,V33-R33) -> 0 | X33: =ROUND((R33/(1+IF(D33="Yes",'Fiscal by Program'!$B$9,'Fiscal by Program'!$B$8))),2)+0.01 -> 10.62 | Y33: =Q33+W33 -> 13.2 | Z33: 4 | AA33: =T33/Z33 -> 0.25 | AB33: =INDEX('[9]Service List'!$K:$K,MATCH(A33,'[9]Service List'!$F:$F,0)) -> 170 | AC33: =INDEX('[5]Combined Bill Code List'!$P:$P,MATCH(A33,'[5]Combined Bill Code List'!$F:$F,0)) -> 0 | AD33: Title XX Flat | AE33: 1 | AF33: 0 | AG33: =ROUND(INDEX('All Trends'!D:D,MATCH($AD33,'All Trends'!$C:$C,0)),4) -> 1 | AH33: =ROUND(INDEX('All Trends'!E:E,MATCH($AD33,'All Trends'!$C:$C,0)),4) -> 1 | AI33: =ROUND(INDEX('All Trends'!F:F,MATCH($AD33,'All Trends'!$C:$C,0)),4) -> 1 | AJ33: =ROUND(INDEX('All Trends'!G:G,MATCH($AD33,'All Trends'!$C:$C,0)),4) -> 1 | AK33: =ROUND(INDEX('All Trends'!H:H,MATCH($AD33,'All Trends'!$C:$C,0)),4) -> 1 | AL33: Yes | AM33: =IF(C33="Yes",ROUND(T33*N33*AI33,2),0) -> 487.22 | AN33: =IF(C33="Yes",ROUND(T33*N33*AJ33,2),0) -> 487.22 | AO33: =IF(C33="Yes",ROUND((W33*N33*AI33),2),0) -> 0 | AP33: =IF(C33="Yes",IF($AL33="No",ROUND(($AO33*($AY$2+$AF33)),2),ROUND($AO33,2)),0) -> 0 | AQ33: =IF(C33="Yes",ROUND((W33*N33*AJ33),2),0) -> 0 | AR33: =IF(C33="Yes",IF($AL33="No",ROUND(($AQ33*($AZ$2+$AF33)),2),ROUND($AQ33,2)),0) -> 0
A34: 717CVG0746 | B34: 717CVG0746 | C34: Yes | D34: No | E34: FC | F34: CAS/FC/PHC PAS | G34: =INDEX('[4]RT Description to Bill Matix'!$D:$D,MATCH(A34,'[4]RT Description to Bill Matix'!$M:$M,0)) -> CDS CAS/FC/PAS/PHC NON-PRIORITY | H34: PARTICIPANT PAS FAMILY CARE (CDS) LVL 1 (NON-PRIORITY) | I34: Yes | J34: {=INDEX('Rate Table Service Desc XWalk'!F:F,MATCH(1,(G34='Rate Table Service Desc XWalk'!B:B)*(E34='Rate Table Service Desc XWalk'!A:A),0))} -> 13-5-116 | K34: =INDEX('[5]Combined Bill Code List'!$A:$A,MATCH(A34,'[5]Combined Bill Code List'!$F:$F,0)) -> Title XX | L34: =INDEX('[6]Rate History'!$P:$P,MATCH(A34,'[6]Rate History'!$F:$F,0)) -> 1 hour | M34: =INDEX('[7]PDF DB Service Pivot'!$C:$C,MATCH(B34,'[7]PDF DB Service Pivot'!$B:$B,0)) -> 231980.7 | N34: =IF(ISNUMBER(FIND("ISS",F34)),IF(I34="Yes",((M34/Q34)/6)*12,(M34/6)*12),IF(AND(I34="Yes",M34=O34),M34/Q34,M34)) -> 17789.931 | O34: =INDEX('[7]PDF DB Service Pivot'!$D:$D,MATCH(B34,'[7]PDF DB Service Pivot'!$B:$B,0)) -> 231980.7 | P34: 45170 | Q34: 13.04 | R34: 11.77 | S34: =_xlfn.IFNA(R34/Q34,"") -> 0.90260736 | T34: 1 | U34: =ROUND(V34/Z34,2) -> 0 | V34: {=_xlfn.IFS('Fiscal by Program'!$B$7<10.61,0,'Fiscal by Program'!$B$7>10.6,(ROUND('Fiscal by Program'!$B$7*(1+IF(D34="Yes",'Fiscal by Program'!$B$9,'Fiscal by Program'!$B$8))*T34,2)))} -> 0 | W34: =IF(V34-R34<0,0,V34-R34) -> 0 | X34: =ROUND((R34/(1+IF(D34="Yes",'Fiscal by Program'!$B$9,'Fiscal by Program'!$B$8))),2)+0.01 -> 10.64 | Y34: =Q34+W34 -> 13.04 | Z34: 4 | AA34: =T34/Z34 -> 0.25 | AB34: =INDEX('[9]Service List'!$K:$K,MATCH(A34,'[9]Service List'!$F:$F,0)) -> 169 | AC34: =INDEX('[5]Combined Bill Code List'!$P:$P,MATCH(A34,'[5]Combined Bill Code List'!$F:$F,0)) -> 0 | AD34: Title XX Flat | AE34: 1 | AF34: 0 | AG34: =ROUND(INDEX('All Trends'!D:D,MATCH($AD34,'All Trends'!$C:$C,0)),4) -> 1 | AH34: =ROUND(INDEX('All Trends'!E:E,MATCH($AD34,'All Trends'!$C:$C,0)),4) -> 1 | AI34: =ROUND(INDEX('All Trends'!F:F,MATCH($AD34,'All Trends'!$C:$C,0)),4) -> 1 | AJ34: =ROUND(INDEX('All Trends'!G:G,MATCH($AD34,'All Trends'!$C:$C,0)),4) -> 1 | AK34: =ROUND(INDEX('All Trends'!H:H,MATCH($AD34,'All Trends'!$C:$C,0)),4) -> 1 | AL34: Yes | AM34: =IF(C34="Yes",ROUND(T34*N34*AI34,2),0) -> 17789.93 | AN34: =IF(C34="Yes",ROUND(T34*N34*AJ34,2),0) -> 17789.93 | AO34: =IF(C34="Yes",ROUND((W34*N34*AI34),2),0) -> 0 | AP34: =IF(C34="Yes",IF($AL34="No",ROUND(($AO34*($AY$2+$AF34)),2),ROUND($AO34,2)),0) -> 0 | AQ34: =IF(C34="Yes",ROUND((W34*N34*AJ34),2),0) -> 0 | AR34: =IF(C34="Yes",IF($AL34="No",ROUND(($AQ34*($AZ$2+$AF34)),2),ROUND($AQ34,2)),0) -> 0
A35: T2031HKHE | B35: T2031HKHE | C35: Yes | D35: Yes | E35: HCBS-AMH | F35: Assisted Living | G35: Assisted Living Services | H35: Assisted Living Services | J35: 14-1-3 | K35: 1915(i) State Plan (Title XIX) | L35: 1 day | M35: 171 | N35: =IF(ISNUMBER(FIND("ISS",F35)),IF(I35="Yes",((M35/Q35)/6)*12,(M35/6)*12),IF(AND(I35="Yes",M35=O35),M35/Q35,M35)) -> 171 | O35: 5381.37 | P35: 45170 | Q35: 33.4 | R35: 19.87 | S35: 0.59491018 | T35: 2.51 | U35: =ROUND(V35/Z35,2) -> 0 | V35: {=_xlfn.IFS('Fiscal by Program'!$B$7<10.61,0,'Fiscal by Program'!$B$7>10.6,(ROUND('Fiscal by Program'!$B$7*(1+IF(D35="Yes",'Fiscal by Program'!$B$9,'Fiscal by Program'!$B$8))*T35,2)))} -> 0 | W35: =IF(V35-R35<0,0,V35-R35) -> 0 | X35: =ROUND((R35/(1+IF(D35="Yes",'Fiscal by Program'!$B$9,'Fiscal by Program'!$B$8))),2)+0.01 -> 17.95 | Y35: =Q35+W35 -> 33.4 | Z35: 96 | AA35: =T35/Z35 -> 0.026145833 | AC35: 0 | AD35: HCBS-AMH | AE35: 1 | AF35: 0 | AG35: =ROUND(INDEX('All Trends'!D:D,MATCH($AD35,'All Trends'!$C:$C,0)),4) -> 1 | AH35: =ROUND(INDEX('All Trends'!E:E,MATCH($AD35,'All Trends'!$C:$C,0)),4) -> 1 | AI35: =ROUND(INDEX('All Trends'!F:F,MATCH($AD35,'All Trends'!$C:$C,0)),4) -> 1 | AJ35: =ROUND(INDEX('All Trends'!G:G,MATCH($AD35,'All Trends'!$C:$C,0)),4) -> 1 | AK35: =ROUND(INDEX('All Trends'!H:H,MATCH($AD35,'All Trends'!$C:$C,0)),4) -> 1 | AL35: No | AM35: =IF(C35="Yes",ROUND(T35*N35*AI35,2),0) -> 429.21 | AN35: =IF(C35="Yes",ROUND(T35*N35*AJ35,2),0) -> 429.21 | AO35: =IF(C35="Yes",ROUND((W35*N35*AI35),2),0) -> 0 | AP35: =IF(C35="Yes",IF($AL35="No",ROUND(($AO35*($AY$2+$AF35)),2),ROUND($AO35,2)),0) -> 0 | AQ35: =IF(C35="Yes",ROUND((W35*N35*AJ35),2),0) -> 0 | AR35: =IF(C35="Yes",IF($AL35="No",ROUND(($AQ35*($AZ$2+$AF35)),2),ROUND($AQ35,2)),0) -> 0
A36: H2013HKHE | B36: H2013HKHE | C36: Yes | D36: No | E36: HCBS-AMH | F36: SL/RSS | G36: Supervised Living Services | H36: Supervised Living Services | J36: 14-1-97 | K36: 1915(i) State Plan (Title XIX) | L36: 1 day = 18 hours, excluding 6 hours for Day Hab | M36: 99876 | N36: =IF(ISNUMBER(FIND("ISS",F36)),IF(I36="Yes",((M36/Q36)/6)*12,(M36/6)*12),IF(AND(I36="Yes",M36=O36),M36/Q36,M36)) -> 99876 | O36: 14691021 | P36: 41760 | Q36: 147.12 | R36: =Q36*0.523 -> 76.94376 | S36: =_xlfn.IFNA(R36/Q36,"") -> 0.523 | T36: 7.37 | U36: =ROUND(V36/Z36,2) -> 0 | V36: {=_xlfn.IFS('Fiscal by Program'!$B$7<10.61,0,'Fiscal by Program'!$B$7>10.6,(ROUND('Fiscal by Program'!$B$7*(1+IF(D36="Yes",'Fiscal by Program'!$B$9,'Fiscal by Program'!$B$8))*T36,2)))} -> 0 | W36: =IF(V36-R36<0,0,V36-R36) -> 0 | X36: =ROUND((R36/(1+IF(D36="Yes",'Fiscal by Program'!$B$9,'Fiscal by Program'!$B$8))),2)+0.01 -> 69.49 | Y36: =Q36+W36 -> 147.12 | Z36: 72 | AA36: =T36/Z36 -> 0.10236111 | AC36: 0 | AD36: HCBS-AMH | AE36: 1 | AF36: 0 | AG36: =ROUND(INDEX('All Trends'!D:D,MATCH($AD36,'All Trends'!$C:$C,0)),4) -> 1 | AH36: =ROUND(INDEX('All Trends'!E:E,MATCH($AD36,'All Trends'!$C:$C,0)),4) -> 1 | AI36: =ROUND(INDEX('All Trends'!F:F,MATCH($AD36,'All Trends'!$C:$C,0)),4) -> 1 | AJ36: =ROUND(INDEX('All Trends'!G:G,MATCH($AD36,'All Trends'!$C:$C,0)),4) -> 1 | AK36: =ROUND(INDEX('All Trends'!H:H,MATCH($AD36,'All Trends'!$C:$C,0)),4) -> 1 | AL36: No | AM36: =IF(C36="Yes",ROUND(T36*N36*AI36,2),0) -> 736086.12 | AN36: =IF(C36="Yes",ROUND(T36*N36*AJ36,2),0) -> 736086.12 | AO36: =IF(C36="Yes",ROUND((W36*N36*AI36),2),0) -> 0 | AP36: =IF(C36="Yes",IF($AL36="No",ROUND(($AO36*($AY$2+$AF36)),2),ROUND($AO36,2)),0) -> 0 | AQ36: =IF(C36="Yes",ROUND((W36*N36*AJ36),2),0) -> 0 | AR36: =IF(C36="Yes",IF($AL36="No",ROUND(($AQ36*($AZ$2+$AF36)),2),ROUND($AQ36,2)),0) -> 0
A37: S5130HKHE | B37: S5130HKHE | C37: Yes | D37: No | E37: HCBS-AMH | F37: PAS/HAB | G37: Supported Home Living | H37: Supported Home Living | J37: 14-1-98 | K37: 1915(i) State Plan (Title XIX) | L37: 15 minutes | M37: 9290 | N37: =IF(ISNUMBER(FIND("ISS",F37)),IF(I37="Yes",((M37/Q37)/6)*12,(M37/6)*12),IF(AND(I37="Yes",M37=O37),M37/Q37,M37)) -> 9290 | O37: 64145.7 | P37: 44287 | Q37: 5.6 | R37: =Q37*0.825 -> 4.62 | S37: =_xlfn.IFNA(R37/Q37,"") -> 0.825 | T37: 0.25 | U37: =ROUND(V37/Z37,2) -> 0 | V37: {=_xlfn.IFS('Fiscal by Program'!$B$7<10.61,0,'Fiscal by Program'!$B$7>10.6,(ROUND('Fiscal by Program'!$B$7*(1+IF(D37="Yes",'Fiscal by Program'!$B$9,'Fiscal by Program'!$B$8))*T37,2)))} -> 0 | W37: =IF(V37-R37<0,0,V37-R37) -> 0 | X37: =ROUND((R37/(1+IF(D37="Yes",'Fiscal by Program'!$B$9,'Fiscal by Program'!$B$8))),2)+0.01 -> 4.18 | Y37: =Q37+W37 -> 5.6 | Z37: 1 | AA37: =T37/Z37 -> 0.25 | AC37: 0 | AD37: HCBS-AMH | AE37: 1 | AF37: 0 | AG37: =ROUND(INDEX('All Trends'!D:D,MATCH($AD37,'All Trends'!$C:$C,0)),4) -> 1 | AH37: =ROUND(INDEX('All Trends'!E:E,MATCH($AD37,'All Trends'!$C:$C,0)),4) -> 1 | AI37: =ROUND(INDEX('All Trends'!F:F,MATCH($AD37,'All Trends'!$C:$C,0)),4) -> 1 | AJ37: =ROUND(INDEX('All Trends'!G:G,MATCH($AD37,'All Trends'!$C:$C,0)),4) -> 1 | AK37: =ROUND(INDEX('All Trends'!H:H,MATCH($AD37,'All Trends'!$C:$C,0)),4) -> 1 | AL37: No | AM37: =IF(C37="Yes",ROUND(T37*N37*AI37,2),0) -> 2322.5 | AN37: =IF(C37="Yes",ROUND(T37*N37*AJ37,2),0) -> 2322.5 | AO37: =IF(C37="Yes",ROUND((W37*N37*AI37),2),0) -> 0 | AP37: =IF(C37="Yes",IF($AL37="No",ROUND(($AO37*($AY$2+$AF37)),2),ROUND($AO37,2)),0) -> 0 | AQ37: =IF(C37="Yes",ROUND((W37*N37*AJ37),2),0) -> 0 | AR37: =IF(C37="Yes",IF($AL37="No",ROUND(($AQ37*($AZ$2+$AF37)),2),ROUND($AQ37,2)),0) -> 0
A38: 2110CFCM0354 | B38: 2110CFCM0354 | C38: Yes | D38: No | E38: HCS | F38: PAS/HAB | G38: =INDEX('[4]RT Description to Bill Matix'!$D:$D,MATCH(A38,'[4]RT Description to Bill Matix'!$M:$M,0)) -> PAS/HAB (CFC) and Transportation | H38: CFC PAS/HAB LOC 1 | J38: {=INDEX('Rate Table Service Desc XWalk'!F:F,MATCH(1,(G38='Rate Table Service Desc XWalk'!B:B)*(E38='Rate Table Service Desc XWalk'!A:A),0))} -> 3-1-79 | K38: =INDEX('[5]Combined Bill Code List'!$A:$A,MATCH(A38,'[5]Combined Bill Code List'!$F:$F,0)) -> State Plan (Title XIX) | L38: =INDEX('[6]Rate History'!$P:$P,MATCH(A38,'[6]Rate History'!$F:$F,0)) -> 1 hour | M38: =INDEX('[7]PDF DB Service Pivot'!$C:$C,MATCH(B38,'[7]PDF DB Service Pivot'!$B:$B,0)) -> 1668316.4 | N38: =IF(ISNUMBER(FIND("ISS",F38)),IF(I38="Yes",((M38/Q38)/6)*12,(M38/6)*12),IF(AND(I38="Yes",M38=O38),M38/Q38,M38)) -> 1668316.4 | O38: =INDEX('[7]PDF DB Service Pivot'!$D:$D,MATCH(B38,'[7]PDF DB Service Pivot'!$B:$B,0)) -> 31345024 | P38: 45170 | Q38: 18.36 | R38: 15.15 | S38: =_xlfn.IFNA(R38/Q38,"") -> 0.8251634 | T38: 1 | U38: =ROUND(V38/Z38,2) -> 0 | V38: {=_xlfn.IFS('Fiscal by Program'!$B$7<10.61,0,'Fiscal by Program'!$B$7>10.6,(ROUND('Fiscal by Program'!$B$7*(1+IF(D38="Yes",'Fiscal by Program'!$B$9,'Fiscal by Program'!$B$8))*T38,2)))} -> 0 | W38: =IF(V38-R38<0,0,V38-R38) -> 0 | X38: =ROUND((R38/(1+IF(D38="Yes",'Fiscal by Program'!$B$9,'Fiscal by Program'!$B$8))),2)+0.01 -> 13.69 | Y38: =Q38+W38 -> 18.36 | Z38: 4 | AA38: =T38/Z38 -> 0.25 | AB38: =INDEX('[9]Service List'!$K:$K,MATCH(A38,'[9]Service List'!$F:$F,0)) -> 284 | AC38: =INDEX('[5]Combined Bill Code List'!$P:$P,MATCH(A38,'[5]Combined Bill Code List'!$F:$F,0)) -> CFC | AD38: HCS | AE38: 1 | AF38: -0.06 | AG38: =ROUND(INDEX('All Trends'!D:D,MATCH($AD38,'All Trends'!$C:$C,0)),4) -> 0.9927 | AH38: =ROUND(INDEX('All Trends'!E:E,MATCH($AD38,'All Trends'!$C:$C,0)),4) -> 1.0091 | AI38: =ROUND(INDEX('All Trends'!F:F,MATCH($AD38,'All Trends'!$C:$C,0)),4) -> 1.0519 | AJ38: =ROUND(INDEX('All Trends'!G:G,MATCH($AD38,'All Trends'!$C:$C,0)),4) -> 1.0519 | AK38: =ROUND(INDEX('All Trends'!H:H,MATCH($AD38,'All Trends'!$C:$C,0)),4) -> 1.0519 | AL38: No | AM38: =IF(C38="Yes",ROUND(T38*N38*AI38,2),0) -> 1754902 | AN38: =IF(C38="Yes",ROUND(T38*N38*AJ38,2),0) -> 1754902 | AO38: =IF(C38="Yes",ROUND((W38*N38*AI38),2),0) -> 0 | AP38: =IF(C38="Yes",IF($AL38="No",ROUND(($AO38*($AY$2+$AF38)),2),ROUND($AO38,2)),0) -> 0 | AQ38: =IF(C38="Yes",ROUND((W38*N38*AJ38),2),0) -> 0 | AR38: =IF(C38="Yes",IF($AL38="No",ROUND(($AQ38*($AZ$2+$AF38)),2),ROUND($AQ38,2)),0) -> 0
A39: 2110CFCM0366 | B39: 2110CFCM0366 | C39: Yes | D39: No | E39: HCS | F39: PAS/HAB | G39: =INDEX('[4]RT Description to Bill Matix'!$D:$D,MATCH(A39,'[4]RT Description to Bill Matix'!$M:$M,0)) -> PAS/HAB (CFC) and Transportation | H39: CFC PAS/HAB LOC 8 | J39: {=INDEX('Rate Table Service Desc XWalk'!F:F,MATCH(1,(G39='Rate Table Service Desc XWalk'!B:B)*(E39='Rate Table Service Desc XWalk'!A:A),0))} -> 3-1-79 | K39: =INDEX('[5]Combined Bill Code List'!$A:$A,MATCH(A39,'[5]Combined Bill Code List'!$F:$F,0)) -> State Plan (Title XIX) | L39: =INDEX('[6]Rate History'!$P:$P,MATCH(A39,'[6]Rate History'!$F:$F,0)) -> 1 hour | M39: =INDEX('[7]PDF DB Service Pivot'!$C:$C,MATCH(B39,'[7]PDF DB Service Pivot'!$B:$B,0)) -> 21089.25 | N39: =IF(ISNUMBER(FIND("ISS",F39)),IF(I39="Yes",((M39/Q39)/6)*12,(M39/6)*12),IF(AND(I39="Yes",M39=O39),M39/Q39,M39)) -> 21089.25 | O39: =INDEX('[7]PDF DB Service Pivot'!$D:$D,MATCH(B39,'[7]PDF DB Service Pivot'!$B:$B,0)) -> 393767.36 | P39: 45170 | Q39: 18.36 | R39: 15.15 | S39: =_xlfn.IFNA(R39/Q39,"") -> 0.8251634 | T39: 1 | U39: =ROUND(V39/Z39,2) -> 0 | V39: {=_xlfn.IFS('Fiscal by Program'!$B$7<10.61,0,'Fiscal by Program'!$B$7>10.6,(ROUND('Fiscal by Program'!$B$7*(1+IF(D39="Yes",'Fiscal by Program'!$B$9,'Fiscal by Program'!$B$8))*T39,2)))} -> 0 | W39: =IF(V39-R39<0,0,V39-R39) -> 0 | X39: =ROUND((R39/(1+IF(D39="Yes",'Fiscal by Program'!$B$9,'Fiscal by Program'!$B$8))),2)+0.01 -> 13.69 | Y39: =Q39+W39 -> 18.36 | Z39: 4 | AA39: =T39/Z39 -> 0.25 | AB39: =INDEX('[9]Service List'!$K:$K,MATCH(A39,'[9]Service List'!$F:$F,0)) -> 285 | AC39: =INDEX('[5]Combined Bill Code List'!$P:$P,MATCH(A39,'[5]Combined Bill Code List'!$F:$F,0)) -> CFC | AD39: HCS | AE39: 1 | AF39: -0.06 | AG39: =ROUND(INDEX('All Trends'!D:D,MATCH($AD39,'All Trends'!$C:$C,0)),4) -> 0.9927 | AH39: =ROUND(INDEX('All Trends'!E:E,MATCH($AD39,'All Trends'!$C:$C,0)),4) -> 1.0091 | AI39: =ROUND(INDEX('All Trends'!F:F,MATCH($AD39,'All Trends'!$C:$C,0)),4) -> 1.0519 | AJ39: =ROUND(INDEX('All Trends'!G:G,MATCH($AD39,'All Trends'!$C:$C,0)),4) -> 1.0519 | AK39: =ROUND(INDEX('All Trends'!H:H,MATCH($AD39,'All Trends'!$C:$C,0)),4) -> 1.0519 | AL39: No | AM39: =IF(C39="Yes",ROUND(T39*N39*AI39,2),0) -> 22183.78 | AN39: =IF(C39="Yes",ROUND(T39*N39*AJ39,2),0) -> 22183.78 | AO39: =IF(C39="Yes",ROUND((W39*N39*AI39),2),0) -> 0 | AP39: =IF(C39="Yes",IF($AL39="No",ROUND(($AO39*($AY$2+$AF39)),2),ROUND($AO39,2)),0) -> 0 | AQ39: =IF(C39="Yes",ROUND((W39*N39*AJ39),2),0) -> 0 | AR39: =IF(C39="Yes",IF($AL39="No",ROUND(($AQ39*($AZ$2+$AF39)),2),ROUND($AQ39,2)),0) -> 0
A40: 2110CFVM0355 | B40: 2110CFVM0355 | C40: Yes | D40: No | E40: HCS | F40: PAS/HAB | G40: =INDEX('[4]RT Description to Bill Matix'!$D:$D,MATCH(A40,'[4]RT Description to Bill Matix'!$M:$M,0)) -> CDS PAS/HAB (CFC) and Transportation | H40: CFC PAS/HAB (CDS) LOC 1 | I40: Yes | J40: {=INDEX('Rate Table Service Desc XWalk'!F:F,MATCH(1,(G40='Rate Table Service Desc XWalk'!B:B)*(E40='Rate Table Service Desc XWalk'!A:A),0))} -> 3-5-143 | K40: =INDEX('[5]Combined Bill Code List'!$A:$A,MATCH(A40,'[5]Combined Bill Code List'!$F:$F,0)) -> State Plan (Title XIX) | L40: =INDEX('[6]Rate History'!$P:$P,MATCH(A40,'[6]Rate History'!$F:$F,0)) -> 1 hour | M40: =INDEX('[7]PDF DB Service Pivot'!$C:$C,MATCH(B40,'[7]PDF DB Service Pivot'!$B:$B,0)) -> 61516838 | N40: =IF(ISNUMBER(FIND("ISS",F40)),IF(I40="Yes",((M40/Q40)/6)*12,(M40/6)*12),IF(AND(I40="Yes",M40=O40),M40/Q40,M40)) -> 2693381.7 | O40: =INDEX('[7]PDF DB Service Pivot'!$D:$D,MATCH(B40,'[7]PDF DB Service Pivot'!$B:$B,0)) -> 61516838 | P40: 45170 | Q40: 22.84 | R40: 18.84 | S40: =_xlfn.IFNA(R40/Q40,"") -> 0.82486865 | T40: 1 | U40: =ROUND(V40/Z40,2) -> 0 | V40: {=_xlfn.IFS('Fiscal by Program'!$B$7<10.61,0,'Fiscal by Program'!$B$7>10.6,(ROUND('Fiscal by Program'!$B$7*(1+IF(D40="Yes",'Fiscal by Program'!$B$9,'Fiscal by Program'!$B$8))*T40,2)))} -> 0 | W40: =IF(V40-R40<0,0,V40-R40) -> 0 | X40: =ROUND((R40/(1+IF(D40="Yes",'Fiscal by Program'!$B$9,'Fiscal by Program'!$B$8))),2)+0.01 -> 17.02 | Y40: =Q40+W40 -> 22.84 | Z40: 4 | AA40: =T40/Z40 -> 0.25 | AB40: =INDEX('[9]Service List'!$K:$K,MATCH(A40,'[9]Service List'!$F:$F,0)) -> 282 | AC40: =INDEX('[5]Combined Bill Code List'!$P:$P,MATCH(A40,'[5]Combined Bill Code List'!$F:$F,0)) -> CFC | AD40: HCS | AE40: 1 | AF40: -0.06 | AG40: =ROUND(INDEX('All Trends'!D:D,MATCH($AD40,'All Trends'!$C:$C,0)),4) -> 0.9927 | AH40: =ROUND(INDEX('All Trends'!E:E,MATCH($AD40,'All Trends'!$C:$C,0)),4) -> 1.0091 | AI40: =ROUND(INDEX('All Trends'!F:F,MATCH($AD40,'All Trends'!$C:$C,0)),4) -> 1.0519 | AJ40: =ROUND(INDEX('All Trends'!G:G,MATCH($AD40,'All Trends'!$C:$C,0)),4) -> 1.0519 | AK40: =ROUND(INDEX('All Trends'!H:H,MATCH($AD40,'All Trends'!$C:$C,0)),4) -> 1.0519 | AL40: No | AM40: =IF(C40="Yes",ROUND(T40*N40*AI40,2),0) -> 2833168.2 | AN40: =IF(C40="Yes",ROUND(T40*N40*AJ40,2),0) -> 2833168.2 | AO40: =IF(C40="Yes",ROUND((W40*N40*AI40),2),0) -> 0 | AP40: =IF(C40="Yes",IF($AL40="No",ROUND(($AO40*($AY$2+$AF40)),2),ROUND($AO40,2)),0) -> 0 | AQ40: =IF(C40="Yes",ROUND((W40*N40*AJ40),2),0) -> 0 | AR40: =IF(C40="Yes",IF($AL40="No",ROUND(($AQ40*($AZ$2+$AF40)),2),ROUND($AQ40,2)),0) -> 0
A41: 2110CFVM0367 | B41: 2110CFVM0367 | C41: Yes | D41: No | E41: HCS | F41: PAS/HAB | G41: =INDEX('[4]RT Description to Bill Matix'!$D:$D,MATCH(A41,'[4]RT Description to Bill Matix'!$M:$M,0)) -> CDS PAS/HAB (CFC) and Transportation | H41: CFC PAS/HAB (CDS) LOC 8 | I41: Yes | J41: {=INDEX('Rate Table Service Desc XWalk'!F:F,MATCH(1,(G41='Rate Table Service Desc XWalk'!B:B)*(E41='Rate Table Service Desc XWalk'!A:A),0))} -> 3-5-143 | K41: =INDEX('[5]Combined Bill Code List'!$A:$A,MATCH(A41,'[5]Combined Bill Code List'!$F:$F,0)) -> State Plan (Title XIX) | L41: =INDEX('[6]Rate History'!$P:$P,MATCH(A41,'[6]Rate History'!$F:$F,0)) -> 1 hour | M41: =INDEX('[7]PDF DB Service Pivot'!$C:$C,MATCH(B41,'[7]PDF DB Service Pivot'!$B:$B,0)) -> 750317.56 | N41: =IF(ISNUMBER(FIND("ISS",F41)),IF(I41="Yes",((M41/Q41)/6)*12,(M41/6)*12),IF(AND(I41="Yes",M41=O41),M41/Q41,M41)) -> 32851.032 | O41: =INDEX('[7]PDF DB Service Pivot'!$D:$D,MATCH(B41,'[7]PDF DB Service Pivot'!$B:$B,0)) -> 750317.56 | P41: 45170 | Q41: 22.84 | R41: 18.84 | S41: =_xlfn.IFNA(R41/Q41,"") -> 0.82486865 | T41: 1 | U41: =ROUND(V41/Z41,2) -> 0 | V41: {=_xlfn.IFS('Fiscal by Program'!$B$7<10.61,0,'Fiscal by Program'!$B$7>10.6,(ROUND('Fiscal by Program'!$B$7*(1+IF(D41="Yes",'Fiscal by Program'!$B$9,'Fiscal by Program'!$B$8))*T41,2)))} -> 0 | W41: =IF(V41-R41<0,0,V41-R41) -> 0 | X41: =ROUND((R41/(1+IF(D41="Yes",'Fiscal by Program'!$B$9,'Fiscal by Program'!$B$8))),2)+0.01 -> 17.02 | Y41: =Q41+W41 -> 22.84 | Z41: 4 | AA41: =T41/Z41 -> 0.25 | AB41: =INDEX('[9]Service List'!$K:$K,MATCH(A41,'[9]Service List'!$F:$F,0)) -> 283 | AC41: =INDEX('[5]Combined Bill Code List'!$P:$P,MATCH(A41,'[5]Combined Bill Code List'!$F:$F,0)) -> CFC | AD41: HCS | AE41: 1 | AF41: -0.06 | AG41: =ROUND(INDEX('All Trends'!D:D,MATCH($AD41,'All Trends'!$C:$C,0)),4) -> 0.9927 | AH41: =ROUND(INDEX('All Trends'!E:E,MATCH($AD41,'All Trends'!$C:$C,0)),4) -> 1.0091 | AI41: =ROUND(INDEX('All Trends'!F:F,MATCH($AD41,'All Trends'!$C:$C,0)),4) -> 1.0519 | AJ41: =ROUND(INDEX('All Trends'!G:G,MATCH($AD41,'All Trends'!$C:$C,0)),4) -> 1.0519 | AK41: =ROUND(INDEX('All Trends'!H:H,MATCH($AD41,'All Trends'!$C:$C,0)),4) -> 1.0519 | AL41: No | AM41: =IF(C41="Yes",ROUND(T41*N41*AI41,2),0) -> 34556 | AN41: =IF(C41="Yes",ROUND(T41*N41*AJ41,2),0) -> 34556 | AO41: =IF(C41="Yes",ROUND((W41*N41*AI41),2),0) -> 0 | AP41: =IF(C41="Yes",IF($AL41="No",ROUND(($AO41*($AY$2+$AF41)),2),ROUND($AO41,2)),0) -> 0 | AQ41: =IF(C41="Yes",ROUND((W41*N41*AJ41),2),0) -> 0 | AR41: =IF(C41="Yes",IF($AL41="No",ROUND(($AQ41*($AZ$2+$AF41)),2),ROUND($AQ41,2)),0) -> 0
A42: 2111XM0143 | B42: 2111XM0143 | C42: Yes | D42: No | E42: HCS | F42: In Home Respite | G42: =INDEX('[4]RT Description to Bill Matix'!$D:$D,MATCH(A42,'[4]RT Description to Bill Matix'!$M:$M,0)) -> In Home Respite | H42: HOURLY RESPITE LOC 1 IN-HOME | J42: {=INDEX('Rate Table Service Desc XWalk'!F:F,MATCH(1,(G42='Rate Table Service Desc XWalk'!B:B)*(E42='Rate Table Service Desc XWalk'!A:A),0))} -> 3-1-39 | K42: =INDEX('[5]Combined Bill Code List'!$A:$A,MATCH(A42,'[5]Combined Bill Code List'!$F:$F,0)) -> 1915(c) waiver | L42: =INDEX('[6]Rate History'!$P:$P,MATCH(A42,'[6]Rate History'!$F:$F,0)) -> 1 hour | M42: =INDEX('[7]PDF DB Service Pivot'!$C:$C,MATCH(B42,'[7]PDF DB Service Pivot'!$B:$B,0)) -> 92440.99 | N42: =IF(ISNUMBER(FIND("ISS",F42)),IF(I42="Yes",((M42/Q42)/6)*12,(M42/6)*12),IF(AND(I42="Yes",M42=O42),M42/Q42,M42)) -> 92440.99 | O42: =INDEX('[7]PDF DB Service Pivot'!$D:$D,MATCH(B42,'[7]PDF DB Service Pivot'!$B:$B,0)) -> 1794840.7 | P42: 45170 | Q42: 20 | R42: 11.77 | S42: =_xlfn.IFNA(R42/Q42,"") -> 0.5885 | T42: 1 | U42: =ROUND(V42/Z42,2) -> 0 | V42: {=_xlfn.IFS('Fiscal by Program'!$B$7<10.61,0,'Fiscal by Program'!$B$7>10.6,(ROUND('Fiscal by Program'!$B$7*(1+IF(D42="Yes",'Fiscal by Program'!$B$9,'Fiscal by Program'!$B$8))*T42,2)))} -> 0 | W42: =IF(V42-R42<0,0,V42-R42) -> 0 | X42: =ROUND((R42/(1+IF(D42="Yes",'Fiscal by Program'!$B$9,'Fiscal by Program'!$B$8))),2)+0.01 -> 10.64 | Y42: =Q42+W42 -> 20 | Z42: 4 | AA42: =T42/Z42 -> 0.25 | AB42: =INDEX('[9]Service List'!$K:$K,MATCH(A42,'[9]Service List'!$F:$F,0)) -> 394 | AC42: =INDEX('[5]Combined Bill Code List'!$P:$P,MATCH(A42,'[5]Combined Bill Code List'!$F:$F,0)) -> 0 | AD42: HCS | AE42: 1 | AF42: 0 | AG42: =ROUND(INDEX('All Trends'!D:D,MATCH($AD42,'All Trends'!$C:$C,0)),4) -> 0.9927 | AH42: =ROUND(INDEX('All Trends'!E:E,MATCH($AD42,'All Trends'!$C:$C,0)),4) -> 1.0091 | AI42: =ROUND(INDEX('All Trends'!F:F,MATCH($AD42,'All Trends'!$C:$C,0)),4) -> 1.0519 | AJ42: =ROUND(INDEX('All Trends'!G:G,MATCH($AD42,'All Trends'!$C:$C,0)),4) -> 1.0519 | AK42: =ROUND(INDEX('All Trends'!H:H,MATCH($AD42,'All Trends'!$C:$C,0)),4) -> 1.0519 | AL42: No | AM42: =IF(C42="Yes",ROUND(T42*N42*AI42,2),0) -> 97238.68 | AN42: =IF(C42="Yes",ROUND(T42*N42*AJ42,2),0) -> 97238.68 | AO42: =IF(C42="Yes",ROUND((W42*N42*AI42),2),0) -> 0 | AP42: =IF(C42="Yes",IF($AL42="No",ROUND(($AO42*($AY$2+$AF42)),2),ROUND($AO42,2)),0) -> 0 | AQ42: =IF(C42="Yes",ROUND((W42*N42*AJ42),2),0) -> 0 | AR42: =IF(C42="Yes",IF($AL42="No",ROUND(($AQ42*($AZ$2+$AF42)),2),ROUND($AQ42,2)),0) -> 0
A43: 2111XM0144 | B43: 2111XM0144 | C43: Yes | D43: No | E43: HCS | F43: In Home Respite | G43: =INDEX('[4]RT Description to Bill Matix'!$D:$D,MATCH(A43,'[4]RT Description to Bill Matix'!$M:$M,0)) -> In Home Respite | H43: HOURLY RESPITE LOC 8 IN-HOME | J43: {=INDEX('Rate Table Service Desc XWalk'!F:F,MATCH(1,(G43='Rate Table Service Desc XWalk'!B:B)*(E43='Rate Table Service Desc XWalk'!A:A),0))} -> 3-1-39 | K43: =INDEX('[5]Combined Bill Code List'!$A:$A,MATCH(A43,'[5]Combined Bill Code List'!$F:$F,0)) -> 1915(c) waiver | L43: =INDEX('[6]Rate History'!$P:$P,MATCH(A43,'[6]Rate History'!$F:$F,0)) -> 1 hour | M43: =INDEX('[7]PDF DB Service Pivot'!$C:$C,MATCH(B43,'[7]PDF DB Service Pivot'!$B:$B,0)) -> 12.75 | N43: =IF(ISNUMBER(FIND("ISS",F43)),IF(I43="Yes",((M43/Q43)/6)*12,(M43/6)*12),IF(AND(I43="Yes",M43=O43),M43/Q43,M43)) -> 12.75 | O43: =INDEX('[7]PDF DB Service Pivot'!$D:$D,MATCH(B43,'[7]PDF DB Service Pivot'!$B:$B,0)) -> 256.79 | P43: 45170 | Q43: 20 | R43: 11.77 | S43: =_xlfn.IFNA(R43/Q43,"") -> 0.5885 | T43: 1 | U43: =ROUND(V43/Z43,2) -> 0 | V43: {=_xlfn.IFS('Fiscal by Program'!$B$7<10.61,0,'Fiscal by Program'!$B$7>10.6,(ROUND('Fiscal by Program'!$B$7*(1+IF(D43="Yes",'Fiscal by Program'!$B$9,'Fiscal by Program'!$B$8))*T43,2)))} -> 0 | W43: =IF(V43-R43<0,0,V43-R43) -> 0 | X43: =ROUND((R43/(1+IF(D43="Yes",'Fiscal by Program'!$B$9,'Fiscal by Program'!$B$8))),2)+0.01 -> 10.64 | Y43: =Q43+W43 -> 20 | Z43: 4 | AA43: =T43/Z43 -> 0.25 | AB43: =INDEX('[9]Service List'!$K:$K,MATCH(A43,'[9]Service List'!$F:$F,0)) -> 395 | AC43: =INDEX('[5]Combined Bill Code List'!$P:$P,MATCH(A43,'[5]Combined Bill Code List'!$F:$F,0)) -> 0 | AD43: HCS | AE43: 1 | AF43: 0 | AG43: =ROUND(INDEX('All Trends'!D:D,MATCH($AD43,'All Trends'!$C:$C,0)),4) -> 0.9927 | AH43: =ROUND(INDEX('All Trends'!E:E,MATCH($AD43,'All Trends'!$C:$C,0)),4) -> 1.0091 | AI43: =ROUND(INDEX('All Trends'!F:F,MATCH($AD43,'All Trends'!$C:$C,0)),4) -> 1.0519 | AJ43: =ROUND(INDEX('All Trends'!G:G,MATCH($AD43,'All Trends'!$C:$C,0)),4) -> 1.0519 | AK43: =ROUND(INDEX('All Trends'!H:H,MATCH($AD43,'All Trends'!$C:$C,0)),4) -> 1.0519 | AL43: No | AM43: =IF(C43="Yes",ROUND(T43*N43*AI43,2),0) -> 13.41 | AN43: =IF(C43="Yes",ROUND(T43*N43*AJ43,2),0) -> 13.41 | AO43: =IF(C43="Yes",ROUND((W43*N43*AI43),2),0) -> 0 | AP43: =IF(C43="Yes",IF($AL43="No",ROUND(($AO43*($AY$2+$AF43)),2),ROUND($AO43,2)),0) -> 0 | AQ43: =IF(C43="Yes",ROUND((W43*N43*AJ43),2),0) -> 0 | AR43: =IF(C43="Yes",IF($AL43="No",ROUND(($AQ43*($AZ$2+$AF43)),2),ROUND($AQ43,2)),0) -> 0
A44: 2111XM0850 | B44: 2111XM0850 | C44: Yes | D44: No | E44: HCS | F44: Out of Home Respite | G44: =INDEX('[4]RT Description to Bill Matix'!$D:$D,MATCH(A44,'[4]RT Description to Bill Matix'!$M:$M,0)) -> Out-of-Home Respite | H44: HOURLY RESPITE LOC 1 IN A DH FACILITY | J44: {=INDEX('Rate Table Service Desc XWalk'!F:F,MATCH(1,(G44='Rate Table Service Desc XWalk'!B:B)*(E44='Rate Table Service Desc XWalk'!A:A),0))} -> 3-1-74 | K44: =INDEX('[5]Combined Bill Code List'!$A:$A,MATCH(A44,'[5]Combined Bill Code List'!$F:$F,0)) -> 1915(c) waiver | L44: =INDEX('[6]Rate History'!$P:$P,MATCH(A44,'[6]Rate History'!$F:$F,0)) -> 1 hour | M44: =INDEX('[7]PDF DB Service Pivot'!$C:$C,MATCH(B44,'[7]PDF DB Service Pivot'!$B:$B,0)) -> 56.75 | N44: =IF(ISNUMBER(FIND("ISS",F44)),IF(I44="Yes",((M44/Q44)/6)*12,(M44/6)*12),IF(AND(I44="Yes",M44=O44),M44/Q44,M44)) -> 56.75 | O44: =INDEX('[7]PDF DB Service Pivot'!$D:$D,MATCH(B44,'[7]PDF DB Service Pivot'!$B:$B,0)) -> 1142.95 | P44: 45170 | Q44: 18.89 | R44: 11.77 | S44: =_xlfn.IFNA(R44/Q44,"") -> 0.623081 | T44: 1 | U44: =ROUND(V44/Z44,2) -> 0 | V44: {=_xlfn.IFS('Fiscal by Program'!$B$7<10.61,0,'Fiscal by Program'!$B$7>10.6,(ROUND('Fiscal by Program'!$B$7*(1+IF(D44="Yes",'Fiscal by Program'!$B$9,'Fiscal by Program'!$B$8))*T44,2)))} -> 0 | W44: =IF(V44-R44<0,0,V44-R44) -> 0 | X44: =ROUND((R44/(1+IF(D44="Yes",'Fiscal by Program'!$B$9,'Fiscal by Program'!$B$8))),2)+0.01 -> 10.64 | Y44: =Q44+W44 -> 18.89 | Z44: 4 | AA44: =T44/Z44 -> 0.25 | AB44: =INDEX('[9]Service List'!$K:$K,MATCH(A44,'[9]Service List'!$F:$F,0)) -> 1245 | AC44: =INDEX('[5]Combined Bill Code List'!$P:$P,MATCH(A44,'[5]Combined Bill Code List'!$F:$F,0)) -> 0 | AD44: HCS | AE44: 1 | AF44: 0 | AG44: =ROUND(INDEX('All Trends'!D:D,MATCH($AD44,'All Trends'!$C:$C,0)),4) -> 0.9927 | AH44: =ROUND(INDEX('All Trends'!E:E,MATCH($AD44,'All Trends'!$C:$C,0)),4) -> 1.0091 | AI44: =ROUND(INDEX('All Trends'!F:F,MATCH($AD44,'All Trends'!$C:$C,0)),4) -> 1.0519 | AJ44: =ROUND(INDEX('All Trends'!G:G,MATCH($AD44,'All Trends'!$C:$C,0)),4) -> 1.0519 | AK44: =ROUND(INDEX('All Trends'!H:H,MATCH($AD44,'All Trends'!$C:$C,0)),4) -> 1.0519 | AL44: No | AM44: =IF(C44="Yes",ROUND(T44*N44*AI44,2),0) -> 59.7 | AN44: =IF(C44="Yes",ROUND(T44*N44*AJ44,2),0) -> 59.7 | AO44: =IF(C44="Yes",ROUND((W44*N44*AI44),2),0) -> 0 | AP44: =IF(C44="Yes",IF($AL44="No",ROUND(($AO44*($AY$2+$AF44)),2),ROUND($AO44,2)),0) -> 0 | AQ44: =IF(C44="Yes",ROUND((W44*N44*AJ44),2),0) -> 0 | AR44: =IF(C44="Yes",IF($AL44="No",ROUND(($AQ44*($AZ$2+$AF44)),2),ROUND($AQ44,2)),0) -> 0
A45: 2111XM0855 | B45: 2111XM0855 | C45: Yes | D45: No | E45: HCS | F45: In Home Respite | G45: =INDEX('[4]RT Description to Bill Matix'!$D:$D,MATCH(A45,'[4]RT Description to Bill Matix'!$M:$M,0)) -> In Home Respite | H45: HOURLY RESPITE LOC 1 WHERE SL OR RSS IS PROVIDED | J45: {=INDEX('Rate Table Service Desc XWalk'!F:F,MATCH(1,(G45='Rate Table Service Desc XWalk'!B:B)*(E45='Rate Table Service Desc XWalk'!A:A),0))} -> 3-1-39 | K45: =INDEX('[5]Combined Bill Code List'!$A:$A,MATCH(A45,'[5]Combined Bill Code List'!$F:$F,0)) -> 1915(c) waiver | L45: =INDEX('[6]Rate History'!$P:$P,MATCH(A45,'[6]Rate History'!$F:$F,0)) -> 1 hour | M45: =INDEX('[7]PDF DB Service Pivot'!$C:$C,MATCH(B45,'[7]PDF DB Service Pivot'!$B:$B,0)) -> 1007.75 | N45: =IF(ISNUMBER(FIND("ISS",F45)),IF(I45="Yes",((M45/Q45)/6)*12,(M45/6)*12),IF(AND(I45="Yes",M45=O45),M45/Q45,M45)) -> 1007.75 | O45: =INDEX('[7]PDF DB Service Pivot'!$D:$D,MATCH(B45,'[7]PDF DB Service Pivot'!$B:$B,0)) -> 19883.73 | P45: 45170 | Q45: 18.89 | R45: 11.77 | S45: =_xlfn.IFNA(R45/Q45,"") -> 0.623081 | T45: 1 | U45: =ROUND(V45/Z45,2) -> 0 | V45: {=_xlfn.IFS('Fiscal by Program'!$B$7<10.61,0,'Fiscal by Program'!$B$7>10.6,(ROUND('Fiscal by Program'!$B$7*(1+IF(D45="Yes",'Fiscal by Program'!$B$9,'Fiscal by Program'!$B$8))*T45,2)))} -> 0 | W45: =IF(V45-R45<0,0,V45-R45) -> 0 | X45: =ROUND((R45/(1+IF(D45="Yes",'Fiscal by Program'!$B$9,'Fiscal by Program'!$B$8))),2)+0.01 -> 10.64 | Y45: =Q45+W45 -> 18.89 | Z45: 4 | AA45: =T45/Z45 -> 0.25 | AB45: =INDEX('[9]Service List'!$K:$K,MATCH(A45,'[9]Service List'!$F:$F,0)) -> 1246 | AC45: =INDEX('[5]Combined Bill Code List'!$P:$P,MATCH(A45,'[5]Combined Bill Code List'!$F:$F,0)) -> 0 | AD45: HCS | AE45: 1 | AF45: 0 | AG45: =ROUND(INDEX('All Trends'!D:D,MATCH($AD45,'All Trends'!$C:$C,0)),4) -> 0.9927 | AH45: =ROUND(INDEX('All Trends'!E:E,MATCH($AD45,'All Trends'!$C:$C,0)),4) -> 1.0091 | AI45: =ROUND(INDEX('All Trends'!F:F,MATCH($AD45,'All Trends'!$C:$C,0)),4) -> 1.0519 | AJ45: =ROUND(INDEX('All Trends'!G:G,MATCH($AD45,'All Trends'!$C:$C,0)),4) -> 1.0519 | AK45: =ROUND(INDEX('All Trends'!H:H,MATCH($AD45,'All Trends'!$C:$C,0)),4) -> 1.0519 | AL45: No | AM45: =IF(C45="Yes",ROUND(T45*N45*AI45,2),0) -> 1060.05 | AN45: =IF(C45="Yes",ROUND(T45*N45*AJ45,2),0) -> 1060.05 | AO45: =IF(C45="Yes",ROUND((W45*N45*AI45),2),0) -> 0 | AP45: =IF(C45="Yes",IF($AL45="No",ROUND(($AO45*($AY$2+$AF45)),2),ROUND($AO45,2)),0) -> 0 | AQ45: =IF(C45="Yes",ROUND((W45*N45*AJ45),2),0) -> 0 | AR45: =IF(C45="Yes",IF($AL45="No",ROUND(($AQ45*($AZ$2+$AF45)),2),ROUND($AQ45,2)),0) -> 0
A46: 2111XM0860 | B46: 2111XM0860 | C46: Yes | D46: No | E46: HCS | F46: In Home Respite | G46: =INDEX('[4]RT Description to Bill Matix'!$D:$D,MATCH(A46,'[4]RT Description to Bill Matix'!$M:$M,0)) -> In Home Respite | H46: HOURLY RESPITE LOC 1 WHERE HH/CC IS PROVIDED | J46: {=INDEX('Rate Table Service Desc XWalk'!F:F,MATCH(1,(G46='Rate Table Service Desc XWalk'!B:B)*(E46='Rate Table Service Desc XWalk'!A:A),0))} -> 3-1-39 | K46: =INDEX('[5]Combined Bill Code List'!$A:$A,MATCH(A46,'[5]Combined Bill Code List'!$F:$F,0)) -> 1915(c) waiver | L46: =INDEX('[6]Rate History'!$P:$P,MATCH(A46,'[6]Rate History'!$F:$F,0)) -> 1 hour | M46: =INDEX('[7]PDF DB Service Pivot'!$C:$C,MATCH(B46,'[7]PDF DB Service Pivot'!$B:$B,0)) -> 3301.25 | N46: =IF(ISNUMBER(FIND("ISS",F46)),IF(I46="Yes",((M46/Q46)/6)*12,(M46/6)*12),IF(AND(I46="Yes",M46=O46),M46/Q46,M46)) -> 3301.25 | O46: =INDEX('[7]PDF DB Service Pivot'!$D:$D,MATCH(B46,'[7]PDF DB Service Pivot'!$B:$B,0)) -> 64418.94 | P46: 45170 | Q46: 18.89 | R46: 11.77 | S46: =_xlfn.IFNA(R46/Q46,"") -> 0.623081 | T46: 1 | U46: =ROUND(V46/Z46,2) -> 0 | V46: {=_xlfn.IFS('Fiscal by Program'!$B$7<10.61,0,'Fiscal by Program'!$B$7>10.6,(ROUND('Fiscal by Program'!$B$7*(1+IF(D46="Yes",'Fiscal by Program'!$B$9,'Fiscal by Program'!$B$8))*T46,2)))} -> 0 | W46: =IF(V46-R46<0,0,V46-R46) -> 0 | X46: =ROUND((R46/(1+IF(D46="Yes",'Fiscal by Program'!$B$9,'Fiscal by Program'!$B$8))),2)+0.01 -> 10.64 | Y46: =Q46+W46 -> 18.89 | Z46: 4 | AA46: =T46/Z46 -> 0.25 | AB46: =INDEX('[9]Service List'!$K:$K,MATCH(A46,'[9]Service List'!$F:$F,0)) -> 1247 | AC46: =INDEX('[5]Combined Bill Code List'!$P:$P,MATCH(A46,'[5]Combined Bill Code List'!$F:$F,0)) -> 0 | AD46: HCS | AE46: 1 | AF46: 0 | AG46: =ROUND(INDEX('All Trends'!D:D,MATCH($AD46,'All Trends'!$C:$C,0)),4) -> 0.9927 | AH46: =ROUND(INDEX('All Trends'!E:E,MATCH($AD46,'All Trends'!$C:$C,0)),4) -> 1.0091 | AI46: =ROUND(INDEX('All Trends'!F:F,MATCH($AD46,'All Trends'!$C:$C,0)),4) -> 1.0519 | AJ46: =ROUND(INDEX('All Trends'!G:G,MATCH($AD46,'All Trends'!$C:$C,0)),4) -> 1.0519 | AK46: =ROUND(INDEX('All Trends'!H:H,MATCH($AD46,'All Trends'!$C:$C,0)),4) -> 1.0519 | AL46: No | AM46: =IF(C46="Yes",ROUND(T46*N46*AI46,2),0) -> 3472.58 | AN46: =IF(C46="Yes",ROUND(T46*N46*AJ46,2),0) -> 3472.58 | AO46: =IF(C46="Yes",ROUND((W46*N46*AI46),2),0) -> 0 | AP46: =IF(C46="Yes",IF($AL46="No",ROUND(($AO46*($AY$2+$AF46)),2),ROUND($AO46,2)),0) -> 0 | AQ46: =IF(C46="Yes",ROUND((W46*N46*AJ46),2),0) -> 0 | AR46: =IF(C46="Yes",IF($AL46="No",ROUND(($AQ46*($AZ$2+$AF46)),2),ROUND($AQ46,2)),0) -> 0
A47: 2111XM0865 | B47: 2111XM0865 | C47: Yes | D47: No | E47: HCS | F47: Out of Home Respite | G47: =INDEX('[4]RT Description to Bill Matix'!$D:$D,MATCH(A47,'[4]RT Description to Bill Matix'!$M:$M,0)) -> Out-of-Home Respite | H47: HOURLY RESPITE LOC 1 IN A SETTING NOT LISTED | J47: {=INDEX('Rate Table Service Desc XWalk'!F:F,MATCH(1,(G47='Rate Table Service Desc XWalk'!B:B)*(E47='Rate Table Service Desc XWalk'!A:A),0))} -> 3-1-74 | K47: =INDEX('[5]Combined Bill Code List'!$A:$A,MATCH(A47,'[5]Combined Bill Code List'!$F:$F,0)) -> 1915(c) waiver | L47: =INDEX('[6]Rate History'!$P:$P,MATCH(A47,'[6]Rate History'!$F:$F,0)) -> 1 hour | M47: =INDEX('[7]PDF DB Service Pivot'!$C:$C,MATCH(B47,'[7]PDF DB Service Pivot'!$B:$B,0)) -> 13075.5 | N47: =IF(ISNUMBER(FIND("ISS",F47)),IF(I47="Yes",((M47/Q47)/6)*12,(M47/6)*12),IF(AND(I47="Yes",M47=O47),M47/Q47,M47)) -> 13075.5 | O47: =INDEX('[7]PDF DB Service Pivot'!$D:$D,MATCH(B47,'[7]PDF DB Service Pivot'!$B:$B,0)) -> 258407.19 | P47: 45170 | Q47: 18.89 | R47: 11.77 | S47: =_xlfn.IFNA(R47/Q47,"") -> 0.623081 | T47: 1 | U47: =ROUND(V47/Z47,2) -> 0 | V47: {=_xlfn.IFS('Fiscal by Program'!$B$7<10.61,0,'Fiscal by Program'!$B$7>10.6,(ROUND('Fiscal by Program'!$B$7*(1+IF(D47="Yes",'Fiscal by Program'!$B$9,'Fiscal by Program'!$B$8))*T47,2)))} -> 0 | W47: =IF(V47-R47<0,0,V47-R47) -> 0 | X47: =ROUND((R47/(1+IF(D47="Yes",'Fiscal by Program'!$B$9,'Fiscal by Program'!$B$8))),2)+0.01 -> 10.64 | Y47: =Q47+W47 -> 18.89 | Z47: 4 | AA47: =T47/Z47 -> 0.25 | AB47: =INDEX('[9]Service List'!$K:$K,MATCH(A47,'[9]Service List'!$F:$F,0)) -> 1248 | AC47: =INDEX('[5]Combined Bill Code List'!$P:$P,MATCH(A47,'[5]Combined Bill Code List'!$F:$F,0)) -> 0 | AD47: HCS | AE47: 1 | AF47: 0 | AG47: =ROUND(INDEX('All Trends'!D:D,MATCH($AD47,'All Trends'!$C:$C,0)),4) -> 0.9927 | AH47: =ROUND(INDEX('All Trends'!E:E,MATCH($AD47,'All Trends'!$C:$C,0)),4) -> 1.0091 | AI47: =ROUND(INDEX('All Trends'!F:F,MATCH($AD47,'All Trends'!$C:$C,0)),4) -> 1.0519 | AJ47: =ROUND(INDEX('All Trends'!G:G,MATCH($AD47,'All Trends'!$C:$C,0)),4) -> 1.0519 | AK47: =ROUND(INDEX('All Trends'!H:H,MATCH($AD47,'All Trends'!$C:$C,0)),4) -> 1.0519 | AL47: No | AM47: =IF(C47="Yes",ROUND(T47*N47*AI47,2),0) -> 13754.12 | AN47: =IF(C47="Yes",ROUND(T47*N47*AJ47,2),0) -> 13754.12 | AO47: =IF(C47="Yes",ROUND((W47*N47*AI47),2),0) -> 0 | AP47: =IF(C47="Yes",IF($AL47="No",ROUND(($AO47*($AY$2+$AF47)),2),ROUND($AO47,2)),0) -> 0 | AQ47: =IF(C47="Yes",ROUND((W47*N47*AJ47),2),0) -> 0 | AR47: =IF(C47="Yes",IF($AL47="No",ROUND(($AQ47*($AZ$2+$AF47)),2),ROUND($AQ47,2)),0) -> 0
A48: 2111XM0867 | B48: 2111XM0867 | C48: Yes | D48: No | E48: HCS | F48: Out of Home Respite | G48: =INDEX('[4]RT Description to Bill Matix'!$D:$D,MATCH(A48,'[4]RT Description to Bill Matix'!$M:$M,0)) -> Out-of-Home Respite | H48: HOURLY RESPITE LOC 1 IN A CAMP | J48: {=INDEX('Rate Table Service Desc XWalk'!F:F,MATCH(1,(G48='Rate Table Service Desc XWalk'!B:B)*(E48='Rate Table Service Desc XWalk'!A:A),0))} -> 3-1-74 | K48: =INDEX('[5]Combined Bill Code List'!$A:$A,MATCH(A48,'[5]Combined Bill Code List'!$F:$F,0)) -> 1915(c) waiver | L48: =INDEX('[6]Rate History'!$P:$P,MATCH(A48,'[6]Rate History'!$F:$F,0)) -> 1 hour | M48: =INDEX('[7]PDF DB Service Pivot'!$C:$C,MATCH(B48,'[7]PDF DB Service Pivot'!$B:$B,0)) -> 296.75 | N48: =IF(ISNUMBER(FIND("ISS",F48)),IF(I48="Yes",((M48/Q48)/6)*12,(M48/6)*12),IF(AND(I48="Yes",M48=O48),M48/Q48,M48)) -> 296.75 | O48: =INDEX('[7]PDF DB Service Pivot'!$D:$D,MATCH(B48,'[7]PDF DB Service Pivot'!$B:$B,0)) -> 5753.73 | P48: 45170 | Q48: 18.89 | R48: 11.77 | S48: =_xlfn.IFNA(R48/Q48,"") -> 0.623081 | T48: 1 | U48: =ROUND(V48/Z48,2) -> 0 | V48: {=_xlfn.IFS('Fiscal by Program'!$B$7<10.61,0,'Fiscal by Program'!$B$7>10.6,(ROUND('Fiscal by Program'!$B$7*(1+IF(D48="Yes",'Fiscal by Program'!$B$9,'Fiscal by Program'!$B$8))*T48,2)))} -> 0 | W48: =IF(V48-R48<0,0,V48-R48) -> 0 | X48: =ROUND((R48/(1+IF(D48="Yes",'Fiscal by Program'!$B$9,'Fiscal by Program'!$B$8))),2)+0.01 -> 10.64 | Y48: =Q48+W48 -> 18.89 | Z48: 4 | AA48: =T48/Z48 -> 0.25 | AB48: =INDEX('[9]Service List'!$K:$K,MATCH(A48,'[9]Service List'!$F:$F,0)) -> 1249 | AC48: =INDEX('[5]Combined Bill Code List'!$P:$P,MATCH(A48,'[5]Combined Bill Code List'!$F:$F,0)) -> 0 | AD48: HCS | AE48: 1 | AF48: 0 | AG48: =ROUND(INDEX('All Trends'!D:D,MATCH($AD48,'All Trends'!$C:$C,0)),4) -> 0.9927 | AH48: =ROUND(INDEX('All Trends'!E:E,MATCH($AD48,'All Trends'!$C:$C,0)),4) -> 1.0091 | AI48: =ROUND(INDEX('All Trends'!F:F,MATCH($AD48,'All Trends'!$C:$C,0)),4) -> 1.0519 | AJ48: =ROUND(INDEX('All Trends'!G:G,MATCH($AD48,'All Trends'!$C:$C,0)),4) -> 1.0519 | AK48: =ROUND(INDEX('All Trends'!H:H,MATCH($AD48,'All Trends'!$C:$C,0)),4) -> 1.0519 | AL48: No | AM48: =IF(C48="Yes",ROUND(T48*N48*AI48,2),0) -> 312.15 | AN48: =IF(C48="Yes",ROUND(T48*N48*AJ48,2),0) -> 312.15 | AO48: =IF(C48="Yes",ROUND((W48*N48*AI48),2),0) -> 0 | AP48: =IF(C48="Yes",IF($AL48="No",ROUND(($AO48*($AY$2+$AF48)),2),ROUND($AO48,2)),0) -> 0 | AQ48: =IF(C48="Yes",ROUND((W48*N48*AJ48),2),0) -> 0 | AR48: =IF(C48="Yes",IF($AL48="No",ROUND(($AQ48*($AZ$2+$AF48)),2),ROUND($AQ48,2)),0) -> 0
A49: 2111XM0869 | B49: 2111XM0869 | C49: Yes | D49: No | E49: HCS | F49: Out of Home Respite | G49: =INDEX('[4]RT Description to Bill Matix'!$D:$D,MATCH(A49,'[4]RT Description to Bill Matix'!$M:$M,0)) -> Out-of-Home Respite | H49: HOURLY RESPITE LOC 1 IN A RESPITE FACILITY | J49: {=INDEX('Rate Table Service Desc XWalk'!F:F,MATCH(1,(G49='Rate Table Service Desc XWalk'!B:B)*(E49='Rate Table Service Desc XWalk'!A:A),0))} -> 3-1-74 | K49: =INDEX('[5]Combined Bill Code List'!$A:$A,MATCH(A49,'[5]Combined Bill Code List'!$F:$F,0)) -> 1915(c) waiver | L49: =INDEX('[6]Rate History'!$P:$P,MATCH(A49,'[6]Rate History'!$F:$F,0)) -> 1 hour | M49: =INDEX('[7]PDF DB Service Pivot'!$C:$C,MATCH(B49,'[7]PDF DB Service Pivot'!$B:$B,0)) -> 889.75 | N49: =IF(ISNUMBER(FIND("ISS",F49)),IF(I49="Yes",((M49/Q49)/6)*12,(M49/6)*12),IF(AND(I49="Yes",M49=O49),M49/Q49,M49)) -> 889.75 | O49: =INDEX('[7]PDF DB Service Pivot'!$D:$D,MATCH(B49,'[7]PDF DB Service Pivot'!$B:$B,0)) -> 17549.64 | P49: 45170 | Q49: 18.89 | R49: 11.77 | S49: =_xlfn.IFNA(R49/Q49,"") -> 0.623081 | T49: 1 | U49: =ROUND(V49/Z49,2) -> 0 | V49: {=_xlfn.IFS('Fiscal by Program'!$B$7<10.61,0,'Fiscal by Program'!$B$7>10.6,(ROUND('Fiscal by Program'!$B$7*(1+IF(D49="Yes",'Fiscal by Program'!$B$9,'Fiscal by Program'!$B$8))*T49,2)))} -> 0 | W49: =IF(V49-R49<0,0,V49-R49) -> 0 | X49: =ROUND((R49/(1+IF(D49="Yes",'Fiscal by Program'!$B$9,'Fiscal by Program'!$B$8))),2)+0.01 -> 10.64 | Y49: =Q49+W49 -> 18.89 | Z49: 4 | AA49: =T49/Z49 -> 0.25 | AB49: =INDEX('[9]Service List'!$K:$K,MATCH(A49,'[9]Service List'!$F:$F,0)) -> 1250 | AC49: =INDEX('[5]Combined Bill Code List'!$P:$P,MATCH(A49,'[5]Combined Bill Code List'!$F:$F,0)) -> 0 | AD49: HCS | AE49: 1 | AF49: 0 | AG49: =ROUND(INDEX('All Trends'!D:D,MATCH($AD49,'All Trends'!$C:$C,0)),4) -> 0.9927 | AH49: =ROUND(INDEX('All Trends'!E:E,MATCH($AD49,'All Trends'!$C:$C,0)),4) -> 1.0091 | AI49: =ROUND(INDEX('All Trends'!F:F,MATCH($AD49,'All Trends'!$C:$C,0)),4) -> 1.0519 | AJ49: =ROUND(INDEX('All Trends'!G:G,MATCH($AD49,'All Trends'!$C:$C,0)),4) -> 1.0519 | AK49: =ROUND(INDEX('All Trends'!H:H,MATCH($AD49,'All Trends'!$C:$C,0)),4) -> 1.0519 | AL49: No | AM49: =IF(C49="Yes",ROUND(T49*N49*AI49,2),0) -> 935.93 | AN49: =IF(C49="Yes",ROUND(T49*N49*AJ49,2),0) -> 935.93 | AO49: =IF(C49="Yes",ROUND((W49*N49*AI49),2),0) -> 0 | AP49: =IF(C49="Yes",IF($AL49="No",ROUND(($AO49*($AY$2+$AF49)),2),ROUND($AO49,2)),0) -> 0 | AQ49: =IF(C49="Yes",ROUND((W49*N49*AJ49),2),0) -> 0 | AR49: =IF(C49="Yes",IF($AL49="No",ROUND(($AQ49*($AZ$2+$AF49)),2),ROUND($AQ49,2)),0) -> 0
A50: 2111XVM0145 | B50: 2111XVM0145 | C50: Yes | D50: No | E50: HCS | F50: In Home Respite | G50: =INDEX('[4]RT Description to Bill Matix'!$D:$D,MATCH(A50,'[4]RT Description to Bill Matix'!$M:$M,0)) -> CDS In Home Respite | H50: HOURLY RESPITE LOC 1 IN-HOME (CDS) | I50: Yes | J50: {=INDEX('Rate Table Service Desc XWalk'!F:F,MATCH(1,(G50='Rate Table Service Desc XWalk'!B:B)*(E50='Rate Table Service Desc XWalk'!A:A),0))} -> 3-5-124 | K50: =INDEX('[5]Combined Bill Code List'!$A:$A,MATCH(A50,'[5]Combined Bill Code List'!$F:$F,0)) -> 1915(c) waiver | L50: =INDEX('[6]Rate History'!$P:$P,MATCH(A50,'[6]Rate History'!$F:$F,0)) -> 1 hour | M50: =INDEX('[7]PDF DB Service Pivot'!$C:$C,MATCH(B50,'[7]PDF DB Service Pivot'!$B:$B,0)) -> 2904386.9 | N50: =IF(ISNUMBER(FIND("ISS",F50)),IF(I50="Yes",((M50/Q50)/6)*12,(M50/6)*12),IF(AND(I50="Yes",M50=O50),M50/Q50,M50)) -> 152862.47 | O50: =INDEX('[7]PDF DB Service Pivot'!$D:$D,MATCH(B50,'[7]PDF DB Service Pivot'!$B:$B,0)) -> 2904386.9 | P50: 45170 | Q50: 19 | R50: 11.77 | S50: =_xlfn.IFNA(R50/Q50,"") -> 0.61947368 | T50: 1 | U50: =ROUND(V50/Z50,2) -> 0 | V50: {=_xlfn.IFS('Fiscal by Program'!$B$7<10.61,0,'Fiscal by Program'!$B$7>10.6,(ROUND('Fiscal by Program'!$B$7*(1+IF(D50="Yes",'Fiscal by Program'!$B$9,'Fiscal by Program'!$B$8))*T50,2)))} -> 0 | W50: =IF(V50-R50<0,0,V50-R50) -> 0 | X50: =ROUND((R50/(1+IF(D50="Yes",'Fiscal by Program'!$B$9,'Fiscal by Program'!$B$8))),2)+0.01 -> 10.64 | Y50: =Q50+W50 -> 19 | Z50: 4 | AA50: =T50/Z50 -> 0.25 | AB50: =INDEX('[9]Service List'!$K:$K,MATCH(A50,'[9]Service List'!$F:$F,0)) -> 392 | AC50: =INDEX('[5]Combined Bill Code List'!$P:$P,MATCH(A50,'[5]Combined Bill Code List'!$F:$F,0)) -> 0 | AD50: HCS | AE50: 1 | AF50: 0 | AG50: =ROUND(INDEX('All Trends'!D:D,MATCH($AD50,'All Trends'!$C:$C,0)),4) -> 0.9927 | AH50: =ROUND(INDEX('All Trends'!E:E,MATCH($AD50,'All Trends'!$C:$C,0)),4) -> 1.0091 | AI50: =ROUND(INDEX('All Trends'!F:F,MATCH($AD50,'All Trends'!$C:$C,0)),4) -> 1.0519 | AJ50: =ROUND(INDEX('All Trends'!G:G,MATCH($AD50,'All Trends'!$C:$C,0)),4) -> 1.0519 | AK50: =ROUND(INDEX('All Trends'!H:H,MATCH($AD50,'All Trends'!$C:$C,0)),4) -> 1.0519 | AL50: No | AM50: =IF(C50="Yes",ROUND(T50*N50*AI50,2),0) -> 160796.03 | AN50: =IF(C50="Yes",ROUND(T50*N50*AJ50,2),0) -> 160796.03 | AO50: =IF(C50="Yes",ROUND((W50*N50*AI50),2),0) -> 0 | AP50: =IF(C50="Yes",IF($AL50="No",ROUND(($AO50*($AY$2+$AF50)),2),ROUND($AO50,2)),0) -> 0 | AQ50: =IF(C50="Yes",ROUND((W50*N50*AJ50),2),0) -> 0 | AR50: =IF(C50="Yes",IF($AL50="No",ROUND(($AQ50*($AZ$2+$AF50)),2),ROUND($AQ50,2)),0) -> 0
A51: 2111XVM0146 | B51: 2111XVM0146 | C51: Yes | D51: No | E51: HCS | F51: In Home Respite | G51: =INDEX('[4]RT Description to Bill Matix'!$D:$D,MATCH(A51,'[4]RT Description to Bill Matix'!$M:$M,0)) -> CDS In Home Respite | H51: HOURLY RESPITE LOC 8 IN-HOME (CDS) | I51: Yes | J51: {=INDEX('Rate Table Service Desc XWalk'!F:F,MATCH(1,(G51='Rate Table Service Desc XWalk'!B:B)*(E51='Rate Table Service Desc XWalk'!A:A),0))} -> 3-5-124 | K51: =INDEX('[5]Combined Bill Code List'!$A:$A,MATCH(A51,'[5]Combined Bill Code List'!$F:$F,0)) -> 1915(c) waiver | L51: =INDEX('[6]Rate History'!$P:$P,MATCH(A51,'[6]Rate History'!$F:$F,0)) -> 1 hour | M51: =INDEX('[7]PDF DB Service Pivot'!$C:$C,MATCH(B51,'[7]PDF DB Service Pivot'!$B:$B,0)) -> 15184.8 | N51: =IF(ISNUMBER(FIND("ISS",F51)),IF(I51="Yes",((M51/Q51)/6)*12,(M51/6)*12),IF(AND(I51="Yes",M51=O51),M51/Q51,M51)) -> 799.2 | O51: =INDEX('[7]PDF DB Service Pivot'!$D:$D,MATCH(B51,'[7]PDF DB Service Pivot'!$B:$B,0)) -> 15184.8 | P51: 45170 | Q51: 19 | R51: 11.77 | S51: =_xlfn.IFNA(R51/Q51,"") -> 0.61947368 | T51: 1 | U51: =ROUND(V51/Z51,2) -> 0 | V51: {=_xlfn.IFS('Fiscal by Program'!$B$7<10.61,0,'Fiscal by Program'!$B$7>10.6,(ROUND('Fiscal by Program'!$B$7*(1+IF(D51="Yes",'Fiscal by Program'!$B$9,'Fiscal by Program'!$B$8))*T51,2)))} -> 0 | W51: =IF(V51-R51<0,0,V51-R51) -> 0 | X51: =ROUND((R51/(1+IF(D51="Yes",'Fiscal by Program'!$B$9,'Fiscal by Program'!$B$8))),2)+0.01 -> 10.64 | Y51: =Q51+W51 -> 19 | Z51: 4 | AA51: =T51/Z51 -> 0.25 | AB51: =INDEX('[9]Service List'!$K:$K,MATCH(A51,'[9]Service List'!$F:$F,0)) -> 393 | AC51: =INDEX('[5]Combined Bill Code List'!$P:$P,MATCH(A51,'[5]Combined Bill Code List'!$F:$F,0)) -> 0 | AD51: HCS | AE51: 1 | AF51: 0 | AG51: =ROUND(INDEX('All Trends'!D:D,MATCH($AD51,'All Trends'!$C:$C,0)),4) -> 0.9927 | AH51: =ROUND(INDEX('All Trends'!E:E,MATCH($AD51,'All Trends'!$C:$C,0)),4) -> 1.0091 | AI51: =ROUND(INDEX('All Trends'!F:F,MATCH($AD51,'All Trends'!$C:$C,0)),4) -> 1.0519 | AJ51: =ROUND(INDEX('All Trends'!G:G,MATCH($AD51,'All Trends'!$C:$C,0)),4) -> 1.0519 | AK51: =ROUND(INDEX('All Trends'!H:H,MATCH($AD51,'All Trends'!$C:$C,0)),4) -> 1.0519 | AL51: No | AM51: =IF(C51="Yes",ROUND(T51*N51*AI51,2),0) -> 840.68 | AN51: =IF(C51="Yes",ROUND(T51*N51*AJ51,2),0) -> 840.68 | AO51: =IF(C51="Yes",ROUND((W51*N51*AI51),2),0) -> 0 | AP51: =IF(C51="Yes",IF($AL51="No",ROUND(($AO51*($AY$2+$AF51)),2),ROUND($AO51,2)),0) -> 0 | AQ51: =IF(C51="Yes",ROUND((W51*N51*AJ51),2),0) -> 0 | AR51: =IF(C51="Yes",IF($AL51="No",ROUND(($AQ51*($AZ$2+$AF51)),2),ROUND($AQ51,2)),0) -> 0
A52: 2111XVM0873 | B52: 2111XVM0873 | C52: Yes | D52: No | E52: HCS | F52: In Home Respite | G52: =INDEX('[4]RT Description to Bill Matix'!$D:$D,MATCH(A52,'[4]RT Description to Bill Matix'!$M:$M,0)) -> CDS In Home Respite | H52: HOURLY RESPITE LOC 1 WHERE SL OR RSS IS PROVIDED (CDS) | I52: Yes | J52: {=INDEX('Rate Table Service Desc XWalk'!F:F,MATCH(1,(G52='Rate Table Service Desc XWalk'!B:B)*(E52='Rate Table Service Desc XWalk'!A:A),0))} -> 3-5-124 | K52: =INDEX('[5]Combined Bill Code List'!$A:$A,MATCH(A52,'[5]Combined Bill Code List'!$F:$F,0)) -> 1915(c) waiver | L52: =INDEX('[6]Rate History'!$P:$P,MATCH(A52,'[6]Rate History'!$F:$F,0)) -> 1 hour | M52: =INDEX('[7]PDF DB Service Pivot'!$C:$C,MATCH(B52,'[7]PDF DB Service Pivot'!$B:$B,0)) -> 4470.52 | N52: =IF(ISNUMBER(FIND("ISS",F52)),IF(I52="Yes",((M52/Q52)/6)*12,(M52/6)*12),IF(AND(I52="Yes",M52=O52),M52/Q52,M52)) -> 249.88932 | O52: =INDEX('[7]PDF DB Service Pivot'!$D:$D,MATCH(B52,'[7]PDF DB Service Pivot'!$B:$B,0)) -> 4470.52 | P52: 45170 | Q52: 17.89 | R52: 11.77 | S52: =_xlfn.IFNA(R52/Q52,"") -> 0.65790945 | T52: 1 | U52: =ROUND(V52/Z52,2) -> 0 | V52: {=_xlfn.IFS('Fiscal by Program'!$B$7<10.61,0,'Fiscal by Program'!$B$7>10.6,(ROUND('Fiscal by Program'!$B$7*(1+IF(D52="Yes",'Fiscal by Program'!$B$9,'Fiscal by Program'!$B$8))*T52,2)))} -> 0 | W52: =IF(V52-R52<0,0,V52-R52) -> 0 | X52: =ROUND((R52/(1+IF(D52="Yes",'Fiscal by Program'!$B$9,'Fiscal by Program'!$B$8))),2)+0.01 -> 10.64 | Y52: =Q52+W52 -> 17.89 | Z52: 4 | AA52: =T52/Z52 -> 0.25 | AB52: =INDEX('[9]Service List'!$K:$K,MATCH(A52,'[9]Service List'!$F:$F,0)) -> 1258 | AC52: =INDEX('[5]Combined Bill Code List'!$P:$P,MATCH(A52,'[5]Combined Bill Code List'!$F:$F,0)) -> 0 | AD52: HCS | AE52: 1 | AF52: 0 | AG52: =ROUND(INDEX('All Trends'!D:D,MATCH($AD52,'All Trends'!$C:$C,0)),4) -> 0.9927 | AH52: =ROUND(INDEX('All Trends'!E:E,MATCH($AD52,'All Trends'!$C:$C,0)),4) -> 1.0091 | AI52: =ROUND(INDEX('All Trends'!F:F,MATCH($AD52,'All Trends'!$C:$C,0)),4) -> 1.0519 | AJ52: =ROUND(INDEX('All Trends'!G:G,MATCH($AD52,'All Trends'!$C:$C,0)),4) -> 1.0519 | AK52: =ROUND(INDEX('All Trends'!H:H,MATCH($AD52,'All Trends'!$C:$C,0)),4) -> 1.0519 | AL52: No | AM52: =IF(C52="Yes",ROUND(T52*N52*AI52,2),0) -> 262.86 | AN52: =IF(C52="Yes",ROUND(T52*N52*AJ52,2),0) -> 262.86 | AO52: =IF(C52="Yes",ROUND((W52*N52*AI52),2),0) -> 0 | AP52: =IF(C52="Yes",IF($AL52="No",ROUND(($AO52*($AY$2+$AF52)),2),ROUND($AO52,2)),0) -> 0 | AQ52: =IF(C52="Yes",ROUND((W52*N52*AJ52),2),0) -> 0 | AR52: =IF(C52="Yes",IF($AL52="No",ROUND(($AQ52*($AZ$2+$AF52)),2),ROUND($AQ52,2)),0) -> 0
A53: 2111XVM0877 | B53: 2111XVM0877 | C53: Yes | D53: No | E53: HCS | F53: Out of Home Respite | G53: =INDEX('[4]RT Description to Bill Matix'!$D:$D,MATCH(A53,'[4]RT Description to Bill Matix'!$M:$M,0)) -> CDS Out-of-Home Respite | H53: HOURLY RESPITE LOC 1 IN A SETTING NOT LISTED (CDS) | I53: Yes | J53: {=INDEX('Rate Table Service Desc XWalk'!F:F,MATCH(1,(G53='Rate Table Service Desc XWalk'!B:B)*(E53='Rate Table Service Desc XWalk'!A:A),0))} -> 3-5-139 | K53: =INDEX('[5]Combined Bill Code List'!$A:$A,MATCH(A53,'[5]Combined Bill Code List'!$F:$F,0)) -> 1915(c) waiver | L53: =INDEX('[6]Rate History'!$P:$P,MATCH(A53,'[6]Rate History'!$F:$F,0)) -> 1 hour | M53: =INDEX('[7]PDF DB Service Pivot'!$C:$C,MATCH(B53,'[7]PDF DB Service Pivot'!$B:$B,0)) -> 47504.01 | N53: =IF(ISNUMBER(FIND("ISS",F53)),IF(I53="Yes",((M53/Q53)/6)*12,(M53/6)*12),IF(AND(I53="Yes",M53=O53),M53/Q53,M53)) -> 2655.3387 | O53: =INDEX('[7]PDF DB Service Pivot'!$D:$D,MATCH(B53,'[7]PDF DB Service Pivot'!$B:$B,0)) -> 47504.01 | P53: 45170 | Q53: 17.89 | R53: 11.77 | S53: =_xlfn.IFNA(R53/Q53,"") -> 0.65790945 | T53: 1 | U53: =ROUND(V53/Z53,2) -> 0 | V53: {=_xlfn.IFS('Fiscal by Program'!$B$7<10.61,0,'Fiscal by Program'!$B$7>10.6,(ROUND('Fiscal by Program'!$B$7*(1+IF(D53="Yes",'Fiscal by Program'!$B$9,'Fiscal by Program'!$B$8))*T53,2)))} -> 0 | W53: =IF(V53-R53<0,0,V53-R53) -> 0 | X53: =ROUND((R53/(1+IF(D53="Yes",'Fiscal by Program'!$B$9,'Fiscal by Program'!$B$8))),2)+0.01 -> 10.64 | Y53: =Q53+W53 -> 17.89 | Z53: 4 | AA53: =T53/Z53 -> 0.25 | AB53: =INDEX('[9]Service List'!$K:$K,MATCH(A53,'[9]Service List'!$F:$F,0)) -> 1260 | AC53: =INDEX('[5]Combined Bill Code List'!$P:$P,MATCH(A53,'[5]Combined Bill Code List'!$F:$F,0)) -> 0 | AD53: HCS | AE53: 1 | AF53: 0 | AG53: =ROUND(INDEX('All Trends'!D:D,MATCH($AD53,'All Trends'!$C:$C,0)),4) -> 0.9927 | AH53: =ROUND(INDEX('All Trends'!E:E,MATCH($AD53,'All Trends'!$C:$C,0)),4) -> 1.0091 | AI53: =ROUND(INDEX('All Trends'!F:F,MATCH($AD53,'All Trends'!$C:$C,0)),4) -> 1.0519 | AJ53: =ROUND(INDEX('All Trends'!G:G,MATCH($AD53,'All Trends'!$C:$C,0)),4) -> 1.0519 | AK53: =ROUND(INDEX('All Trends'!H:H,MATCH($AD53,'All Trends'!$C:$C,0)),4) -> 1.0519 | AL53: No | AM53: =IF(C53="Yes",ROUND(T53*N53*AI53,2),0) -> 2793.15 | AN53: =IF(C53="Yes",ROUND(T53*N53*AJ53,2),0) -> 2793.15 | AO53: =IF(C53="Yes",ROUND((W53*N53*AI53),2),0) -> 0 | AP53: =IF(C53="Yes",IF($AL53="No",ROUND(($AO53*($AY$2+$AF53)),2),ROUND($AO53,2)),0) -> 0 | AQ53: =IF(C53="Yes",ROUND((W53*N53*AJ53),2),0) -> 0 | AR53: =IF(C53="Yes",IF($AL53="No",ROUND(($AQ53*($AZ$2+$AF53)),2),ROUND($AQ53,2)),0) -> 0
A54: 2111XVM1091 | B54: 2111XVM1091 | C54: Yes | D54: No | E54: HCS | F54: Out of Home Respite | G54: =INDEX('[4]RT Description to Bill Matix'!$D:$D,MATCH(A54,'[4]RT Description to Bill Matix'!$M:$M,0)) -> CDS Out-of-Home Respite | H54: HOURLY RESPITE LOC 1 IN-CAMP (CDS) | I54: Yes | J54: {=INDEX('Rate Table Service Desc XWalk'!F:F,MATCH(1,(G54='Rate Table Service Desc XWalk'!B:B)*(E54='Rate Table Service Desc XWalk'!A:A),0))} -> 3-5-139 | K54: =INDEX('[5]Combined Bill Code List'!$A:$A,MATCH(A54,'[5]Combined Bill Code List'!$F:$F,0)) -> 1915(c) waiver | L54: =INDEX('[6]Rate History'!$P:$P,MATCH(A54,'[6]Rate History'!$F:$F,0)) -> 1 hour | M54: =INDEX('[7]PDF DB Service Pivot'!$C:$C,MATCH(B54,'[7]PDF DB Service Pivot'!$B:$B,0)) -> 16810.83 | N54: =IF(ISNUMBER(FIND("ISS",F54)),IF(I54="Yes",((M54/Q54)/6)*12,(M54/6)*12),IF(AND(I54="Yes",M54=O54),M54/Q54,M54)) -> 939.67747 | O54: =INDEX('[7]PDF DB Service Pivot'!$D:$D,MATCH(B54,'[7]PDF DB Service Pivot'!$B:$B,0)) -> 16810.83 | P54: 45170 | Q54: 17.89 | R54: 11.77 | S54: =_xlfn.IFNA(R54/Q54,"") -> 0.65790945 | T54: 1 | U54: =ROUND(V54/Z54,2) -> 0 | V54: {=_xlfn.IFS('Fiscal by Program'!$B$7<10.61,0,'Fiscal by Program'!$B$7>10.6,(ROUND('Fiscal by Program'!$B$7*(1+IF(D54="Yes",'Fiscal by Program'!$B$9,'Fiscal by Program'!$B$8))*T54,2)))} -> 0 | W54: =IF(V54-R54<0,0,V54-R54) -> 0 | X54: =ROUND((R54/(1+IF(D54="Yes",'Fiscal by Program'!$B$9,'Fiscal by Program'!$B$8))),2)+0.01 -> 10.64 | Y54: =Q54+W54 -> 17.89 | Z54: 4 | AA54: =T54/Z54 -> 0.25 | AB54: =INDEX('[9]Service List'!$K:$K,MATCH(A54,'[9]Service List'!$F:$F,0)) -> 1265 | AC54: =INDEX('[5]Combined Bill Code List'!$P:$P,MATCH(A54,'[5]Combined Bill Code List'!$F:$F,0)) -> 0 | AD54: HCS | AE54: 1 | AF54: 0 | AG54: =ROUND(INDEX('All Trends'!D:D,MATCH($AD54,'All Trends'!$C:$C,0)),4) -> 0.9927 | AH54: =ROUND(INDEX('All Trends'!E:E,MATCH($AD54,'All Trends'!$C:$C,0)),4) -> 1.0091 | AI54: =ROUND(INDEX('All Trends'!F:F,MATCH($AD54,'All Trends'!$C:$C,0)),4) -> 1.0519 | AJ54: =ROUND(INDEX('All Trends'!G:G,MATCH($AD54,'All Trends'!$C:$C,0)),4) -> 1.0519 | AK54: =ROUND(INDEX('All Trends'!H:H,MATCH($AD54,'All Trends'!$C:$C,0)),4) -> 1.0519 | AL54: No | AM54: =IF(C54="Yes",ROUND(T54*N54*AI54,2),0) -> 988.45 | AN54: =IF(C54="Yes",ROUND(T54*N54*AJ54,2),0) -> 988.45 | AO54: =IF(C54="Yes",ROUND((W54*N54*AI54),2),0) -> 0 | AP54: =IF(C54="Yes",IF($AL54="No",ROUND(($AO54*($AY$2+$AF54)),2),ROUND($AO54,2)),0) -> 0 | AQ54: =IF(C54="Yes",ROUND((W54*N54*AJ54),2),0) -> 0 | AR54: =IF(C54="Yes",IF($AL54="No",ROUND(($AQ54*($AZ$2+$AF54)),2),ROUND($AQ54,2)),0) -> 0
A55: 2111XVM1092 | B55: 2111XVM1092 | C55: Yes | D55: No | E55: HCS | F55: Out of Home Respite | G55: =INDEX('[4]RT Description to Bill Matix'!$D:$D,MATCH(A55,'[4]RT Description to Bill Matix'!$M:$M,0)) -> CDS Out-of-Home Respite | H55: HOURLY RESPITE LOC 8 IN-CAMP (CDS) | I55: Yes | J55: {=INDEX('Rate Table Service Desc XWalk'!F:F,MATCH(1,(G55='Rate Table Service Desc XWalk'!B:B)*(E55='Rate Table Service Desc XWalk'!A:A),0))} -> 3-5-139 | K55: =INDEX('[5]Combined Bill Code List'!$A:$A,MATCH(A55,'[5]Combined Bill Code List'!$F:$F,0)) -> 1915(c) waiver | L55: =INDEX('[6]Rate History'!$P:$P,MATCH(A55,'[6]Rate History'!$F:$F,0)) -> 1 hour | M55: =INDEX('[7]PDF DB Service Pivot'!$C:$C,MATCH(B55,'[7]PDF DB Service Pivot'!$B:$B,0)) -> 1073.4 | N55: =IF(ISNUMBER(FIND("ISS",F55)),IF(I55="Yes",((M55/Q55)/6)*12,(M55/6)*12),IF(AND(I55="Yes",M55=O55),M55/Q55,M55)) -> 60 | O55: =INDEX('[7]PDF DB Service Pivot'!$D:$D,MATCH(B55,'[7]PDF DB Service Pivot'!$B:$B,0)) -> 1073.4 | P55: 45170 | Q55: 17.89 | R55: 11.77 | S55: =_xlfn.IFNA(R55/Q55,"") -> 0.65790945 | T55: 1 | U55: =ROUND(V55/Z55,2) -> 0 | V55: {=_xlfn.IFS('Fiscal by Program'!$B$7<10.61,0,'Fiscal by Program'!$B$7>10.6,(ROUND('Fiscal by Program'!$B$7*(1+IF(D55="Yes",'Fiscal by Program'!$B$9,'Fiscal by Program'!$B$8))*T55,2)))} -> 0 | W55: =IF(V55-R55<0,0,V55-R55) -> 0 | X55: =ROUND((R55/(1+IF(D55="Yes",'Fiscal by Program'!$B$9,'Fiscal by Program'!$B$8))),2)+0.01 -> 10.64 | Y55: =Q55+W55 -> 17.89 | Z55: 4 | AA55: =T55/Z55 -> 0.25 | AB55: =INDEX('[9]Service List'!$K:$K,MATCH(A55,'[9]Service List'!$F:$F,0)) -> 1266 | AC55: =INDEX('[5]Combined Bill Code List'!$P:$P,MATCH(A55,'[5]Combined Bill Code List'!$F:$F,0)) -> 0 | AD55: HCS | AE55: 1 | AF55: 0 | AG55: =ROUND(INDEX('All Trends'!D:D,MATCH($AD55,'All Trends'!$C:$C,0)),4) -> 0.9927 | AH55: =ROUND(INDEX('All Trends'!E:E,MATCH($AD55,'All Trends'!$C:$C,0)),4) -> 1.0091 | AI55: =ROUND(INDEX('All Trends'!F:F,MATCH($AD55,'All Trends'!$C:$C,0)),4) -> 1.0519 | AJ55: =ROUND(INDEX('All Trends'!G:G,MATCH($AD55,'All Trends'!$C:$C,0)),4) -> 1.0519 | AK55: =ROUND(INDEX('All Trends'!H:H,MATCH($AD55,'All Trends'!$C:$C,0)),4) -> 1.0519 | AL55: No | AM55: =IF(C55="Yes",ROUND(T55*N55*AI55,2),0) -> 63.11 | AN55: =IF(C55="Yes",ROUND(T55*N55*AJ55,2),0) -> 63.11 | AO55: =IF(C55="Yes",ROUND((W55*N55*AI55),2),0) -> 0 | AP55: =IF(C55="Yes",IF($AL55="No",ROUND(($AO55*($AY$2+$AF55)),2),ROUND($AO55,2)),0) -> 0 | AQ55: =IF(C55="Yes",ROUND((W55*N55*AJ55),2),0) -> 0 | AR55: =IF(C55="Yes",IF($AL55="No",ROUND(($AQ55*($AZ$2+$AF55)),2),ROUND($AQ55,2)),0) -> 0
A56: 2123M0977 | B56: 2123M0977 | C56: Yes | D56: No | E56: HCS | F56: ISS | G56: =INDEX('[4]RT Description to Bill Matix'!$D:$D,MATCH(A56,'[4]RT Description to Bill Matix'!$M:$M,0)) -> Individualized Skills and Socialization LON 1 - On-Site | H56: Individualized Skills and Socialization (ISS) LON 1 On-Site | J56: 3-1-45 | K56: =INDEX('[5]Combined Bill Code List'!$A:$A,MATCH(A56,'[5]Combined Bill Code List'!$F:$F,0)) -> 1915(c) waiver | L56: =INDEX('[6]Rate History'!$P:$P,MATCH(A56,'[6]Rate History'!$F:$F,0)) -> 1 hour | M56: =INDEX('[7]PDF DB Service Pivot'!$C:$C,MATCH(B56,'[7]PDF DB Service Pivot'!$B:$B,0)) -> 1427421.5 | N56: =IF(ISNUMBER(FIND("ISS",F56)),IF(I56="Yes",((M56/Q56)/6)*12,(M56/6)*12),IF(AND(I56="Yes",M56=O56),M56/Q56,M56)) -> 2854843 | O56: =INDEX('[7]PDF DB Service Pivot'!$D:$D,MATCH(B56,'[7]PDF DB Service Pivot'!$B:$B,0)) -> 9335574.6 | P56: 44927 | Q56: 6.54 | R56: 2.05 | S56: =_xlfn.IFNA(R56/Q56,"") -> 0.31345566 | T56: 0.14 | U56: =ROUND(V56/Z56,2) -> 0 | V56: {=_xlfn.IFS('Fiscal by Program'!$B$7<10.61,0,'Fiscal by Program'!$B$7>10.6,(ROUND('Fiscal by Program'!$B$7*(1+IF(D56="Yes",'Fiscal by Program'!$B$9,'Fiscal by Program'!$B$8))*T56,2)))} -> 0 | W56: =IF(V56-R56<0,0,V56-R56) -> 0 | X56: =ROUND((R56/(1+IF(D56="Yes",'Fiscal by Program'!$B$9,'Fiscal by Program'!$B$8))),2)+0.01 -> 1.86 | Y56: =Q56+W56 -> 6.54 | Z56: 4 | AA56: =T56/Z56 -> 0.035 | AB56: =INDEX('[9]Service List'!$K:$K,MATCH(A56,'[9]Service List'!$F:$F,0)) -> 238 | AC56: =INDEX('[5]Combined Bill Code List'!$P:$P,MATCH(A56,'[5]Combined Bill Code List'!$F:$F,0)) -> 0 | AD56: HCS | AE56: 1 | AF56: 0 | AG56: =ROUND(INDEX('All Trends'!D:D,MATCH($AD56,'All Trends'!$C:$C,0)),4) -> 0.9927 | AH56: =ROUND(INDEX('All Trends'!E:E,MATCH($AD56,'All Trends'!$C:$C,0)),4) -> 1.0091 | AI56: =ROUND(INDEX('All Trends'!F:F,MATCH($AD56,'All Trends'!$C:$C,0)),4) -> 1.0519 | AJ56: =ROUND(INDEX('All Trends'!G:G,MATCH($AD56,'All Trends'!$C:$C,0)),4) -> 1.0519 | AK56: =ROUND(INDEX('All Trends'!H:H,MATCH($AD56,'All Trends'!$C:$C,0)),4) -> 1.0519 | AL56: No | AM56: =IF(C56="Yes",ROUND(T56*N56*AI56,2),0) -> 420421.31 | AN56: =IF(C56="Yes",ROUND(T56*N56*AJ56,2),0) -> 420421.31 | AO56: =IF(C56="Yes",ROUND((W56*N56*AI56),2),0) -> 0 | AP56: =IF(C56="Yes",IF($AL56="No",ROUND(($AO56*($AY$2+$AF56)),2),ROUND($AO56,2)),0) -> 0 | AQ56: =IF(C56="Yes",ROUND((W56*N56*AJ56),2),0) -> 0 | AR56: =IF(C56="Yes",IF($AL56="No",ROUND(($AQ56*($AZ$2+$AF56)),2),ROUND($AQ56,2)),0) -> 0
A57: 2123M0978 | B57: 2123M0978 | C57: Yes | D57: No | E57: HCS | F57: ISS | G57: =INDEX('[4]RT Description to Bill Matix'!$D:$D,MATCH(A57,'[4]RT Description to Bill Matix'!$M:$M,0)) -> Individualized Skills and Socialization LON 1 - Off-Site (incl. Enhanced) | H57: Individualized Skills and Socialization (ISS) LON 1 Off-Site | J57: 3-1-45 | K57: =INDEX('[5]Combined Bill Code List'!$A:$A,MATCH(A57,'[5]Combined Bill Code List'!$F:$F,0)) -> 1915(c) waiver | L57: =INDEX('[6]Rate History'!$P:$P,MATCH(A57,'[6]Rate History'!$F:$F,0)) -> 1 hour | M57: =INDEX('[7]PDF DB Service Pivot'!$C:$C,MATCH(B57,'[7]PDF DB Service Pivot'!$B:$B,0)) -> 163325.5 | N57: =IF(ISNUMBER(FIND("ISS",F57)),IF(I57="Yes",((M57/Q57)/6)*12,(M57/6)*12),IF(AND(I57="Yes",M57=O57),M57/Q57,M57)) -> 326651 | O57: =INDEX('[7]PDF DB Service Pivot'!$D:$D,MATCH(B57,'[7]PDF DB Service Pivot'!$B:$B,0)) -> 1543476.7 | P57: 44927 | Q57: 9.45 | R57: 1.76 | S57: =_xlfn.IFNA(R57/Q57,"") -> 0.18624339 | T57: 0.13 | U57: =ROUND(V57/Z57,2) -> 0 | V57: {=_xlfn.IFS('Fiscal by Program'!$B$7<10.61,0,'Fiscal by Program'!$B$7>10.6,(ROUND('Fiscal by Program'!$B$7*(1+IF(D57="Yes",'Fiscal by Program'!$B$9,'Fiscal by Program'!$B$8))*T57,2)))} -> 0 | W57: =IF(V57-R57<0,0,V57-R57) -> 0 | X57: =ROUND((R57/(1+IF(D57="Yes",'Fiscal by Program'!$B$9,'Fiscal by Program'!$B$8))),2)+0.01 -> 1.6 | Y57: =Q57+W57 -> 9.45 | Z57: 4 | AA57: =T57/Z57 -> 0.0325 | AB57: =INDEX('[9]Service List'!$K:$K,MATCH(A57,'[9]Service List'!$F:$F,0)) -> 239 | AC57: =INDEX('[5]Combined Bill Code List'!$P:$P,MATCH(A57,'[5]Combined Bill Code List'!$F:$F,0)) -> 0 | AD57: HCS | AE57: 1 | AF57: 0 | AG57: =ROUND(INDEX('All Trends'!D:D,MATCH($AD57,'All Trends'!$C:$C,0)),4) -> 0.9927 | AH57: =ROUND(INDEX('All Trends'!E:E,MATCH($AD57,'All Trends'!$C:$C,0)),4) -> 1.0091 | AI57: =ROUND(INDEX('All Trends'!F:F,MATCH($AD57,'All Trends'!$C:$C,0)),4) -> 1.0519 | AJ57: =ROUND(INDEX('All Trends'!G:G,MATCH($AD57,'All Trends'!$C:$C,0)),4) -> 1.0519 | AK57: =ROUND(INDEX('All Trends'!H:H,MATCH($AD57,'All Trends'!$C:$C,0)),4) -> 1.0519 | AL57: No | AM57: =IF(C57="Yes",ROUND(T57*N57*AI57,2),0) -> 44668.54 | AN57: =IF(C57="Yes",ROUND(T57*N57*AJ57,2),0) -> 44668.54 | AO57: =IF(C57="Yes",ROUND((W57*N57*AI57),2),0) -> 0 | AP57: =IF(C57="Yes",IF($AL57="No",ROUND(($AO57*($AY$2+$AF57)),2),ROUND($AO57,2)),0) -> 0 | AQ57: =IF(C57="Yes",ROUND((W57*N57*AJ57),2),0) -> 0 | AR57: =IF(C57="Yes",IF($AL57="No",ROUND(($AQ57*($AZ$2+$AF57)),2),ROUND($AQ57,2)),0) -> 0
